Workbook
Name IndustrySector: 'Industry List'!$B$3:$B$110
Name NonUKCountry: 'Country List'!$E$4:$E$239

Sheet Front Page
A1: Office for National Statistics: Front page
B3: 2021
B4: l Notice is given under section 1 of the Statistics of Trade Act 1947.
B5: l If you do not complete and return this questionnaire, penalties may be incurred (under section 4 of the Statistics of Trade Act 1947).
B6: l All the information you provide is kept strictly confidential. It is illegal for us to reveal your data or identify your business to unauthorised persons.
B8: Please read this page and the 'General Instructions' tab before answering any questions, as they contain useful information on how best to complete this questionnaire. The 'Help' tab contains question specific information which can be consulted if further explanation or detail is required.
B10: Purpose of this Survey
B11: The purpose of this survey is to collect data on assets and liabilities of foreign parent companies in their UK affiliates and branches and the investment positions and transactions related to those assets and liabilities. Data from this survey is used to measure earnings, transactions and levels of investment by immediate foreign parent companies in their UK affiliates.
B14: Your data will contribute to an essential measurement of the UK's Balance of Payments. Details on the publication of this data can be found at www.statistics.gov.uk. For further information regarding Foreign Direct Investment (FDI), please refer to the Organisation for Economic Cooperation and Development (OECD) Benchmark Definition of FDI (fourth Edition).
B18: Definition of UK
B19: The UK includes England, Scotland, Wales and Northern Ireland but excludes the Channel Islands and the Isle of Man. For purposes of oil and mineral exploration and extraction the UK includes the UK continental shelf.
B21: Exclude: Data relating only to UK parents of the UK affiliate company.
B23: What ONS requires:
B24: - Where there is more than one UK-resident company or branch within the enterprise group, you are asked to complete the questionnaire on behalf of the entire group of UK companies.
... B44: * This spreadsheet must be uploaded to SDC on completion *

Sheet General Instructions
B1: Advice on completing the Questionnaire
B3: You should complete this questionnaire if you are:
B4: - an independent UK company, or
B5: - the senior company in a group of UK companies, or
B6: - a holding company for one or more UK companies, or
B7: - a branch of a foreign company or foreign Head Office
B8: and
B9: - a foreign company owns 10% or more of your equity capital.
B11: We require data for:
B12: - your company
B13: - any immediate UK or foreign affiliate or branch of your UK company
B14: - any fellow enterprise with outstanding intercompany or branch head balances
... B25: This questionnaire is split into the following sections:
B27: Section | C27: Description
B28: Contact details | C28: -
B29: Section A | C29: Reporting Period and Company Share Status
B30: Section B | C30: Business Structure
B31: Section C | C31: Immediate Foreign Parent Company, Head Office or Fellow Enterprise Details
B32: Section D | C32: Earnings & Dividends
B33: Section E | C33: Quoted Equity Capital Transactions and Balance Sheet
B34: Section F | C34: Unquoted Equity Capital Transactions and Balance Sheet
B35: Section G | C35: Preference Shares and Debt Attributable to the Immediate Foreign Parent Company
B36: Section H | C36: Balance Sheet Intercompany Loans and Current Account
B37: Section I | C37: Branch Earnings, Assets and Liabilities
B38: Section J | C38: Re-invested / Retained earnings
... B40: Section L | C40: Comments
B42: Please note, changes have been made to the questionnaire from the Annual 2020 reporting period.
B44: New questions have been added to the following sections:
B45: - Section D
B46: - Section E
B47: - Section F
B49: We have also added the following new sections:
B50: - Section J
B51: - Section K
B53: The fundamental FDI concept is of a chain of investment leading away from a single investor.
B54: This can be in either or both directions i.e. inward and/or outward. The basic FDI relationship links are :
B55: FDI Relationship | C55: Share holding with voting rights equal to or greater than | D55: Share holding with voting rights equal to or less than
B57: Affiliate | C57: 0.1 | D57: 1
B58: Associate | C58: 0.1 | D58: 0.5
B59: Subsidiary | C59: 0.501 | D59: 1
B61: FDI Relationship links | C61: Parent to affiliate | D61: Level 1 only
C62: Parent to branch | D62: Level 1 only
C63: Subsidiary to subsidiary | D63: Any subsequent level
C64: Subsidiary to associate | D64: Any subsequent level
C65: Associate to subsidiary | D65: Any subsequent level
B66: Non-FDI Relationship links | C66: Associate to associate | D66: Any subsequent level
B68: Consolidated links apply until there are no further subsidiaries in the chain or the 'associate to associate' link occurs.
B70: The concept of consolidation, as in ‘consolidated profit’, refers to the grouping together of items within a single
B71: industrial/geographical unit, as defined under the Fully Consolidated System described below.
B73: The diagram below demonstrates a simple flow of direct investment, showing both inward and outward directions
B74: involving a UK company.
B105: The diagram below and the corresponding text demonstrate inward investment links.
B106: This is the Fully Consolidated System.
B132: A is an immediate parent of the UK affiliate company, with 60% ownership of its UK affiliate.
B134: B is an immediate parent of its affiliate company A and therefore a parent of the UK affiliate company, with 33%
B135: (55% x 60%) ownership. It is not an ultimate parent because it, in turn, is an associate of company C.
B137: C is an immediate parent because of its associate company B, an ultimate parent of A and therefore an ultimate
B138: parent of the UK affiliate company, even though only 4% (12% x 33%) of the UK affiliate's capital is indirectly
... B198: Help and advice is attached to many of the questions in the form of pop up information which appears when you hover the mouse over the question box. Hover your mouse over the example question below to see what we mean.
B199: 22 1322 | C199: What was the value of your tax refunds?
B201: Answering the questions in sequence
B202: When you start to complete the questionnaire you will notice that nearly all of the cells to fill in are greyed out. This is to allow you to navigate the questionnaire more easily. You need to fill in the questions in order, beginning with the contact information. As you answer each question it unlocks following questions.
B206: It is important to note that terms referred to in this questionnaire may differ to accountancy standard terms. This terms are defined throughout the questionnaire to assist with completion of this survey.
B209: Note on names
B210: To help with our data processing, it will not be possible to include the following characters in name fields:
C211: ,
C212: |
C213: ,

Sheet Questionnaire
A1: 062:0105 | B1: Annual Inward Foreign Direct Investment Survey | D1: 2021 | E1: Report monetary figures to the nearest £0.1 million
C2: Please begin by inserting your contact details
C3: Contact details
C4: Please insert the details of the person we should contact if we have any queries regarding the figures returned on this questionnaire.
B5: Company* | C5: Company A
A6: 9020 | B6: Contact* | C6: Colin McColin
A7: 9030 | B7: Tel. No* | C7: 0111 1111111
A8: 9040 | B8: Fax
A9: 9050 | B9: E-Mail* | C9: colin.mccolin@doogle.com
B10: Date
B11: Website
C12: You must complete all entries indicated by a * above, before continuing
C13: Section A - Reporting Period and Company Share Status
C14: Data should be provided from your own accounting systems.
C15: Please report for the period 01/01/2021 to 31/12/2021
A16: 0411 | B16: 1 | C16: If you are unable to report figures for the above period, please give the start date for the reporting period which you are supplying data for. Please use the format dd/mm/yyyy.
A17: 0412 | C17: Please give the end date for the reporting period which you are supplying data for. Please use the format dd/mm/yyyy.
A18: 0421 | B18: 2 | C18: What is the year(s) of your annual accounting period for your published statutory accounts? (Please select from the drop down) | D18: 2021
A19: 0315 | B19: 3 | C19: Are the shares of the UK company quoted on the London Stock Exchange? (Please select from the drop down) | D19: No (unquoted affiliate)
C21: Section B - Business Structure
C22: For this section of the questionnaire you are being asked questions around ownership of companies and therefore we are asking you to provide figures as a percentage of voting power. From question 16 onwards, we move away from questions on voting power and you will be asked to answer questions with regards to voting share capital. (Voting share capital refers directly to the share equity in a company.)
C23: Ultimate Parent Company
C24: The ultimate parent company is the one that is at the top of the ownership chain, i.e. not controlled by any other entity.
C25: If your immediate foreign parent company is also your ultimate parent company, please provide their details for both the ‘ultimate parent company’ questions, and the ‘immediate foreign parent company’ questions.
A26: 0218 | B26: 4 | C26: What is the legal name of your ultimate parent company? | D26: Acme Ltd
A27: 0219 | B27: 5 | C27: What is the country of residence of your ultimate parent company? (Please select from the drop down) | D27: CHRISTMAS ISLAND
A28: 0228 | B28: 6 | C28: What is the primary industry sector for your ultimate parent company? (Please select from the drop down) | D28: Forestry & logging
A29: 3733 | B29: 7 | C29: What percentage of the UK affiliate company's voting power is held by the ultimate parent company? | D29: 100
C30: Voting Power Generally, ordinary shares provide voting power (the measure of control of a company). While voting power is often obtained through the purchase of equity, it is possible to have voting power that is not the same proportion as equity ownership. This is mainly the case where there are different classes of shares such as 'A' and 'B' class shares, where A may have a higher weight of voting power (control) than the B class of shares. It is also possible to obtain voting power without purchasing equity (for example through repurchase agreements). Note: for a branch voting power will automatically be 100%.
C31: Immediate Foreign Affiliate(s) Affiliate is used as an umbrella term covering both subsidiaries (where the investor holds more than 50% of the voting power) and associates (where the investor holds between 10% and 50%). An immediate foreign affiliate company is the first foreign (non-UK) affiliate in which your company holds at least 10% of the voting power. Your company is a foreign affiliate if a foreign company holds at least 10% of your voting power.
A32: 0231 | B32: 8 | C32: In how many immediate foreign affiliate companies (outward investment) does the UK affiliate company directly or indirectly invest (with a shareholding with a voting power of 10% or more)? | D32: 10
C33: Immediate Foreign Parent(s)
C34: An immediate foreign parent is the first foreign (i.e. non-UK) business which holds 10% or more voting power within your company. It is possible for there to be more than one immediate foreign parent company.
A35: 0232 | B35: 9 | C35: How many immediate foreign parent companies have holdings of 10% or more voting power within your company? | D35: 1
C36: The remainder of this questionnaire asks you to provide details of your immediate foreign parent company or head office, or a fellow enterprise. If you have more than one immediate foreign parent company, or fellow enterprise relationship, a separate column must be completed for each of these entities.
C37: Section C - Immediate Foreign Parent Company, Head Office or Fellow Enterprise Details | D37: 1 | E37: 2 | F37: 3 | G37: 4 | H37: 5 | I37: 6 | J37: 7 | K37: 8 | L37: 9 | M37: 10 | N37: 11 | O37: 12 | P37: 13 | Q37: 14 | R37: 15 | S37: 16 | T37: 17 | U37: 18 | V37: 19 | W37: 20 | X37: 21 | Y37: 22 | Z37: 23 | AA37: 24 | AB37: 25 | AC37: 26 | AD37: 27 | AE37: 28 | AF37: 29 | AG37: 30 | AH37: 31 | AI37: 32 | AJ37: 33 | AK37: 34 | AL37: 35 | AM37: 36 | AN37: 37 | AO37: 38 | AP37: 39 | AQ37: 40 | AR37: 41 | AS37: 42 | AT37: 43 | AU37: 44 | AV37: 45 | AW37: 46 | AX37: 47 | AY37: 48 | AZ37: 49 | BA37: 50 | BB37: 51 | BC37: 52 | BD37: 53 | BE37: 54 | BF37: 55 | BG37: 56 | BH37: 57 | BI37: 58 | BJ37: 59 | BK37: 60 | BL37: 61 | BM37: 62 | BN37: 63 | BO37: 64 | BP37: 65 | BQ37: 66 | BR37: 67 | BS37: 68 | BT37: 69 | BU37: 70 | BV37: 71 | BW37: 72 | BX37: 73 | BY37: 74 | BZ37: 75 | CA37: 76 | CB37: 77 | CC37: 78 | CD37: 79 | CE37: 80 | CF37: 81 | CG37: 82 | CH37: 83 | CI37: 84 | CJ37: 85 | CK37: 86 | CL37: 87 | CM37: 88 | CN37: 89 | CO37: 90 | CP37: 91 | CQ37: 92 | CR37: 93 | CS37: 94 | CT37: 95 | CU37: 96 | CV37: 97 | CW37: 98 | CX37: 99 | CY37: 100 | CZ37: 101 | DA37: 102 | DB37: 103 | DC37: 104 | DD37: 105 | DE37: 106 | DF37: 107 | DG37: 108 | DH37: 109 | DI37: 110 | DJ37: 111 | DK37: 112 | DL37: 113 | DM37: 114 | DN37: 115 | DO37: 116 | DP37: 117 | DQ37: 118 | DR37: 119 | DS37: 120 | DT37: 121 | DU37: 122 | DV37: 123 | DW37: 124 | DX37: 125 | DY37: 126 | DZ37: 127 | EA37: 128 | EB37: 129 | EC37: 130 | ED37: 131 | EE37: 132 | EF37: 133 | EG37: 134 | EH37: 135 | EI37: 136 | EJ37: 137 | EK37: 138 | EL37: 139 | EM37: 140 | EN37: 141 | EO37: 142 | EP37: 143 | EQ37: 144 | ER37: 145 | ES37: 146 | ET37: 147 | EU37: 148 | EV37: 149 | EW37: 150 | EX37: 151 | EY37: 152 | EZ37: 153 | FA37: 154 | FB37: 155 | FC37: 156 | FD37: 157 | FE37: 158 | FF37: 159 | FG37: 160 | FH37: 161 | FI37: 162 | FJ37: 163 | FK37: 164 | FL37: 165 | FM37: 166 | FN37: 167 | FO37: 168 | FP37: 169 | FQ37: 170 | FR37: 171 | FS37: 172 | FT37: 173 | FU37: 174 | FV37: 175 | FW37: 176 | FX37: 177 | FY37: 178 | FZ37: 179 | GA37: 180 | GB37: 181 | GC37: 182 | GD37: 183 | GE37: 184 | GF37: 185 | GG37: 186 | GH37: 187 | GI37: 188 | GJ37: 189 | GK37: 190 | GL37: 191 | GM37: 192 | GN37: 193 | GO37: 194 | GP37: 195 | GQ37: 196 | GR37: 197 | GS37: 198 | GT37: 199 | GU37: 200 | GV37: 201 | GW37: 202 | GX37: 203 | GY37: 204 | GZ37: 205 | HA37: 206 | HB37: 207 | HC37: 208 | HD37: 209 | HE37: 210 | HF37: 211 | HG37: 212 | HH37: 213 | HI37: 214 | HJ37: 215 | HK37: 216 | HL37: 217 | HM37: 218 | HN37: 219 | HO37: 220 | HP37: 221 | HQ37: 222 | HR37: 223 | HS37: 224 | HT37: 225 | HU37: 226 | HV37: 227 | HW37: 228 | HX37: 229 | HY37: 230 | HZ37: 231 | IA37: 232 | IB37: 233 | IC37: 234 | ID37: 235 | IE37: 236 | IF37: 237 | IG37: 238 | IH37: 239 | II37: 240 | IJ37: 241 | IK37: 242 | IL37: 243 | IM37: 244 | IN37: 245 | IO37: 246 | IP37: 247 | IQ37: 248 | IR37: 249 | IS37: 250
A38: 0211 | B38: 10 | C38: What is the legal name of your immediate foreign parent company, head office or fellow enterprise? | D38: Parent Company A
A39: 0601 | B39: 11 | C39: Is the foreign entity named in question 10 an immediate foreign parent, head office or a fellow enterprise of the UK company or branch? (Please select from the drop down) | D39: Foreign Parent
A40: 0505 | B40: 12 | C40: Is your immediate foreign parent company, head office or fellow enterprise a type of holding company specifically set up for passing investments through its country of residence rather than being the primary destination of such investment? (Please select from the drop down) | D40: Yes
A41: 0212 | B41: 13 | C41: What is the country of residence of your immediate foreign parent company, head office or fellow enterprise? (Please select from the drop down) | D41: CANADA
A42: 0213 | B42: 14 | C42: What is the primary industry sector of your immediate foreign parent company, head office or fellow enterprise? (Please select from the drop down) | D42: Financial holding companies only
C43: Voting Power See previous definition above.
A44: 3734 | B44: 15 | C44: What percentage of the UK affiliate company's voting power is held by your immediate foreign parent company? (If you are a Fellow Enterprise leave blank) | D44: 100
B45: NOTE: | C45: The questions on business structure have now been completed. For the remainder of the questionnaire please answer questions with regard to voting share capital. Voting share capital refers directly to the share equity in a company regardless of the class of the share. This differs from Voting Power (asked for earlier in the questionnaire), which is looking at the measure of control of a company through the voting power held via different classes of shares such as 'A' and 'B' class shares, which have different weighting of voting power.
A46: 0214 | B46: 16 | C46: What percentage of the UK affiliates company's voting share capital is held by your immediate foreign parent company? (If you are a Fellow Enterprise leave blank) | D46: 100
A47: 0602 | B47: 17 | C47: Is the UK entity completing this questionnaire, an affiliate company, fellow enterprise or a branch? (Please select from the drop down) | D47: Affiliate
D48: =IF(D47="Branch", "Go to Section I", IF(D47="Fellow Enterprise", "Go to Section H", "")) | E48: =IF(E47="Branch", "Go to Section I", IF(E47="Fellow Enterprise", "Go to Section H", "")) | F48: =IF(F47="Branch", "Go to Section I", IF(F47="Fellow Enterprise", "Go to Section H", "")) | G48: =IF(G47="Branch", "Go to Section I", IF(G47="Fellow Enterprise", "Go to Section H", "")) | H48: =IF(H47="Branch", "Go to Section I", IF(H47="Fellow Enterprise", "Go to Section H", "")) | I48: =IF(I47="Branch", "Go to Section I", IF(I47="Fellow Enterprise", "Go to Section H", "")) | J48: =IF(J47="Branch", "Go to Section I", IF(J47="Fellow Enterprise", "Go to Section H", "")) | K48: =IF(K47="Branch", "Go to Section I", IF(K47="Fellow Enterprise", "Go to Section H", "")) | ... IS48: =IF(IS47="Branch", "Go to Section I", IF(IS47="Fellow Enterprise", "Go to Section H", ""))
C49: Section D - Earnings and Dividends
C50: Profits and Losses made by the UK Affiliate Company or group of companies
C51: All monetary figures must be reported to the nearest £0.1 million.
A52: 1011 | B52: 18.a | C52: What was the value of your immediate foreign parent's share of the UK affiliate company's consolidated profit?
B53: 18.a.i | C53: Of the value reported for question 18.a, how much was attributed to each of the following regions:
A54: 4111 | C54: North East (England)
A55: 4112 | C55: North West (England)
A56: 4113 | C56: Yorkshire and The Humber (England)
A57: 4114 | C57: East Midlands (England)
A58: 4115 | C58: West Midlands (England)
A59: 4116 | C59: East of England (England)
A60: 4117 | C60: London (England)
A61: 4118 | C61: South East (England)
A62: 4119 | C62: South West (England)
A63: 4130 | C63: Scotland
A64: 4140 | C64: Wales
A65: 4150 | C65: Northern Ireland
A66: 4160 | C66: Value that cannot be attributed to a region
A67: 4161 | B67: 18.a.ii | C67: If you provided a figure for "Value that cannot be attributed to a region" in 18.a.i, please use this box to explain why.
A68: 1012 | B68: 18.b | C68: What was the value of your immediate foreign parent's share of the UK affiliate company's consolidated loss? | D68: 10.9
A69: 1311 | B69: 19 | C69: What was the value of withholding taxes deducted from payments made to your immediate foreign parent company and its foreign affiliate companies by the UK affiliate company? | D69: 0
A70: 1321 | B70: 20 | C70: What was the value of your tax credits? | D70: 0
A71: 1322 | B71: 21 | C71: What was the value of your tax refunds? | D71: 0
A72: 2019 | B72: 22 | C72: What was the value of ordinary dividends payable to your immediate foreign parent in this reporting period? | D72: 6914.4
A73: 2039 | B73: 23.a | C73: What was the value of exceptional dividends payable to your immediate foreign parent in this reporting period? | D73: 0
A74: 3725 | B74: 23.b | C74: What were the reasons for the exceptional dividends included in Question 23.a?
A75: 0605 | B75: 24 | C75: At the end of the reporting period, are the shares that you are reporting for quoted or unquoted? (Please select from the drop down) | D75: Unquoted
D76: =IF(D75="Unquoted", "Go to Section F", "") -> Go to Section F | E76: =IF(E75="Unquoted", "Go to Section F", "") | F76: =IF(F75="Unquoted", "Go to Section F", "") | G76: =IF(G75="Unquoted", "Go to Section F", "") | H76: =IF(H75="Unquoted", "Go to Section F", "") | I76: =IF(I75="Unquoted", "Go to Section F", "") | J76: =IF(J75="Unquoted", "Go to Section F", "") | K76: =IF(K75="Unquoted", "Go to Section F", "") | ... IS76: =IF(IS75="Unquoted", "Go to Section F", "")
C77: Section E - Quoted Equity Capital Transactions and Balance Sheet All monetary figures must be reported to the nearest £0.1 million.
A78: 3191 | B78: 25 | C78: What was the value, as recorded in the UK affiliate company's balance sheet, of quoted equity capital and reserves of the UK affiliate company directly attributable to your immediate foreign parent company at the start of the reporting period? (Figure can be negative)
A79: 3726 | B79: 26 | C79: What was the market value of the immediate foreign parent's share of the UK affiliate company at the start of the reporting period?
A80: 3192 | B80: 27 | C80: What was the value, as recorded in the UK affiliate company's balance sheet, of quoted equity capital and reserves of the UK affiliate company directly attributable to your immediate foreign parent company at the end of the reporting period? (Figure can be negative)
A81: 3727 | B81: 28 | C81: What was the market value of the immediate foreign parent's share of the UK affiliate company at the end of the reporting period?
A82: 2111 | B82: 29.a | C82: What was the total value at the end of the reporting period of acquisitions of quoted equity capital by your immediate foreign parent?
B83: 29.a.i | C83: Of the value reported for question 29.a, how much was attributed to:
A84: 4201 | C84: a. Acquiring an existing asset or business
A85: 4202 | C85: b. Establishing a new business (not through merger and acquisition)
A86: 4203 | C86: c. Extension of an existing business or productive capacity
A87: 4204 | C87: d. Other financial restructuring
A88: 4205 | C88: Please use this box to explain any other restructuring from part (d):
B89: 29.a.ii | C89: Of the value reported for question 29.a, how much of the funding was sourced through:
A90: 4211 | C90: a. Direct cash from immediate overseas parent
A91: 4212 | C91: b. Intercompany loan
A92: 4213 | C92: c. Share issuance
A93: 4214 | C93: d. Other
A94: 4215 | C94: Please use this box to explain any other funding from part (d):
A95: 2112 | B95: 29.b | C95: What was the total value at the end of the reporting period of disposals of quoted equity capital by your immediate foreign parent?
B96: 29.b.i | C96: Of the value reported for question 29.b, how much was attributed to:
A97: 4221 | C97: a. Disposing of an existing asset or business
A98: 4222 | C98: b. Reduction of an existing business or productive capacity
A99: 4223 | C99: c. Other financial restructuring
A100: 4224 | C100: Please use this box to explain any other restructuring from part (c):
B101: 29.b.ii | C101: Of the value reported for question 29.b, how much of the funds were received through:
...

Sheet Help
A1: Questions | C1: Help with questions
A3: Contact details
B4: Please insert the details of the person we should contact if we have any queries regarding the figures returned on this questionnaire.
A5: Company* | C5: Company legal name. Mandatory. Don’t use ‘,’ or ‘|’.
A6: Contact* | C6: Contact name. Mandatory.
A7: Tel. No* | C7: Telephone number. Mandatory.
A8: Fax
A9: E-Mail* | C9: E-mail. Mandatory.
A10: Date
A11: Website
B13: Section A - Reporting Period
B14: Data should be provided from your own accounting systems.
B15: Please report for the period 01/01/2021 to 31/12/2021
A16: 1 | B16: If you are unable to report figures for the above period, please give the start date for the reporting period which you are supplying data for. Please use the format dd/mm/yyyy. | C16: The majority of the year you are supplying data for should be within the year we have specified. We cannot accept data relating to earlier years as such a return would distort the final Balance of Payments results.
B17: Please give the end date for the reporting period which you are supplying data for. Please use the format dd/mm/yyyy.
A18: 2 | B18: What is the year(s) of your annual accounting period for your published statutory accounts? (Please select from the drop down) | C18: The ONS use this to correlate the quarterly and annual datasets prepared from your data.
A19: 3 | B19: Are the shares of the UK company quoted on the London Stock Exchange? (Please select from the drop down) | C19: If the UK company is quoted or listed on the London Stock Exchange please select the appropriate answer from the dropdown list: 'Yes (quoted affiliate)', 'No (unquoted affiliate)' or 'N/A (branch)'.
B21: Section B - Business Structure
B22: For this section of the questionnaire you are being asked questions around ownership of companies and therefore we are asking you to provide figures as a percentage of voting power. From question 16 onwards, we move away from questions on voting power and you will be asked to answer questions with regards to voting share capital. (Voting share capital refers directly to the share equity in a company.)
B23: Ultimate Parent Company
B24: The ultimate parent company is the one that is at the top of the ownership chain,
B25: i.e. not controlled by any other entity. If your immediate foreign parent company is also your ultimate parent company, please provide their details for both the ‘ultimate parent company’ questions, and the ‘immediate foreign parent company’ questions.
A26: 4 | B26: What is the legal name of your ultimate parent company? | C26: If you have more than one ultimate parent please contact the ONS. Don’t use ‘,’ or ‘|’.
A27: 5 | B27: What is the country of residence of your ultimate parent company? (Please select from the drop down) | C27: Residence is defined in paragraph 73 of the International Monetary Fund Balance of Payments Manual 5 as follows: ‘An enterprise is said to have a centre of economic interest and to be a resident unit of a country (economic territory) when the enterprise is engaged in a significant amount of production of goods and/or services there or when the enterprise owns land or buildings located there. The enterprise must maintain at least one production establishment in the country and must plan to operate the establishment indefinitely or over a long period of time’. Please note that in this context 'production' refers to all forms of economic activity - not simply the production of goods. This country must be outside of the United Kingdom, but can include the Isle of Man, Jersey, Guernsey or any of the other Channel Islands.
A28: 6 | B28: What is the primary industry sector for your ultimate parent company? (Please select from the drop down) | C28: The primary industry sector codes are as defined in the 'UK Standard Industrial Classification of Economic Activities 2007' published by ONS. There are some subdivisions for the banking and security dealer sectors. See ONS web site for comprehensive classification list: https://www.ons.gov.uk/methodology/classificationsandstandards/ukstandardindustrialclassificationofeconomicactivities/uksic2007 If you require an SIC code, please see the resources available on the above page, including the SIC Main Volume (PDF 1,294 KB), Index (XLS 2,919 KB) and Interactive Hierarchy.
A29: 7 | B29: What percentage of the UK affiliate company's voting power is held by the ultimate parent company?
B30: Voting Power Generally, ordinary shares provide voting power (the measure of control of a company). While voting power is often obtained through the purchase of equity, it is possible to have voting power that is not the same proportion as equity ownership. This is mainly the case where there are different classes of shares such as 'A' and 'B' class shares, where A may have a higher weight of voting power (control) than the B class of shares. It is also possible to obtain voting power without purchasing equity (for example through repurchase agreements). Note: for a branch voting power will automatically be 100%.
B31: Immediate Foreign Affiliate(s) Affiliate is used as an umbrella term covering both subsidiaries (where the investor holds more than 50% of the voting power) and associates (where the investor holds between 10% and 50%). An immediate foreign affiliate company is the first foreign (non-UK) affiliate in which your company holds at least 10% of the voting power. Your company is a foreign affiliate if a foreign company holds at least 10% of your voting power.
A32: 8 | B32: In how many immediate foreign affiliate companies (outward investment) does the UK affiliate company directly or indirectly invest (with a shareholding with a voting power of 10% or more)?
B33: Immediate Foreign Parent(s)
B34: An immediate foreign parent is the first foreign (i.e. non-UK) business which holds 10% or more voting power within your company. It is possible for there to be more than one immediate foreign parent company.
A35: 9 | B35: How many immediate foreign parent companies have holdings of 10% or more voting power within your company?
B36: The remainder of this questionnaire asks you to provide details of your immediate foreign parent company or head office, or a fellow enterprise. If you have more than one immediate foreign parent company, or fellow enterprise relationship, a separate column must be completed for each of these entities.
B37: Section C - Immediate Foreign Parent Company, Head Office or Fellow Enterprise Details
A38: 10 | B38: What is the legal name of your immediate foreign parent company, head office or fellow enterprise? | C38: Company legal name. Don’t use ‘,’ or ‘|’.
A39: 11 | B39: Is the foreign entity named in question 10 an immediate foreign parent, head office or a fellow enterprise of the UK company or branch? (Please select from the drop down)
A40: 12 | B40: Is your immediate foreign parent company, head office or fellow enterprise a type of holding company specifically set up for passing investments through its country of residence rather than being the primary destination of such investment? (Please select from the drop down) | C40: In FDI terms, an overseas holding company is defined as a company set up for purposes of passing investments through the resident country rather than being the primary destination of such investment.
A41: 13 | B41: What is the country of residence of your immediate foreign parent company, head office or fellow enterprise? (Please select from the drop down) | C41: Residence is defined in paragraph 73 of the International Monetary Fund Balance of Payments Manual 5 as follows. ‘An enterprise is said to have a centre of economic interest and to be a resident unit of a country (economic territory) when the enterprise is engaged in a significant amount of production of goods and/or services there or when the enterprise owns land or buildings located there. The enterprise must maintain at least one production establishment in the country and must plan to operate the establishment indefinitely or over a long period of time’. Please note that in this context 'production' refers to all forms of economic activity - not simply the production of goods. This country must be outside of the United Kingdom, but can include the Isle of Man, Jersey, Guernsey or any of the other Channel Islands.
A42: 14 | B42: What is the primary industry sector of your immediate foreign parent company, head office or fellow enterprise? (Please select from the drop down) | C42: The primary industry sector codes are as defined in the 'UK Standard Industrial Classification of Economic Activities 2007' published by ONS. There are some subdivisions for the banking and security dealer sectors. See ONS web site for comprehensive classification list: https://www.ons.gov.uk/methodology/classificationsandstandards/ukstandardindustrialclassificationofeconomicactivities/uksic2007 If you require an SIC code, please see the resources available on the above page, including the SIC Main Volume (PDF 1,294 KB), Index (XLS 2,919 KB) and Interactive Hierarchy.
B43: Branch For FDI a branch is a permanent establishment but not a separate legal entity. Such establishments should either have a complete set of accounts or be able to compile a meaningful set of accounts, from both an economic and legal viewpoint. A branch is controlled by the 'Head Office' of the parent company.
A44: 15 | B44: What percentage of the UK affiliate company's voting power is held by your immediate foreign parent company? (If you are a Fellow Enterprise leave blank) | C44: This should be between 10% and 100%.
A45: NOTE: | B45: The questions on business structure have now been completed. For the remainder of the questionnaire please answer questions with regard to voting share capital. Voting share capital refers directly to the share equity in a company regardless of the class of the share. This differs from Voting Power (asked for earlier in the questionnaire), which is looking at the measure of control of a company through the voting power held via different classes of shares such as 'A' and 'B' class shares, which have different weighting of voting power.
A46: 16 | B46: What percentage of the UK affiliates company's voting share capital is held by your immediate foreign parent company? (If you are a Fellow Enterprise leave blank)
A47: 17 | B47: Is the UK entity completing this questionnaire, an affiliate company or a branch? (Please select from the drop down) | C47: Affiliate Affiliate is used as an umbrella term covering both subsidiaries (where the investor holds more than 50% of the voting power) and associates (where the investor holds between 10% and 50%). An immediate foreign affiliate company is the first foreign (non-UK) affiliate in which your company holds at least 10% of the voting power. Your company is a foreign affiliate if a foreign company holds at least 10% of your voting power. Foreign Fellow Enterprise A foreign fellow enterprise is a foreign company with whom you have an equity or debt relationship and share the same ultimate parent company. The ultimate parent company must have 10% or more voting power in one of the fellow enterprises. Neither fellow enterprise company owns more than 10% voting power in the other fellow enterprise. Branch For FDI a branch is a permanent establishment but not a separate legal entity. Such establishments should either have a complete set of accounts or be able to compile a meaningful set of accounts, from both an ecomonic and legal viewpoint.
C48: =IF(C47="Branch", "Go to Section I", "") | D48: =IF(D47="Branch", "Go to Section I", "") | E48: =IF(E47="Branch", "Go to Section I", "") | F48: =IF(F47="Branch", "Go to Section I", "") | G48: =IF(G47="Branch", "Go to Section I", "") | H48: =IF(H47="Branch", "Go to Section I", "") | I48: =IF(I47="Branch", "Go to Section I", "") | J48: =IF(J47="Branch", "Go to Section I", "") | ... L48: =IF(L47="Branch", "Go to Section I", "")
B49: Section D - Earnings & Dividends | C49: Include: - Interest accrued to or from this UK affiliate company. - Profits and losses after accounting for depreciation. - UK taxes charged on profits (corporation tax). - Ordinary and exceptional dividends paid, i.e. do not deduct those from reported profit or loss figures for this question (ordinary dividends should be repeated in question 22). Exclude: - Deferred taxation. - Realised and or unrealised capital increases or decreases made by the company. - Increases or decreases arising from valuation changes such as inventory write-offs. - Provisions for bad debts. - Costs of reorganisation or restructuring which have any material effect on the nature of the operation.
B50: Profits and Losses made by the UK Affiliate Company or group of companies
B51: All monetary figures must be reported to the nearest £0.1 million.
A52: 18.a | B52: What was the value of your immediate foreign parent's share of the UK affiliate company's consolidated profit? | C52: Include: - Interest accrued to or from this UK affiliate company. - Profits and losses after accounting for depreciation. - UK taxes charged on profits (corporation tax). - Ordinary and exceptional dividends paid, i.e. do not deduct those from reported profit or loss figures for this question (ordinary dividends should be repeated in question 22). Exclude: - Deferred taxation. - Realised and or unrealised capital increases or decreases made by the company. - Increases or decreases arising from valuation changes such as inventory write-offs. - Provisions for bad debts. - Costs of reorganisation or restructuring which have any material effect on the nature of the operation.
A53: 18.a.i | B53: Of the value reported for question 18a, how much was attributed to each of the following regions: | C53: ONS Economic Survey Division: Question 18.a asks for the immediate foreign parents share of the UK affiliate company’s consolidated profit. Question 18.a.i asks how the immediate foreign parents share is apportioned to the regions within the UK. For example, if the immediate UK affiliate company is based in Wales, then the whole share of the profit is attributed to Wales. If the UK affiliates are based in multiple regions, for example one in Scotland and one in London, then the share of the profit would be apportioned to these regions based on the voting share capital. The sum of the regions should equal the value in question 18.a. If it is not possible to attribute some, or all, of the data to a UK region, please assign the value to “Value that cannot be attributed to a region” and include a response to 18.a.ii to explain why this is not possible. The region breakdowns provided form Level 1 of the Nomenclature of Territorial Units for Statistics (NUTS) classification. For more information on which locations are included in each region, please see: https://www.ons.gov.uk/methodology/geography/ukgeographies/eurostat
B54: North East (England) | C54: Include: Tees Valley and Durham Northumberland and Tyne and Wear
B55: North West (England) | C55: Include: Cumbria Cheshire Greater Manchester Lancashire Merseyside
B56: Yorkshire and The Humber (England) | C56: Include: East Yorkshire and Northern Lincolnshire North Yorkshire South Yorkshire West Yorkshire
B57: East Midlands (England) | C57: Include: Derbyshire and Nottinghamshire Leicestershire, Rutland and Northamptonshire Lincolnshire
B58: West Midlands (England) | C58: Include: Herefordshire, Worcestershire and Warwickshire Shropshire and Staffordshire West Midlands
B59: East of England (England) | C59: Include: East Anglia Bedfordshire and Hertfordshire Essex
B60: London (England) | C60: Include: Inner London – West Inner London – East Outer London – East and North East Outer London – South Outer London – West and North West
B61: South East (England) | C61: Include: Berkshire, Buckinghamshire and Oxfordshire Surrey, East and West Sussex Hampshire and Isle of Wight Kent
B62: South West (England) | C62: Include: Gloucestershire, Wiltshire and Bristol/Bath area Dorset and Somerset Cornwall and Isles of Scilly Devon
B63: Scotland
B64: Wales
B65: Northern Ireland
B66: Value that cannot be attributed to a region
A67: 18.a.ii | B67: If you provided a figure for "Value that cannot be attributed to a region" in 18.a.i, please use this box to explain why. | C67: If you have entered any value into the 'Value that cannot be attributed to a region' option for 18.a.i, please use this question to explain why. If you entered 0 for 'Value that cannot be attributed to a region', then you do not need to answer this question.
A68: 18.b | B68: What was the value of your immediate foreign parent's share of the UK affiliate company's consolidated loss? | C68: Include: - Interest accrued to or from this UK affiliate company. - Profits and losses after accounting for depreciation. - UK taxes charged on profits (corporation tax). - Ordinary and exceptional dividends paid, i.e. do not deduct those from reported profit or loss figures for this question (ordinary dividends should be repeated in question 22). Exclude: - Deferred taxation. - Realised and or unrealised capital increases or decreases made by the company. - Increases or decreases arising from valuation changes such as inventory write-offs. - Provisions for bad debts. - Costs of reorganisation or restructuring which have any material effect on the nature of the operation.
A69: 19 | B69: What was the value of withholding taxes deducted from payments made to your immediate foreign parent company and its foreign affiliate companies by the UK affiliate company? | C69: Include: - Tax withheld on payments to this immediate foreign parent company or head office and foreign affiliates less tax withheld on payments from this immediate foreign parent company and foreign affiliates. Exclude: - Underlying taxes on profits (for example, corporation tax)
A70: 20 | B70: What was the value of your tax credits? | C70: These are credits that, with permission from Her Majesty's Revenue and Customs, have been paid or received direct to or from the UK company under the double taxation agreements with other countries.
A71: 21 | B71: What was the value of your tax refunds? | C71: These are refunds that, with permission from Her Majesty's Revenue and Customs, have been paid or received direct to or from the UK company under the double taxation agreements with other countries.
A72: 22 | B72: What was the value of ordinary dividends paid to your immediate foreign parent in this reporting period? | C72: Dividends - This is a payment made to the shareholders that can be paid out of the profit and loss account or the companies reserves. If the UK company received a dividend from the foreign parent this should be provided in Question 30a for quoted equity capital or 34a for unquoted equity capital. Provide the full value of the dividends paid, including withholding tax and tax credits. Exclude: Exceptional dividends
A73: 23.a | B73: What was the value of exceptional dividends paid to your immediate foreign parent in this reporting period? | C73: An exceptional dividend is a non-recurring distribution of profit which is unusually large in size or is of an unusual nature. For instance, it could be due to exceptional profit or financial restructuring of the group. Exceptional dividends may also be known as 'Super' dividends or 'Extra' dividends.
A74: 23.b | B74: What were the reasons for the exceptional dividends included in Question 23a? | C74: If not applicable, please leave blank.
A75: 24 | B75: At the end of the reporting period, are the shares that you are reporting for quoted or unquoted? (Please select from the drop down) | C75: You should answer 'Quoted' if the UK company is quoted on the London Stock Exchange. If you are reporting for shares that will be unquoted at the end of this period, but were previously quoted shares, please answer 'Unquoted', and include these figures in Section F. If you are reporting for shares that were made quoted prior to the end of this period, but were previously unquoted shares, please answer 'Quoted', and include these figures in Section E.
B77: Section E - Quoted Equity Capital Transactions and Balance Sheet All monetary figures must be reported to the nearest £0.1 million. | C77: If you are reporting for shares that will be unquoted at the end of this period, but were previously quoted shares, please include these figures in Question 32, rather than 27.
A78: 25 | B78: What was the value, as recorded in the UK affiliate company's balance sheet, of quoted equity capital and reserves of the UK affiliate company directly attributable to your immediate foreign parent company at the start of the reporting period? (Figure can be negative) | C78: This figure should equal the previous reporting period's closing balance.
A79: 26 | B79: What was the market value of the immediate foreign parent's share of the UK affiliate company at the start of the reporting period?
A80: 27 | B80: What was the value, as recorded in the UK affiliate company's balance sheet, of quoted equity capital and reserves of the UK affiliate company directly attributable to your immediate foreign parent company at the end of the reporting period? (Figure can be negative) | C80: This figure should equal the questions 25+18-19+(29a-29b)+30. Include: - Any unquoted acquisition or disposal made during this period which was subsequently made quoted by the end of this period. Exclude: - Quoted equity capital and reserves of this UK affiliate company attributable to other shareholders. - Any quoted acquisitions or disposals made during this period which was subsequently made unquoted at the end of this period.
A81: 28 | B81: What was the market value of the immediate foreign parent's share of the UK affiliate company at the end of the reporting period?
A82: 29.a | B82: What was the total value at the end of the reporting period of acquisitions of quoted equity capital by your immediate foreign parent? | C82: For Questions 29a and 29b, please report in cash or exchange values, not nominal values. Include: - Quoted shares of the UK affiliate company. - Existing and new issues of quoted shares. - Acquisitions or disposals where an immediate foreign parent company's shares are issued in exchange for the equity capital of the UK affiliate company (valued at the market value of the immediate foreign parent company's share on the day of purchase) and capital contributions from the immediate foreign parent company or associate companies. - Acquisitions or disposals arising from capitalisation of the intercompany current account balances or unlisted loans (with a corresponding reduction in the net amount due to the Foreign Parent company in Section H). - Capital and cash injections which are not for repayment and on which no interest is payable. - Assets. - Land, structures, immovable equipment that are directly owned but not already covered through ownership of an associated company. - Mobile equipment (such as ships, aircraft, gas and oil drilling rigs) that operate in the UK economy for at least one year, is recognised by the tax authorities and is not already covered through ownership of an associated company. - Manufacturing rights or securities, for example, supplied by or to this immediate foreign parent company. - Acquisitions or disposals of licences or rights to mine or explore. Exclude: - Intercompany current account. - Acquisitions or disposals funded by intercompany transfers. - Patents and trademarks. - Unquoted or preference shares.
A83: 29 a.i | B83: Of the value reported for question 29a, how much was attributed to:
B84: a. Acquiring an existing asset or business | C84: Including: - Merger and acquisition
B85: b. Establishing a new business (not through merger and acquisition)
B86: c. Extension of an existing business or productive capacity | C86: Including: - Investment on new buildings and machinery for an existing business
B87: d. Other financial restructuring | C87: Including: - Share buyback for the purposes of debt repayment or loss reduction - Cash injections, cash redemptions or share buyback for the purposes of debt repayment or loss reduction
B88: Please use this box to explain any other restructuring from part (d):
A89: 29.a.ii | B89: Of the value reported for question 29a, how much of the funding was sourced through:
B90: a. Direct cash from immediate overseas parent
B91: b. Intercompany loan
B92: c. Share issuance
B93: d. Other
B94: Please use this box to explain any other funding from part (d):
A95: 29.b | B95: What was the total value at the end of the reporting period of disposals of quoted equity capital by your immediate foreign parent?
A96: 29.b.i | B96: Of the value reported for question 29b, how much was attributed to:
B97: a. Disposing of an existing asset or business | C97: Including: - Merger and acquisition
B98: b. Reduction of an existing business or productive capacity | C98: Including: - Disinvestment on buildings and machinery for an existing business
B99: c. Other financial restructuring | C99: Including: - Share buyback for the purposes of debt repayment or loss reduction - Cash injections, cash redemptions or share buyback for the purposes of debt repayment or loss reduction.
B100: Please use this box to explain any other restructuring from part (c):
A101: 29.b.ii | B101: Of the value reported for question 29b, how much of the funds were received through:
B102: a. Direct cash to immediate overseas parent
B103: b. Intercompany loan
B104: c. Share issuance
...

Sheet Validation
A1: Validation Queries
A4: Validation queries may have occurred. Please check your responses and amend them where necessary.
A5: ERROR - data has not been entered where a blank entry is not acceptable.
A6: QUERY - data entered does not correlate with other entries and requires correction or explanation.
A7: WARNING - data entered is unusually high or low - please check your entry and confirm if correct.
A8: If the data is correct please comment on the reasons in the comments box at the bottom of the Questionnaire tab.
A9: This will avoid you being contacted for clarification.
A12: =IF(AND(Questionnaire!C5<>0, Questionnaire!C6<>0, Questionnaire!C7<>0, Questionnaire!C9<>0),"OK Contact Details","ERROR Contact Details - You have not completed all of the compulsory contact details") -> OK Contact Details | B12: =IF(LEFT(A12,2)="OK",0,IF(LEFT(A12,2)="ER",2,1)) -> 0 | C12: =IF(AND(Questionnaire!C5<>0,LEN(Questionnaire!C5)<1001, Questionnaire!C6<>0,LEN(Questionnaire!C6)<1001, Questionnaire!C7<>0,LEN(Questionnaire!C7)<1001, Questionnaire!C9<>0,LEN(Questionnaire!C9)<1001),"OK Contact Details Length","ERROR Contact Details - Too many characters in a field") -> OK Contact Details Length
A13: =IF(Questionnaire!D18=0,"ERROR Q 2 - Annual accounting period - You have not completed this question","OK Q 2") -> OK Q 2 | B13: =IF(LEFT(A13,2)="OK",0,IF(LEFT(A13,2)="ER",2,1)) -> 0
A14: =IF(Questionnaire!D19<>0=TRUE,"OK Q 3", "ERROR Q 3 - Quoted or Unquoted company - You must answer 'Yes' or 'No' to Q3") -> OK Q 3 | B14: =IF(LEFT(A14,2)=0,"OK",IF(LEFT(A14,2)="ER",2,1)) -> 1
A15: =IF(Questionnaire!D27<>0=TRUE,IF(COUNTIF('Country List'!$B$4:$B$240,Questionnaire!D27)=0,"ERROR Q 5 - This must match a country option from the drop-down list","OK Q 5"),"ERROR Q 5 - This must match a country option from the drop-down list") -> OK Q 5 | B15: =IF(LEFT(A15,2)=0,"OK",IF(LEFT(A15,2)="ER",2,1)) -> 1
A16: =IF(Questionnaire!D28<>0=TRUE,IF(COUNTIF('Industry List'!$B$3:$B$110,Questionnaire!D28)=0,"ERROR Q 6 - This must match an industry option from the drop-down list","OK Q 6"),"ERROR Q 6 - This must match an industry option from the drop-down list") -> OK Q 6 | B16: =IF(LEFT(A16,2)=0,"OK",IF(LEFT(A16,2)="ER",2,1)) -> 1
A17: =IF(ISNUMBER(Questionnaire!D32),"OK Q 8","ERROR Q 8 - Number of immediate foreign affiliates - You have not completed this question") -> OK Q 8 | B17: =IF(LEFT(A17,2)=0,"OK",IF(LEFT(A17,2)="ER",2,1)) -> 1
E18: =IF(OR(Questionnaire!G19="N/A (branch)"=TRUE,Questionnaire!G47="Branch"=TRUE),"OK Qu 3/24",IF(AND(Questionnaire!G19<>0=TRUE,Questionnaire!G75<>0=TRUE),"ERROR Qu 3/24 - Quoted or Unquoted company - You must answer 'Yes' or 'No' to Q3 and Q24", "OK Qu 3/24")) -> OK Qu 3/24
A19: =IF(ISNUMBER(Questionnaire!D35),"OK Q 9","ERROR Q 9 - Number of immediate foreign parents - You have not completed this question") -> OK Q 9 | B19: =IF(LEFT(A19,2)=0,"OK",IF(LEFT(A19,2)="ER",2,1)) -> 1
A20: =IF(LEFT(A21,2)="OK",1,IF(LEFT(A21,2)="ER",2,1)) -> 1 | B20: =IF(LEFT(B21,2)="OK",1,IF(LEFT(B21,2)="ER",2,1)) -> 1 | C20: =IF(LEFT(C21,2)="OK",1,IF(LEFT(C21,2)="ER",2,1)) -> 1 | D20: =IF(LEFT(D21,2)="OK",1,IF(LEFT(D21,2)="ER",2,1)) -> 1 | E20: =IF(LEFT(E21,2)="OK",1,IF(LEFT(E21,2)="ER",2,1)) -> 1 | F20: =IF(LEFT(F21,2)="OK",1,IF(LEFT(F21,2)="ER",2,1)) -> 1 | G20: =IF(LEFT(G21,2)="OK",1,IF(LEFT(G21,2)="ER",2,1)) -> 1 | H20: =IF(LEFT(H21,2)="OK",1,IF(LEFT(H21,2)="ER",2,1)) -> 1 | ... IP20: =IF(LEFT(IP21,2)="OK",1,IF(LEFT(IP21,2)="ER",2,1)) -> 1
A21: =IF(Questionnaire!D38>0 = TRUE, "OK Q 12", IF(OR(Questionnaire!D40="Yes",Questionnaire!D40="No"),"OK Q 12","ERROR Q 12 - You must enter 'Yes' or 'No' ")) -> OK Q 12 | B21: =IF(Questionnaire!E40<>0 = FALSE, "OK Q 12", IF(OR(Questionnaire!E40="Yes",Questionnaire!E40="No"),"OK Q 12","ERROR Q 12 - You must enter 'Yes' or 'No' ")) -> OK Q 12 | C21: =IF(Questionnaire!F40<>0 = FALSE, "OK Q 12", IF(OR(Questionnaire!F40="Yes",Questionnaire!F40="No"),"OK Q 12","ERROR Q 12 - You must enter 'Yes' or 'No' ")) -> OK Q 12 | D21: =IF(Questionnaire!G40<>0 = FALSE, "OK Q 12", IF(OR(Questionnaire!G40="Yes",Questionnaire!G40="No"),"OK Q 12","ERROR Q 12 - You must enter 'Yes' or 'No' ")) -> OK Q 12 | E21: =IF(Questionnaire!H40<>0 = FALSE, "OK Q 12", IF(OR(Questionnaire!H40="Yes",Questionnaire!H40="No"),"OK Q 12","ERROR Q 12 - You must enter 'Yes' or 'No' ")) -> OK Q 12 | F21: =IF(Questionnaire!I40<>0 = FALSE, "OK Q 12", IF(OR(Questionnaire!I40="Yes",Questionnaire!I40="No"),"OK Q 12","ERROR Q 12 - You must enter 'Yes' or 'No' ")) -> OK Q 12 | G21: =IF(Questionnaire!J40<>0 = FALSE, "OK Q 12", IF(OR(Questionnaire!J40="Yes",Questionnaire!J40="No"),"OK Q 12","ERROR Q 12 - You must enter 'Yes' or 'No' ")) -> OK Q 12 | H21: =IF(Questionnaire!K40<>0 = FALSE, "OK Q 12", IF(OR(Questionnaire!K40="Yes",Questionnaire!K40="No"),"OK Q 12","ERROR Q 12 - You must enter 'Yes' or 'No' ")) -> OK Q 12 | I21: =IF(Questionnaire!L40<>0 = FALSE, "OK Q 12", IF(OR(Questionnaire!L40="Yes",Questionnaire!L40="No"),"OK Q 12","ERROR Q 12 - You must enter 'Yes' or 'No' ")) -> OK Q 12 | ... IP21: =IF(Questionnaire!IS40<>0 = FALSE, "OK Q 12", IF(OR(Questionnaire!IS40="Yes",Questionnaire!IS40="No"),"OK Q 12","ERROR Q 12 - You must enter 'Yes' or 'No' ")) -> OK Q 12
A22: =IF(LEFT(A23,2)="OK",1,IF(LEFT(A23,2)="ER",2,1)) -> 1 | B22: =IF(LEFT(B23,2)="OK",1,IF(LEFT(B23,2)="ER",2,1)) -> 1 | C22: =IF(LEFT(C23,2)="OK",1,IF(LEFT(C23,2)="ER",2,1)) -> 1 | D22: =IF(LEFT(D23,2)="OK",1,IF(LEFT(D23,2)="ER",2,1)) -> 1 | E22: =IF(LEFT(E23,2)="OK",1,IF(LEFT(E23,2)="ER",2,1)) -> 1 | F22: =IF(LEFT(F23,2)="OK",1,IF(LEFT(F23,2)="ER",2,1)) -> 1 | G22: =IF(LEFT(G23,2)="OK",1,IF(LEFT(G23,2)="ER",2,1)) -> 1 | H22: =IF(LEFT(H23,2)="OK",1,IF(LEFT(H23,2)="ER",2,1)) -> 1 | ... IP22: =IF(LEFT(IP23,2)="OK",1,IF(LEFT(IP23,2)="ER",2,1)) -> 1
A23: =IF(Questionnaire!D41<>0 = FALSE, "OK Q 13", IF(COUNTIF('Country List'!$E$4:$E$239,Questionnaire!D41)=0,"ERROR Q 13 - This must match a country option from the drop-down list","OK Q 13")) -> OK Q 13 | B23: =IF(Questionnaire!E41<>0 = FALSE, "OK Q 13", IF(COUNTIF('Country List'!$E$4:$E$239,Questionnaire!E41)=0,"ERROR Q 13 - This must match a country option from the drop-down list","OK Q 13")) -> OK Q 13 | C23: =IF(Questionnaire!F41<>0 = FALSE, "OK Q 13", IF(COUNTIF('Country List'!$E$4:$E$239,Questionnaire!F41)=0,"ERROR Q 13 - This must match a country option from the drop-down list","OK Q 13")) -> OK Q 13 | D23: =IF(Questionnaire!G41<>0 = FALSE, "OK Q 13", IF(COUNTIF('Country List'!$E$4:$E$239,Questionnaire!G41)=0,"ERROR Q 13 - This must match a country option from the drop-down list","OK Q 13")) -> OK Q 13 | E23: =IF(Questionnaire!H41<>0 = FALSE, "OK Q 13", IF(COUNTIF('Country List'!$E$4:$E$239,Questionnaire!H41)=0,"ERROR Q 13 - This must match a country option from the drop-down list","OK Q 13")) -> OK Q 13 | F23: =IF(Questionnaire!I41<>0 = FALSE, "OK Q 13", IF(COUNTIF('Country List'!$E$4:$E$239,Questionnaire!I41)=0,"ERROR Q 13 - This must match a country option from the drop-down list","OK Q 13")) -> OK Q 13 | G23: =IF(Questionnaire!J41<>0 = FALSE, "OK Q 13", IF(COUNTIF('Country List'!$E$4:$E$239,Questionnaire!J41)=0,"ERROR Q 13 - This must match a country option from the drop-down list","OK Q 13")) -> OK Q 13 | H23: =IF(Questionnaire!K41<>0 = FALSE, "OK Q 13", IF(COUNTIF('Country List'!$E$4:$E$239,Questionnaire!K41)=0,"ERROR Q 13 - This must match a country option from the drop-down list","OK Q 13")) -> OK Q 13 | ... IP23: =IF(Questionnaire!IS41<>0 = FALSE, "OK Q 13", IF(COUNTIF('Country List'!$E$4:$E$239,Questionnaire!IS41)=0,"ERROR Q 13 - This must match a country option from the drop-down list","OK Q 13")) -> OK Q 13
A24: =IF(LEFT(A25,2)="OK",1,IF(LEFT(A25,2)="ER",2,1)) -> 1 | B24: =IF(LEFT(B25,2)="OK",1,IF(LEFT(B25,2)="ER",2,1)) -> 1 | C24: =IF(LEFT(C25,2)="OK",1,IF(LEFT(C25,2)="ER",2,1)) -> 1 | D24: =IF(LEFT(D25,2)="OK",1,IF(LEFT(D25,2)="ER",2,1)) -> 1 | E24: =IF(LEFT(E25,2)="OK",1,IF(LEFT(E25,2)="ER",2,1)) -> 1 | F24: =IF(LEFT(F25,2)="OK",1,IF(LEFT(F25,2)="ER",2,1)) -> 1 | G24: =IF(LEFT(G25,2)="OK",1,IF(LEFT(G25,2)="ER",2,1)) -> 1 | H24: =IF(LEFT(H25,2)="OK",1,IF(LEFT(H25,2)="ER",2,1)) -> 1 | ... IP24: =IF(LEFT(IP25,2)="OK",1,IF(LEFT(IP25,2)="ER",2,1)) -> 1
A25: =IF(Questionnaire!D42<>0 = FALSE, "OK Q 14", IF(COUNTIF('Industry List'!$B$3:$B$110,Questionnaire!D42)=0,"ERROR Q 14 - This must match an industry option from the drop-down list","OK Q 14")) -> OK Q 14 | B25: =IF(Questionnaire!E42<>0 = FALSE, "OK Q 14", IF(COUNTIF('Industry List'!$B$3:$B$110,Questionnaire!E42)=0,"ERROR Q 14 - This must match an industry option from the drop-down list","OK Q 14")) -> OK Q 14 | C25: =IF(Questionnaire!F42<>0 = FALSE, "OK Q 14", IF(COUNTIF('Industry List'!$B$3:$B$110,Questionnaire!F42)=0,"ERROR Q 14 - This must match an industry option from the drop-down list","OK Q 14")) -> OK Q 14 | D25: =IF(Questionnaire!G42<>0 = FALSE, "OK Q 14", IF(COUNTIF('Industry List'!$B$3:$B$110,Questionnaire!G42)=0,"ERROR Q 14 - This must match an industry option from the drop-down list","OK Q 14")) -> OK Q 14 | E25: =IF(Questionnaire!H42<>0 = FALSE, "OK Q 14", IF(COUNTIF('Industry List'!$B$3:$B$110,Questionnaire!H42)=0,"ERROR Q 14 - This must match an industry option from the drop-down list","OK Q 14")) -> OK Q 14 | F25: =IF(Questionnaire!I42<>0 = FALSE, "OK Q 14", IF(COUNTIF('Industry List'!$B$3:$B$110,Questionnaire!I42)=0,"ERROR Q 14 - This must match an industry option from the drop-down list","OK Q 14")) -> OK Q 14 | G25: =IF(Questionnaire!J42<>0 = FALSE, "OK Q 14", IF(COUNTIF('Industry List'!$B$3:$B$110,Questionnaire!J42)=0,"ERROR Q 14 - This must match an industry option from the drop-down list","OK Q 14")) -> OK Q 14 | H25: =IF(Questionnaire!K42<>0 = FALSE, "OK Q 14", IF(COUNTIF('Industry List'!$B$3:$B$110,Questionnaire!K42)=0,"ERROR Q 14 - This must match an industry option from the drop-down list","OK Q 14")) -> OK Q 14 | ... IP25: =IF(Questionnaire!IS42<>0 = FALSE, "OK Q 14", IF(COUNTIF('Industry List'!$B$3:$B$110,Questionnaire!IS42)=0,"ERROR Q 14 - This must match an industry option from the drop-down list","OK Q 14")) -> OK Q 14
A26: =IF(LEFT(A27,2)="OK",0,IF(LEFT(A27,2)="WA",2,1)) -> 0 | B26: =IF(LEFT(B27,2)="OK",0,IF(LEFT(B27,2)="WA",2,1)) -> 0 | C26: =IF(LEFT(C27,2)="OK",0,IF(LEFT(C27,2)="WA",2,1)) -> 0 | D26: =IF(LEFT(D27,2)="OK",0,IF(LEFT(D27,2)="WA",2,1)) -> 0 | E26: =IF(LEFT(E27,2)="OK",0,IF(LEFT(E27,2)="WA",2,1)) -> 0 | F26: =IF(LEFT(F27,2)="OK",0,IF(LEFT(F27,2)="WA",2,1)) -> 0 | G26: =IF(LEFT(G27,2)="OK",0,IF(LEFT(G27,2)="WA",2,1)) -> 0 | H26: =IF(LEFT(H27,2)="OK",0,IF(LEFT(H27,2)="WA",2,1)) -> 0 | ... IP26: =IF(LEFT(IP27,2)="OK",0,IF(LEFT(IP27,2)="WA",2,1)) -> 0
A27: =IF(ABS(Questionnaire!D52-Questionnaire!D68)>1000,"WARNING Q 18.a-18.b - Net affiliates profit/loss is greater than £1000m - please check","OK Q 18.a-18.b") -> OK Q 18.a-18.b | B27: =IF(ABS(Questionnaire!E52-Questionnaire!E68)>1000,"WARNING Q 18.a-18.b - Net affiliates profit/loss is greater than £1000m - please check","OK Q 18.a-18.b") -> OK Q 18.a-18.b | C27: =IF(ABS(Questionnaire!F52-Questionnaire!F68)>1000,"WARNING Q 18.a-18.b - Net affiliates profit/loss is greater than £1000m - please check","OK Q 18.a-18.b") -> OK Q 18.a-18.b | D27: =IF(ABS(Questionnaire!G52-Questionnaire!G68)>1000,"WARNING Q 18.a-18.b - Net affiliates profit/loss is greater than £1000m - please check","OK Q 18.a-18.b") -> OK Q 18.a-18.b | E27: =IF(ABS(Questionnaire!H52-Questionnaire!H68)>1000,"WARNING Q 18.a-18.b - Net affiliates profit/loss is greater than £1000m - please check","OK Q 18.a-18.b") -> OK Q 18.a-18.b | F27: =IF(ABS(Questionnaire!I52-Questionnaire!I68)>1000,"WARNING Q 18.a-18.b - Net affiliates profit/loss is greater than £1000m - please check","OK Q 18.a-18.b") -> OK Q 18.a-18.b | G27: =IF(ABS(Questionnaire!J52-Questionnaire!J68)>1000,"WARNING Q 18.a-18.b - Net affiliates profit/loss is greater than £1000m - please check","OK Q 18.a-18.b") -> OK Q 18.a-18.b | H27: =IF(ABS(Questionnaire!K52-Questionnaire!K68)>1000,"WARNING Q 18.a-18.b - Net affiliates profit/loss is greater than £1000m - please check","OK Q 18.a-18.b") -> OK Q 18.a-18.b | ... IP27: =IF(ABS(Questionnaire!IS52-Questionnaire!IS68)>1000,"WARNING Q 18.a-18.b - Net affiliates profit/loss is greater than £1000m - please check","OK Q 18.a-18.b") -> OK Q 18.a-18.b
A28: =IF(LEFT(A29,2)="OK",0,IF(LEFT(A29,2)="QU",2,1)) -> 0 | B28: =IF(LEFT(B29,2)="OK",0,IF(LEFT(B29,2)="QU",2,1)) -> 0 | C28: =IF(LEFT(C29,2)="OK",0,IF(LEFT(C29,2)="QU",2,1)) -> 0 | D28: =IF(LEFT(D29,2)="OK",0,IF(LEFT(D29,2)="QU",2,1)) -> 0 | E28: =IF(LEFT(E29,2)="OK",0,IF(LEFT(E29,2)="QU",2,1)) -> 0 | F28: =IF(LEFT(F29,2)="OK",0,IF(LEFT(F29,2)="QU",2,1)) -> 0 | G28: =IF(LEFT(G29,2)="OK",0,IF(LEFT(G29,2)="QU",2,1)) -> 0 | H28: =IF(LEFT(H29,2)="OK",0,IF(LEFT(H29,2)="QU",2,1)) -> 0 | ... IP28: =IF(LEFT(IP29,2)="OK",0,IF(LEFT(IP29,2)="QU",2,1)) -> 0
A29: =IF(Questionnaire!D52=(Questionnaire!D54+Questionnaire!D55+Questionnaire!D56+Questionnaire!D57+Questionnaire!D58+Questionnaire!D59+Questionnaire!D60+Questionnaire!D61+Questionnaire!D62+Questionnaire!D63+Questionnaire!D64+Questionnaire!D65+Questionnaire!D66)=TRUE,"OK Q18.a.i","QUERY Q18 - Components in 18a.i must sum to profit in 18.a - please check") -> OK Q18.a.i | B29: =IF(Questionnaire!E52=(Questionnaire!E54+Questionnaire!E55+Questionnaire!E56+Questionnaire!E57+Questionnaire!E58+Questionnaire!E59+Questionnaire!E60+Questionnaire!E61+Questionnaire!E62+Questionnaire!E63+Questionnaire!E64+Questionnaire!E65+Questionnaire!E66)=TRUE,"OK Q18.a.i","QUERY Q18 - Components in 18a.i must sum to profit in 18.a - please check") -> OK Q18.a.i | C29: =IF(Questionnaire!F52=(Questionnaire!F54+Questionnaire!F55+Questionnaire!F56+Questionnaire!F57+Questionnaire!F58+Questionnaire!F59+Questionnaire!F60+Questionnaire!F61+Questionnaire!F62+Questionnaire!F63+Questionnaire!F64+Questionnaire!F65+Questionnaire!F66)=TRUE,"OK Q18.a.i","QUERY Q18 - Components in 18a.i must sum to profit in 18.a - please check") -> OK Q18.a.i | D29: =IF(Questionnaire!G52=(Questionnaire!G54+Questionnaire!G55+Questionnaire!G56+Questionnaire!G57+Questionnaire!G58+Questionnaire!G59+Questionnaire!G60+Questionnaire!G61+Questionnaire!G62+Questionnaire!G63+Questionnaire!G64+Questionnaire!G65+Questionnaire!G66)=TRUE,"OK Q18.a.i","QUERY Q18 - Components in 18a.i must sum to profit in 18.a - please check") -> OK Q18.a.i | E29: =IF(Questionnaire!H52=(Questionnaire!H54+Questionnaire!H55+Questionnaire!H56+Questionnaire!H57+Questionnaire!H58+Questionnaire!H59+Questionnaire!H60+Questionnaire!H61+Questionnaire!H62+Questionnaire!H63+Questionnaire!H64+Questionnaire!H65+Questionnaire!H66)=TRUE,"OK Q18.a.i","QUERY Q18 - Components in 18a.i must sum to profit in 18.a - please check") -> OK Q18.a.i | F29: =IF(Questionnaire!I52=(Questionnaire!I54+Questionnaire!I55+Questionnaire!I56+Questionnaire!I57+Questionnaire!I58+Questionnaire!I59+Questionnaire!I60+Questionnaire!I61+Questionnaire!I62+Questionnaire!I63+Questionnaire!I64+Questionnaire!I65+Questionnaire!I66)=TRUE,"OK Q18.a.i","QUERY Q18 - Components in 18a.i must sum to profit in 18.a - please check") -> OK Q18.a.i | G29: =IF(Questionnaire!J52=(Questionnaire!J54+Questionnaire!J55+Questionnaire!J56+Questionnaire!J57+Questionnaire!J58+Questionnaire!J59+Questionnaire!J60+Questionnaire!J61+Questionnaire!J62+Questionnaire!J63+Questionnaire!J64+Questionnaire!J65+Questionnaire!J66)=TRUE,"OK Q18.a.i","QUERY Q18 - Components in 18a.i must sum to profit in 18.a - please check") -> OK Q18.a.i | H29: =IF(Questionnaire!K52=(Questionnaire!K54+Questionnaire!K55+Questionnaire!K56+Questionnaire!K57+Questionnaire!K58+Questionnaire!K59+Questionnaire!K60+Questionnaire!K61+Questionnaire!K62+Questionnaire!K63+Questionnaire!K64+Questionnaire!K65+Questionnaire!K66)=TRUE,"OK Q18.a.i","QUERY Q18 - Components in 18a.i must sum to profit in 18.a - please check") -> OK Q18.a.i | ... IP29: =IF(Questionnaire!IS52=(Questionnaire!IS54+Questionnaire!IS55+Questionnaire!IS56+Questionnaire!IS57+Questionnaire!IS58+Questionnaire!IS59+Questionnaire!IS60+Questionnaire!IS61+Questionnaire!IS62+Questionnaire!IS63+Questionnaire!IS64+Questionnaire!IS65+Questionnaire!IS66)=TRUE,"OK Q18.a.i","QUERY Q18 - Components in 18a.i must sum to profit in 18.a - please check") -> OK Q18.a.i
A30: =IF(LEFT(A31,2)="OK",0,IF(LEFT(A31,2)="QU",2,1)) -> 2 | B30: =IF(LEFT(B31,2)="OK",0,IF(LEFT(B31,2)="QU",2,1)) -> 0 | C30: =IF(LEFT(C31,2)="OK",0,IF(LEFT(C31,2)="QU",2,1)) -> 0 | D30: =IF(LEFT(D31,2)="OK",0,IF(LEFT(D31,2)="QU",2,1)) -> 0 | E30: =IF(LEFT(E31,2)="OK",0,IF(LEFT(E31,2)="QU",2,1)) -> 0 | F30: =IF(LEFT(F31,2)="OK",0,IF(LEFT(F31,2)="QU",2,1)) -> 0 | G30: =IF(LEFT(G31,2)="OK",0,IF(LEFT(G31,2)="QU",2,1)) -> 0 | H30: =IF(LEFT(H31,2)="OK",0,IF(LEFT(H31,2)="QU",2,1)) -> 0 | ... IP30: =IF(LEFT(IP31,2)="OK",0,IF(LEFT(IP31,2)="QU",2,1)) -> 0
A31: =IF(Questionnaire!D72=0,"OK Q 22",IF((Questionnaire!D72)>(Questionnaire!D52),"QUERY Q 22 - Ordinary Dividends are greater than affiliates profit, re-invested earnings will be negative","OK Q 22")) -> QUERY Q 22 - Ordinary Dividends are greater than affiliates profit, re-invested earnings will be negative | B31: =IF(Questionnaire!E72=0,"OK Q 22",IF((Questionnaire!E72)>(Questionnaire!E52-Questionnaire!E68),"QUERY Q 22 - Ordinary Dividends are greater than affiliates profit, re-invested earnings will be negative","OK Q 22")) -> OK Q 22 | C31: =IF(Questionnaire!F72=0,"OK Q 22",IF((Questionnaire!F72)>(Questionnaire!F52),"QUERY Q 22 - Ordinary Dividends are greater than affiliates profit, re-invested earnings will be negative","OK Q 22")) -> OK Q 22 | D31: =IF(Questionnaire!G72=0,"OK Q 22",IF((Questionnaire!G72)>(Questionnaire!G52),"QUERY Q 22 - Ordinary Dividends are greater than affiliates profit, re-invested earnings will be negative","OK Q 22")) -> OK Q 22 | E31: =IF(Questionnaire!H72=0,"OK Q 22",IF((Questionnaire!H72)>(Questionnaire!H52),"QUERY Q 22 - Ordinary Dividends are greater than affiliates profit, re-invested earnings will be negative","OK Q 22")) -> OK Q 22 | F31: =IF(Questionnaire!I72=0,"OK Q 22",IF((Questionnaire!I72)>(Questionnaire!I52),"QUERY Q 22 - Ordinary Dividends are greater than affiliates profit, re-invested earnings will be negative","OK Q 22")) -> OK Q 22 | G31: =IF(Questionnaire!J72=0,"OK Q 22",IF((Questionnaire!J72)>(Questionnaire!J52),"QUERY Q 22 - Ordinary Dividends are greater than affiliates profit, re-invested earnings will be negative","OK Q 22")) -> OK Q 22 | H31: =IF(Questionnaire!K72=0,"OK Q 22",IF((Questionnaire!K72)>(Questionnaire!K52),"QUERY Q 22 - Ordinary Dividends are greater than affiliates profit, re-invested earnings will be negative","OK Q 22")) -> OK Q 22 | I31: =IF(Questionnaire!L72=0,"OK Q 22",IF((Questionnaire!L72)>(Questionnaire!L52),"QUERY Q 22 - Ordinary Dividends are greater than affiliates profit, re-invested earnings will be negative","OK Q 22")) -> OK Q 22 | J31: =IF(Questionnaire!M72=0,"OK Q 22",IF((Questionnaire!M72)>(Questionnaire!M52),"QUERY Q 22 - Ordinary Dividends are greater than affiliates profit, re-invested earnings will be negative","OK Q 22")) -> OK Q 22 | ... IP31: =IF(Questionnaire!IS72=0,"OK Q 22",IF((Questionnaire!IS72)>(Questionnaire!IS52),"QUERY Q 22 - Ordinary Dividends are greater than affiliates profit, re-invested earnings will be negative","OK Q 22")) -> OK Q 22
A32: =IF(LEFT(A33,2)="OK",0,IF(LEFT(A33,2)="WA",2,1)) -> 2 | B32: =IF(LEFT(B33,2)="OK",0,IF(LEFT(B33,2)="WA",2,1)) -> 0 | C32: =IF(LEFT(C33,2)="OK",0,IF(LEFT(C33,2)="WA",2,1)) -> 0 | D32: =IF(LEFT(D33,2)="OK",0,IF(LEFT(D33,2)="WA",2,1)) -> 0 | E32: =IF(LEFT(E33,2)="OK",0,IF(LEFT(E33,2)="WA",2,1)) -> 0 | F32: =IF(LEFT(F33,2)="OK",0,IF(LEFT(F33,2)="WA",2,1)) -> 0 | G32: =IF(LEFT(G33,2)="OK",0,IF(LEFT(G33,2)="WA",2,1)) -> 0 | H32: =IF(LEFT(H33,2)="OK",0,IF(LEFT(H33,2)="WA",2,1)) -> 0 | ... IP32: =IF(LEFT(IP33,2)="OK",0,IF(LEFT(IP33,2)="WA",2,1)) -> 0
A33: =IF(Questionnaire!D72>100,"WARNING Q 22 - Ordinary Dividends are greater than £100m - please check","OK Q 22") -> WARNING Q 22 - Ordinary Dividends are greater than £100m - please check | B33: =IF(Questionnaire!E72>100,"WARNING Q 22 - Ordinary Dividends are greater than £100m - please check","OK Q 22") -> OK Q 22 | C33: =IF(Questionnaire!F72>100,"WARNING Q 22 - Ordinary Dividends are greater than £100m - please check","OK Q 22") -> OK Q 22 | D33: =IF(Questionnaire!G72>100,"WARNING Q 22 - Ordinary Dividends are greater than £100m - please check","OK Q 22") -> OK Q 22 | E33: =IF(Questionnaire!H72>100,"WARNING Q 22 - Ordinary Dividends are greater than £100m - please check","OK Q 22") -> OK Q 22 | F33: =IF(Questionnaire!I72>100,"WARNING Q 22 - Ordinary Dividends are greater than £100m - please check","OK Q 22") -> OK Q 22 | G33: =IF(Questionnaire!J72>100,"WARNING Q 22 - Ordinary Dividends are greater than £100m - please check","OK Q 22") -> OK Q 22 | H33: =IF(Questionnaire!K72>100,"WARNING Q 22 - Ordinary Dividends are greater than £100m - please check","OK Q 22") -> OK Q 22 | ... IP33: =IF(Questionnaire!IS72>100,"WARNING Q 22 - Ordinary Dividends are greater than £100m - please check","OK Q 22") -> OK Q 22
A34: =IF(LEFT(A35,2)="OK",0,IF(LEFT(A35,2)="QU",2,1)) -> 0 | B34: =IF(LEFT(B35,2)="OK",0,IF(LEFT(B35,2)="QU",2,1)) -> 0 | C34: =IF(LEFT(C35,2)="OK",0,IF(LEFT(C35,2)="QU",2,1)) -> 0 | D34: =IF(LEFT(D35,2)="OK",0,IF(LEFT(D35,2)="QU",2,1)) -> 0 | E34: =IF(LEFT(E35,2)="OK",0,IF(LEFT(E35,2)="QU",2,1)) -> 0 | F34: =IF(LEFT(F35,2)="OK",0,IF(LEFT(F35,2)="QU",2,1)) -> 0 | G34: =IF(LEFT(G35,2)="OK",0,IF(LEFT(G35,2)="QU",2,1)) -> 0 | H34: =IF(LEFT(H35,2)="OK",0,IF(LEFT(H35,2)="QU",2,1)) -> 0 | ... IP34: =IF(LEFT(IP35,2)="OK",0,IF(LEFT(IP35,2)="QU",2,1)) -> 0
A35: =IF(OR(Questionnaire!D80=Questionnaire!D78+Questionnaire!D52-Questionnaire!D68-Questionnaire!D72+Questionnaire!D82-Questionnaire!D95+Questionnaire!D108-Questionnaire!D109,Questionnaire!D75="Unquoted")=TRUE,"OK Q 27","QUERY Q 27 - Closing Quoted Shares - Sum of transactions does not equal closing balance - please check") -> OK Q 27 | B35: =IF(OR(Questionnaire!E80=Questionnaire!E78+Questionnaire!E52-Questionnaire!E68-Questionnaire!E72+Questionnaire!E82-Questionnaire!E95+Questionnaire!E108-Questionnaire!E109,Questionnaire!E75="Unquoted")=TRUE,"OK Q 27","QUERY Q 27 - Closing Quoted Shares - Sum of transactions does not equal closing balance - please check") -> OK Q 27 | C35: =IF(OR(Questionnaire!F80=Questionnaire!F78+Questionnaire!F52-Questionnaire!F68-Questionnaire!F72+Questionnaire!F82-Questionnaire!F95+Questionnaire!F108-Questionnaire!F109,Questionnaire!F75="Unquoted")=TRUE,"OK Q 27","QUERY Q 27 - Closing Quoted Shares - Sum of transactions does not equal closing balance - please check") -> OK Q 27 | D35: =IF(OR(Questionnaire!G80=Questionnaire!G78+Questionnaire!G52-Questionnaire!G68-Questionnaire!G72+Questionnaire!G82-Questionnaire!G95+Questionnaire!G108-Questionnaire!G109,Questionnaire!G75="Unquoted")=TRUE,"OK Q 27","QUERY Q 27 - Closing Quoted Shares - Sum of transactions does not equal closing balance - please check") -> OK Q 27 | E35: =IF(OR(Questionnaire!H80=Questionnaire!H78+Questionnaire!H52-Questionnaire!H68-Questionnaire!H72+Questionnaire!H82-Questionnaire!H95+Questionnaire!H108-Questionnaire!H109,Questionnaire!H75="Unquoted")=TRUE,"OK Q 27","QUERY Q 27 - Closing Quoted Shares - Sum of transactions does not equal closing balance - please check") -> OK Q 27 | F35: =IF(OR(Questionnaire!I80=Questionnaire!I78+Questionnaire!I52-Questionnaire!I68-Questionnaire!I72+Questionnaire!I82-Questionnaire!I95+Questionnaire!I108-Questionnaire!I109,Questionnaire!I75="Unquoted")=TRUE,"OK Q 27","QUERY Q 27 - Closing Quoted Shares - Sum of transactions does not equal closing balance - please check") -> OK Q 27 | G35: =IF(OR(Questionnaire!J80=Questionnaire!J78+Questionnaire!J52-Questionnaire!J68-Questionnaire!J72+Questionnaire!J82-Questionnaire!J95+Questionnaire!J108-Questionnaire!J109,Questionnaire!J75="Unquoted")=TRUE,"OK Q 27","QUERY Q 27 - Closing Quoted Shares - Sum of transactions does not equal closing balance - please check") -> OK Q 27 | H35: =IF(OR(Questionnaire!K80=Questionnaire!K78+Questionnaire!K52-Questionnaire!K68-Questionnaire!K72+Questionnaire!K82-Questionnaire!K95+Questionnaire!K108-Questionnaire!K109,Questionnaire!K75="Unquoted")=TRUE,"OK Q 27","QUERY Q 27 - Closing Quoted Shares - Sum of transactions does not equal closing balance - please check") -> OK Q 27 | ... IP35: =IF(OR(Questionnaire!IS80=Questionnaire!IS78+Questionnaire!IS52-Questionnaire!IS68-Questionnaire!IS72+Questionnaire!IS82-Questionnaire!IS95+Questionnaire!IS108-Questionnaire!IS109,Questionnaire!IS75="Unquoted")=TRUE,"OK Q 27","QUERY Q 27 - Closing Quoted Shares - Sum of transactions does not equal closing balance - please check") -> OK Q 27
A36: =IF(LEFT(A37,2)="OK",0,IF(LEFT(A37,2)="QU",2,1)) -> 0 | B36: =IF(LEFT(B37,2)="OK",0,IF(LEFT(B37,2)="QU",2,1)) -> 0 | C36: =IF(LEFT(C37,2)="OK",0,IF(LEFT(C37,2)="QU",2,1)) -> 0 | D36: =IF(LEFT(D37,2)="OK",0,IF(LEFT(D37,2)="QU",2,1)) -> 0 | E36: =IF(LEFT(E37,2)="OK",0,IF(LEFT(E37,2)="QU",2,1)) -> 0 | F36: =IF(LEFT(F37,2)="OK",0,IF(LEFT(F37,2)="QU",2,1)) -> 0 | G36: =IF(LEFT(G37,2)="OK",0,IF(LEFT(G37,2)="QU",2,1)) -> 0 | H36: =IF(LEFT(H37,2)="OK",0,IF(LEFT(H37,2)="QU",2,1)) -> 0 | ... IP36: =IF(LEFT(IP37,2)="OK",0,IF(LEFT(IP37,2)="QU",2,1)) -> 0
A37: =IF(Questionnaire!D82=(Questionnaire!D84+Questionnaire!D85+Questionnaire!D86+Questionnaire!D87)=TRUE,"OK Q29.a.i","QUERY Q29a - Components in 29.a.i must sum to acquisitions of quoted equity capital total value in 29.a - please check") -> OK Q29.a.i | B37: =IF(Questionnaire!E82=(Questionnaire!E84+Questionnaire!E85+Questionnaire!E86+Questionnaire!E87)=TRUE,"OK Q29.a.i","QUERY Q29a - Components in 29.a.i must sum to acquisitions of quoted equity capital total value in 29.a - please check") -> OK Q29.a.i | C37: =IF(Questionnaire!F82=(Questionnaire!F84+Questionnaire!F85+Questionnaire!F86+Questionnaire!F87)=TRUE,"OK Q29.a.i","QUERY Q29a - Components in 29.a.i must sum to acquisitions of quoted equity capital total value in 29.a - please check") -> OK Q29.a.i | D37: =IF(Questionnaire!G82=(Questionnaire!G84+Questionnaire!G85+Questionnaire!G86+Questionnaire!G87)=TRUE,"OK Q29.a.i","QUERY Q29a - Components in 29.a.i must sum to acquisitions of quoted equity capital total value in 29.a - please check") -> OK Q29.a.i | E37: =IF(Questionnaire!H82=(Questionnaire!H84+Questionnaire!H85+Questionnaire!H86+Questionnaire!H87)=TRUE,"OK Q29.a.i","QUERY Q29a - Components in 29.a.i must sum to acquisitions of quoted equity capital total value in 29.a - please check") -> OK Q29.a.i | F37: =IF(Questionnaire!I82=(Questionnaire!I84+Questionnaire!I85+Questionnaire!I86+Questionnaire!I87)=TRUE,"OK Q29.a.i","QUERY Q29a - Components in 29.a.i must sum to acquisitions of quoted equity capital total value in 29.a - please check") -> OK Q29.a.i | G37: =IF(Questionnaire!J82=(Questionnaire!J84+Questionnaire!J85+Questionnaire!J86+Questionnaire!J87)=TRUE,"OK Q29.a.i","QUERY Q29a - Components in 29.a.i must sum to acquisitions of quoted equity capital total value in 29.a - please check") -> OK Q29.a.i | H37: =IF(Questionnaire!K82=(Questionnaire!K84+Questionnaire!K85+Questionnaire!K86+Questionnaire!K87)=TRUE,"OK Q29.a.i","QUERY Q29a - Components in 29.a.i must sum to acquisitions of quoted equity capital total value in 29.a - please check") -> OK Q29.a.i | ... IP37: =IF(Questionnaire!IS82=(Questionnaire!IS84+Questionnaire!IS85+Questionnaire!IS86+Questionnaire!IS87)=TRUE,"OK Q29.a.i","QUERY Q29a - Components in 29.a.i must sum to acquisitions of quoted equity capital total value in 29.a - please check") -> OK Q29.a.i
A38: =IF(LEFT(A39,2)="OK",0,IF(LEFT(A39,2)="QU",2,1)) -> 0 | B38: =IF(LEFT(B39,2)="OK",0,IF(LEFT(B39,2)="QU",2,1)) -> 0 | C38: =IF(LEFT(C39,2)="OK",0,IF(LEFT(C39,2)="QU",2,1)) -> 0 | D38: =IF(LEFT(D39,2)="OK",0,IF(LEFT(D39,2)="QU",2,1)) -> 0 | E38: =IF(LEFT(E39,2)="OK",0,IF(LEFT(E39,2)="QU",2,1)) -> 0 | F38: =IF(LEFT(F39,2)="OK",0,IF(LEFT(F39,2)="QU",2,1)) -> 0 | G38: =IF(LEFT(G39,2)="OK",0,IF(LEFT(G39,2)="QU",2,1)) -> 0 | H38: =IF(LEFT(H39,2)="OK",0,IF(LEFT(H39,2)="QU",2,1)) -> 0 | ... IP38: =IF(LEFT(IP39,2)="OK",0,IF(LEFT(IP39,2)="QU",2,1)) -> 0
A39: =IF(Questionnaire!D82=(Questionnaire!D90+Questionnaire!D91+Questionnaire!D92+Questionnaire!D93)=TRUE,"OK Q29.a.ii","QUERY Q29a - Components in 29.a.ii must sum to acquisitions of quoted equity capital total value in 29.a - please check") -> OK Q29.a.ii | B39: =IF(Questionnaire!E82=(Questionnaire!E90+Questionnaire!E91+Questionnaire!E92+Questionnaire!E93)=TRUE,"OK Q29.a.ii","QUERY Q29a - Components in 29.a.ii must sum to acquisitions of quoted equity capital total value in 29.a - please check") -> OK Q29.a.ii | C39: =IF(Questionnaire!F82=(Questionnaire!F90+Questionnaire!F91+Questionnaire!F92+Questionnaire!F93)=TRUE,"OK Q29.a.ii","QUERY Q29a - Components in 29.a.ii must sum to acquisitions of quoted equity capital total value in 29.a - please check") -> OK Q29.a.ii | D39: =IF(Questionnaire!G82=(Questionnaire!G90+Questionnaire!G91+Questionnaire!G92+Questionnaire!G93)=TRUE,"OK Q29.a.ii","QUERY Q29a - Components in 29.a.ii must sum to acquisitions of quoted equity capital total value in 29.a - please check") -> OK Q29.a.ii | E39: =IF(Questionnaire!H82=(Questionnaire!H90+Questionnaire!H91+Questionnaire!H92+Questionnaire!H93)=TRUE,"OK Q29.a.ii","QUERY Q29a - Components in 29.a.ii must sum to acquisitions of quoted equity capital total value in 29.a - please check") -> OK Q29.a.ii | F39: =IF(Questionnaire!I82=(Questionnaire!I90+Questionnaire!I91+Questionnaire!I92+Questionnaire!I93)=TRUE,"OK Q29.a.ii","QUERY Q29a - Components in 29.a.ii must sum to acquisitions of quoted equity capital total value in 29.a - please check") -> OK Q29.a.ii | G39: =IF(Questionnaire!J82=(Questionnaire!J90+Questionnaire!J91+Questionnaire!J92+Questionnaire!J93)=TRUE,"OK Q29.a.ii","QUERY Q29a - Components in 29.a.ii must sum to acquisitions of quoted equity capital total value in 29.a - please check") -> OK Q29.a.ii | H39: =IF(Questionnaire!K82=(Questionnaire!K90+Questionnaire!K91+Questionnaire!K92+Questionnaire!K93)=TRUE,"OK Q29.a.ii","QUERY Q29a - Components in 29.a.ii must sum to acquisitions of quoted equity capital total value in 29.a - please check") -> OK Q29.a.ii | ... IP39: =IF(Questionnaire!IS82=(Questionnaire!IS90+Questionnaire!IS91+Questionnaire!IS92+Questionnaire!IS93)=TRUE,"OK Q29.a.ii","QUERY Q29a - Components in 29.a.ii must sum to acquisitions of quoted equity capital total value in 29.a - please check") -> OK Q29.a.ii
A40: =IF(LEFT(A41,2)="OK",0,IF(LEFT(A41,2)="QU",2,1)) -> 0 | B40: =IF(LEFT(B41,2)="OK",0,IF(LEFT(B41,2)="QU",2,1)) -> 0 | C40: =IF(LEFT(C41,2)="OK",0,IF(LEFT(C41,2)="QU",2,1)) -> 0 | D40: =IF(LEFT(D41,2)="OK",0,IF(LEFT(D41,2)="QU",2,1)) -> 0 | E40: =IF(LEFT(E41,2)="OK",0,IF(LEFT(E41,2)="QU",2,1)) -> 0 | F40: =IF(LEFT(F41,2)="OK",0,IF(LEFT(F41,2)="QU",2,1)) -> 0 | G40: =IF(LEFT(G41,2)="OK",0,IF(LEFT(G41,2)="QU",2,1)) -> 0 | H40: =IF(LEFT(H41,2)="OK",0,IF(LEFT(H41,2)="QU",2,1)) -> 0 | ... IP40: =IF(LEFT(IP41,2)="OK",0,IF(LEFT(IP41,2)="QU",2,1)) -> 0
A41: =IF(Questionnaire!D95=(Questionnaire!D97+Questionnaire!D98+Questionnaire!D99)=TRUE,"OK Q29.b.i","QUERY Q29b - Components in 29.b.i must sum to disposal of quoted equity capital total value in 29.b - please check") -> OK Q29.b.i | B41: =IF(Questionnaire!E95=(Questionnaire!E97+Questionnaire!E98+Questionnaire!E99)=TRUE,"OK Q29.b.i","QUERY Q29b - Components in 29.b.i must sum to disposal of quoted equity capital total value in 29.b - please check") -> OK Q29.b.i | C41: =IF(Questionnaire!F95=(Questionnaire!F97+Questionnaire!F98+Questionnaire!F99)=TRUE,"OK Q29.b.i","QUERY Q29b - Components in 29.b.i must sum to disposal of quoted equity capital total value in 29.b - please check") -> OK Q29.b.i | D41: =IF(Questionnaire!G95=(Questionnaire!G97+Questionnaire!G98+Questionnaire!G99)=TRUE,"OK Q29.b.i","QUERY Q29b - Components in 29.b.i must sum to disposal of quoted equity capital total value in 29.b - please check") -> OK Q29.b.i | E41: =IF(Questionnaire!H95=(Questionnaire!H97+Questionnaire!H98+Questionnaire!H99)=TRUE,"OK Q29.b.i","QUERY Q29b - Components in 29.b.i must sum to disposal of quoted equity capital total value in 29.b - please check") -> OK Q29.b.i | F41: =IF(Questionnaire!I95=(Questionnaire!I97+Questionnaire!I98+Questionnaire!I99)=TRUE,"OK Q29.b.i","QUERY Q29b - Components in 29.b.i must sum to disposal of quoted equity capital total value in 29.b - please check") -> OK Q29.b.i | G41: =IF(Questionnaire!J95=(Questionnaire!J97+Questionnaire!J98+Questionnaire!J99)=TRUE,"OK Q29.b.i","QUERY Q29b - Components in 29.b.i must sum to disposal of quoted equity capital total value in 29.b - please check") -> OK Q29.b.i | H41: =IF(Questionnaire!K95=(Questionnaire!K97+Questionnaire!K98+Questionnaire!K99)=TRUE,"OK Q29.b.i","QUERY Q29b - Components in 29.b.i must sum to disposal of quoted equity capital total value in 29.b - please check") -> OK Q29.b.i | ... IP41: =IF(Questionnaire!IS95=(Questionnaire!IS97+Questionnaire!IS98+Questionnaire!IS99)=TRUE,"OK Q29.b.i","QUERY Q29b - Components in 29.b.i must sum to disposal of quoted equity capital total value in 29.b - please check") -> OK Q29.b.i
A42: =IF(LEFT(A43,2)="OK",0,IF(LEFT(A43,2)="QU",2,1)) -> #REF! | B42: =IF(LEFT(B43,2)="OK",0,IF(LEFT(B43,2)="QU",2,1)) -> 0 | C42: =IF(LEFT(C43,2)="OK",0,IF(LEFT(C43,2)="QU",2,1)) -> 0 | D42: =IF(LEFT(D43,2)="OK",0,IF(LEFT(D43,2)="QU",2,1)) -> 0 | E42: =IF(LEFT(E43,2)="OK",0,IF(LEFT(E43,2)="QU",2,1)) -> 0 | F42: =IF(LEFT(F43,2)="OK",0,IF(LEFT(F43,2)="QU",2,1)) -> 0 | G42: =IF(LEFT(G43,2)="OK",0,IF(LEFT(G43,2)="QU",2,1)) -> 0 | H42: =IF(LEFT(H43,2)="OK",0,IF(LEFT(H43,2)="QU",2,1)) -> 0 | ... IP42: =IF(LEFT(IP43,2)="OK",0,IF(LEFT(IP43,2)="QU",2,1)) -> 0
A43: =IF(Questionnaire!D95=(Questionnaire!D102+Questionnaire!D103+Questionnaire!#REF!+Questionnaire!D104)=TRUE,"OK Q29.b.ii","QUERY Q29b - Components in 29.b.ii must sum to disposal of quoted equity capital total value in 29.b - please check") -> #REF! | B43: =IF(Questionnaire!E95=(Questionnaire!E102+Questionnaire!E103+Questionnaire!E104+Questionnaire!E105)=TRUE,"OK Q29.b.ii","QUERY Q29b - Components in 29.b.ii must sum to disposal of quoted equity capital total value in 29.b - please check") -> OK Q29.b.ii | C43: =IF(Questionnaire!F95=(Questionnaire!F102+Questionnaire!F103+Questionnaire!F104+Questionnaire!F105)=TRUE,"OK Q29.b.ii","QUERY Q29b - Components in 29.b.ii must sum to disposal of quoted equity capital total value in 29.b - please check") -> OK Q29.b.ii | D43: =IF(Questionnaire!G95=(Questionnaire!G102+Questionnaire!G103+Questionnaire!G104+Questionnaire!G105)=TRUE,"OK Q29.b.ii","QUERY Q29b - Components in 29.b.ii must sum to disposal of quoted equity capital total value in 29.b - please check") -> OK Q29.b.ii | E43: =IF(Questionnaire!H95=(Questionnaire!H102+Questionnaire!H103+Questionnaire!H104+Questionnaire!H105)=TRUE,"OK Q29.b.ii","QUERY Q29b - Components in 29.b.ii must sum to disposal of quoted equity capital total value in 29.b - please check") -> OK Q29.b.ii | F43: =IF(Questionnaire!I95=(Questionnaire!I102+Questionnaire!I103+Questionnaire!I104+Questionnaire!I105)=TRUE,"OK Q29.b.ii","QUERY Q29b - Components in 29.b.ii must sum to disposal of quoted equity capital total value in 29.b - please check") -> OK Q29.b.ii | G43: =IF(Questionnaire!J95=(Questionnaire!J102+Questionnaire!J103+Questionnaire!J104+Questionnaire!J105)=TRUE,"OK Q29.b.ii","QUERY Q29b - Components in 29.b.ii must sum to disposal of quoted equity capital total value in 29.b - please check") -> OK Q29.b.ii | H43: =IF(Questionnaire!K95=(Questionnaire!K102+Questionnaire!K103+Questionnaire!K104+Questionnaire!K105)=TRUE,"OK Q29.b.ii","QUERY Q29b - Components in 29.b.ii must sum to disposal of quoted equity capital total value in 29.b - please check") -> OK Q29.b.ii | I43: =IF(Questionnaire!L95=(Questionnaire!L102+Questionnaire!L103+Questionnaire!L104+Questionnaire!L105)=TRUE,"OK Q29.b.ii","QUERY Q29b - Components in 29.b.ii must sum to disposal of quoted equity capital total value in 29.b - please check") -> OK Q29.b.ii | ... IP43: =IF(Questionnaire!IS95=(Questionnaire!IS102+Questionnaire!IS103+Questionnaire!IS104+Questionnaire!IS105)=TRUE,"OK Q29.b.ii","QUERY Q29b - Components in 29.b.ii must sum to disposal of quoted equity capital total value in 29.b - please check") -> OK Q29.b.ii
A44: =IF(LEFT(A45,2)="OK",0,IF(LEFT(A45,2)="WA",2,1)) -> 2 | B44: =IF(LEFT(B45,2)="OK",0,IF(LEFT(B45,2)="WA",2,1)) -> 0 | C44: =IF(LEFT(C45,2)="OK",0,IF(LEFT(C45,2)="WA",2,1)) -> 0 | D44: =IF(LEFT(D45,2)="OK",0,IF(LEFT(D45,2)="WA",2,1)) -> 0 | E44: =IF(LEFT(E45,2)="OK",0,IF(LEFT(E45,2)="WA",2,1)) -> 0 | F44: =IF(LEFT(F45,2)="OK",0,IF(LEFT(F45,2)="WA",2,1)) -> 0 | G44: =IF(LEFT(G45,2)="OK",0,IF(LEFT(G45,2)="WA",2,1)) -> 0 | H44: =IF(LEFT(H45,2)="OK",0,IF(LEFT(H45,2)="WA",2,1)) -> 0 | ... IP44: =IF(LEFT(IP45,2)="OK",0,IF(LEFT(IP45,2)="WA",2,1)) -> 0
A45: =IF(ABS((Questionnaire!D113)-(Questionnaire!D114))>200,"WARNING Q 31 & 32 - Net change in unquoted shares is greater than £200m - please check","OK - Net change in unquoted shares") -> WARNING Q 31 & 32 - Net change in unquoted shares is greater than £200m - please check | B45: =IF(ABS((Questionnaire!E113)-(Questionnaire!E114))>200,"WARNING Variable 2299/Q 31 & 32 - Net change in unquoted shares is greater than £200m - please check","OK - Net change in unquoted shares") -> OK - Net change in unquoted shares | C45: =IF(ABS((Questionnaire!F113)-(Questionnaire!F114))>200,"WARNING Variable 2299/Q 31 & 32 - Net change in unquoted shares is greater than £200m - please check","OK - Net change in unquoted shares") -> OK - Net change in unquoted shares | D45: =IF(ABS((Questionnaire!G113)-(Questionnaire!G114))>200,"WARNING Variable 2299/Q 31 & 32 - Net change in unquoted shares is greater than £200m - please check","OK - Net change in unquoted shares") -> OK - Net change in unquoted shares | E45: =IF(ABS((Questionnaire!H113)-(Questionnaire!H114))>200,"WARNING Variable 2299/Q 31 & 32 - Net change in unquoted shares is greater than £200m - please check","OK - Net change in unquoted shares") -> OK - Net change in unquoted shares | F45: =IF(ABS((Questionnaire!I113)-(Questionnaire!I114))>200,"WARNING Variable 2299/Q 31 & 32 - Net change in unquoted shares is greater than £200m - please check","OK - Net change in unquoted shares") -> OK - Net change in unquoted shares | G45: =IF(ABS((Questionnaire!J113)-(Questionnaire!J114))>200,"WARNING Variable 2299/Q 31 & 32 - Net change in unquoted shares is greater than £200m - please check","OK - Net change in unquoted shares") -> OK - Net change in unquoted shares | H45: =IF(ABS((Questionnaire!K113)-(Questionnaire!K114))>200,"WARNING Variable 2299/Q 31 & 32 - Net change in unquoted shares is greater than £200m - please check","OK - Net change in unquoted shares") -> OK - Net change in unquoted shares | I45: =IF(ABS((Questionnaire!L113)-(Questionnaire!L114))>200,"WARNING Variable 2299/Q 31 & 32 - Net change in unquoted shares is greater than £200m - please check","OK - Net change in unquoted shares") -> OK - Net change in unquoted shares | ... IP45: =IF(ABS((Questionnaire!IS113)-(Questionnaire!IS114))>200,"WARNING Variable 2299/Q 31 & 32 - Net change in unquoted shares is greater than £200m - please check","OK - Net change in unquoted shares") -> OK - Net change in unquoted shares
A46: =IF(LEFT(A47,2)="OK",0,IF(LEFT(A47,2)="QU",2,1)) -> 0 | B46: =IF(LEFT(B47,2)="OK",0,IF(LEFT(B47,2)="QU",2,1)) -> 0 | C46: =IF(LEFT(C47,2)="OK",0,IF(LEFT(C47,2)="QU",2,1)) -> 0 | D46: =IF(LEFT(D47,2)="OK",0,IF(LEFT(D47,2)="QU",2,1)) -> 0 | E46: =IF(LEFT(E47,2)="OK",0,IF(LEFT(E47,2)="QU",2,1)) -> 0 | F46: =IF(LEFT(F47,2)="OK",0,IF(LEFT(F47,2)="QU",2,1)) -> 0 | G46: =IF(LEFT(G47,2)="OK",0,IF(LEFT(G47,2)="QU",2,1)) -> 0 | H46: =IF(LEFT(H47,2)="OK",0,IF(LEFT(H47,2)="QU",2,1)) -> 0 | ... IP46: =IF(LEFT(IP47,2)="OK",0,IF(LEFT(IP47,2)="QU",2,1)) -> 0
A47: =IF(OR(Questionnaire!D114=(Questionnaire!D113+Questionnaire!D52-Questionnaire!D68-Questionnaire!D72+Questionnaire!D130-Questionnaire!D143+Questionnaire!D156-Questionnaire!D157),Questionnaire!D75="Quoted")=TRUE,"OK Q 32","QUERY Q 32 - Closing Unquoted Shares - Sum of transactions does not equal closing balance - please check") -> OK Q 32 | B47: =IF(OR(Questionnaire!E114=(Questionnaire!E113+Questionnaire!E52-Questionnaire!E68-Questionnaire!E72+Questionnaire!E130-Questionnaire!E143+Questionnaire!E156-Questionnaire!E157),Questionnaire!E75="Quoted")=TRUE,"OK Q 32","QUERY Q 32 - Closing Unquoted Shares - Sum of transactions does not equal closing balance - please check") -> OK Q 32 | C47: =IF(OR(Questionnaire!F114=(Questionnaire!F113+Questionnaire!F52-Questionnaire!F68-Questionnaire!F72+Questionnaire!F130-Questionnaire!F143+Questionnaire!F156-Questionnaire!F157),Questionnaire!F75="Quoted")=TRUE,"OK Q 32","QUERY Q 32 - Closing Unquoted Shares - Sum of transactions does not equal closing balance - please check") -> OK Q 32 | D47: =IF(OR(Questionnaire!G114=(Questionnaire!G113+Questionnaire!G52-Questionnaire!G68-Questionnaire!G72+Questionnaire!G130-Questionnaire!G143+Questionnaire!G156-Questionnaire!G157),Questionnaire!G75="Quoted")=TRUE,"OK Q 32","QUERY Q 32 - Closing Unquoted Shares - Sum of transactions does not equal closing balance - please check") -> OK Q 32 | E47: =IF(OR(Questionnaire!H114=(Questionnaire!H113+Questionnaire!H52-Questionnaire!H68-Questionnaire!H72+Questionnaire!H130-Questionnaire!H143+Questionnaire!H156-Questionnaire!H157),Questionnaire!G75="Quoted")=TRUE,"OK Q 32","QUERY Q 32 - Closing Unquoted Shares - Sum of transactions does not equal closing balance - please check") -> OK Q 32 | F47: =IF(OR(Questionnaire!I114=(Questionnaire!I113+Questionnaire!I52-Questionnaire!I68-Questionnaire!I72+Questionnaire!I130-Questionnaire!I143+Questionnaire!I156-Questionnaire!I157),Questionnaire!H75="Quoted")=TRUE,"OK Q 32","QUERY Q 32 - Closing Unquoted Shares - Sum of transactions does not equal closing balance - please check") -> OK Q 32 | G47: =IF(OR(Questionnaire!J114=(Questionnaire!J113+Questionnaire!J52-Questionnaire!J68-Questionnaire!J72+Questionnaire!J130-Questionnaire!J143+Questionnaire!J156-Questionnaire!J157),Questionnaire!I75="Quoted")=TRUE,"OK Q 32","QUERY Q 32 - Closing Unquoted Shares - Sum of transactions does not equal closing balance - please check") -> OK Q 32 | H47: =IF(OR(Questionnaire!K114=(Questionnaire!K113+Questionnaire!K52-Questionnaire!K68-Questionnaire!K72+Questionnaire!K130-Questionnaire!K143+Questionnaire!K156-Questionnaire!K157),Questionnaire!J75="Quoted")=TRUE,"OK Q 32","QUERY Q 32 - Closing Unquoted Shares - Sum of transactions does not equal closing balance - please check") -> OK Q 32 | I47: =IF(OR(Questionnaire!L114=(Questionnaire!L113+Questionnaire!L52-Questionnaire!L68-Questionnaire!L72+Questionnaire!L130-Questionnaire!L143+Questionnaire!L156-Questionnaire!L157),Questionnaire!K75="Quoted")=TRUE,"OK Q 32","QUERY Q 32 - Closing Unquoted Shares - Sum of transactions does not equal closing balance - please check") -> OK Q 32 | J47: =IF(OR(Questionnaire!M114=(Questionnaire!M113+Questionnaire!M52-Questionnaire!M68-Questionnaire!M72+Questionnaire!M130-Questionnaire!M143+Questionnaire!M156-Questionnaire!M157),Questionnaire!L75="Quoted")=TRUE,"OK Q 32","QUERY Q 32 - Closing Unquoted Shares - Sum of transactions does not equal closing balance - please check") -> OK Q 32 | K47: =IF(OR(Questionnaire!N114=(Questionnaire!N113+Questionnaire!N52-Questionnaire!N68-Questionnaire!N72+Questionnaire!N130-Questionnaire!N143+Questionnaire!N156-Questionnaire!N157),Questionnaire!M75="Quoted")=TRUE,"OK Q 32","QUERY Q 32 - Closing Unquoted Shares - Sum of transactions does not equal closing balance - please check") -> OK Q 32 | L47: =IF(OR(Questionnaire!O114=(Questionnaire!O113+Questionnaire!O52-Questionnaire!O68-Questionnaire!O72+Questionnaire!O130-Questionnaire!O143+Questionnaire!O156-Questionnaire!O157),Questionnaire!N75="Quoted")=TRUE,"OK Q 32","QUERY Q 32 - Closing Unquoted Shares - Sum of transactions does not equal closing balance - please check") -> OK Q 32 | ... IP47: =IF(OR(Questionnaire!IS114=(Questionnaire!IS113+Questionnaire!IS52-Questionnaire!IS68-Questionnaire!IS72+Questionnaire!IS130-Questionnaire!IS143+Questionnaire!IS156-Questionnaire!IS157),Questionnaire!IR75="Quoted")=TRUE,"OK Q 32","QUERY Q 32 - Closing Unquoted Shares - Sum of transactions does not equal closing balance - please check") -> OK Q 32
A48: =IF(LEFT(A49,2)="OK",0,IF(LEFT(A49,2)="QU",2,1)) -> 0 | B48: =IF(LEFT(B49,2)="OK",0,IF(LEFT(B49,2)="QU",2,1)) -> 0 | C48: =IF(LEFT(C49,2)="OK",0,IF(LEFT(C49,2)="QU",2,1)) -> 0 | D48: =IF(LEFT(D49,2)="OK",0,IF(LEFT(D49,2)="QU",2,1)) -> 0 | E48: =IF(LEFT(E49,2)="OK",0,IF(LEFT(E49,2)="QU",2,1)) -> 0 | F48: =IF(LEFT(F49,2)="OK",0,IF(LEFT(F49,2)="QU",2,1)) -> 0 | G48: =IF(LEFT(G49,2)="OK",0,IF(LEFT(G49,2)="QU",2,1)) -> 0 | H48: =IF(LEFT(H49,2)="OK",0,IF(LEFT(H49,2)="QU",2,1)) -> 0 | ... IP48: =IF(LEFT(IP49,2)="OK",0,IF(LEFT(IP49,2)="QU",2,1)) -> 0
A49: =IF(Questionnaire!D114=(Questionnaire!D116+Questionnaire!D117+Questionnaire!D118+Questionnaire!D119+Questionnaire!D120+Questionnaire!D121+Questionnaire!D122+Questionnaire!D123+Questionnaire!D124+Questionnaire!D125+Questionnaire!D126+Questionnaire!D127+Questionnaire!D128)=TRUE,"OK Q 32a","QUERY Q 32a - must sum to unquoted equity capital and reserves in Q32 - please check") -> OK Q 32a | B49: =IF(Questionnaire!E114=(Questionnaire!E116+Questionnaire!E117+Questionnaire!E118+Questionnaire!E119+Questionnaire!E120+Questionnaire!E121+Questionnaire!E122+Questionnaire!E123+Questionnaire!E124+Questionnaire!E125+Questionnaire!E126+Questionnaire!E127+Questionnaire!E128)=TRUE,"OK Q 32a","QUERY Q 32a - must sum to unquoted equity capital and reserves in Q32 - please check") -> OK Q 32a | C49: =IF(Questionnaire!F114=(Questionnaire!F116+Questionnaire!F117+Questionnaire!F118+Questionnaire!F119+Questionnaire!F120+Questionnaire!F121+Questionnaire!F122+Questionnaire!F123+Questionnaire!F124+Questionnaire!F125+Questionnaire!F126+Questionnaire!F127+Questionnaire!F128)=TRUE,"OK Q 32a","QUERY Q 32a - must sum to unquoted equity capital and reserves in Q32 - please check") -> OK Q 32a | D49: =IF(Questionnaire!G114=(Questionnaire!G116+Questionnaire!G117+Questionnaire!G118+Questionnaire!G119+Questionnaire!G120+Questionnaire!G121+Questionnaire!G122+Questionnaire!G123+Questionnaire!G124+Questionnaire!G125+Questionnaire!G126+Questionnaire!G127+Questionnaire!G128)=TRUE,"OK Q 32a","QUERY Q 32a - must sum to unquoted equity capital and reserves in Q32 - please check") -> OK Q 32a | E49: =IF(Questionnaire!H114=(Questionnaire!H116+Questionnaire!H117+Questionnaire!H118+Questionnaire!H119+Questionnaire!H120+Questionnaire!H121+Questionnaire!H122+Questionnaire!H123+Questionnaire!H124+Questionnaire!H125+Questionnaire!H126+Questionnaire!H127+Questionnaire!H128)=TRUE,"OK Q 32a","QUERY Q 32a - must sum to unquoted equity capital and reserves in Q32 - please check") -> OK Q 32a | F49: =IF(Questionnaire!I114=(Questionnaire!I116+Questionnaire!I117+Questionnaire!I118+Questionnaire!I119+Questionnaire!I120+Questionnaire!I121+Questionnaire!I122+Questionnaire!I123+Questionnaire!I124+Questionnaire!I125+Questionnaire!I126+Questionnaire!I127+Questionnaire!I128)=TRUE,"OK Q 32a","QUERY Q 32a - must sum to unquoted equity capital and reserves in Q32 - please check") -> OK Q 32a | G49: =IF(Questionnaire!J114=(Questionnaire!J116+Questionnaire!J117+Questionnaire!J118+Questionnaire!J119+Questionnaire!J120+Questionnaire!J121+Questionnaire!J122+Questionnaire!J123+Questionnaire!J124+Questionnaire!J125+Questionnaire!J126+Questionnaire!J127+Questionnaire!J128)=TRUE,"OK Q 32a","QUERY Q 32a - must sum to unquoted equity capital and reserves in Q32 - please check") -> OK Q 32a | H49: =IF(Questionnaire!K114=(Questionnaire!K116+Questionnaire!K117+Questionnaire!K118+Questionnaire!K119+Questionnaire!K120+Questionnaire!K121+Questionnaire!K122+Questionnaire!K123+Questionnaire!K124+Questionnaire!K125+Questionnaire!K126+Questionnaire!K127+Questionnaire!K128)=TRUE,"OK Q 32a","QUERY Q 32a - must sum to unquoted equity capital and reserves in Q32 - please check") -> OK Q 32a | ... IP49: =IF(Questionnaire!IS114=(Questionnaire!IS116+Questionnaire!IS117+Questionnaire!IS118+Questionnaire!IS119+Questionnaire!IS120+Questionnaire!IS121+Questionnaire!IS122+Questionnaire!IS123+Questionnaire!IS124+Questionnaire!IS125+Questionnaire!IS126+Questionnaire!IS127+Questionnaire!IS128)=TRUE,"OK Q 32a","QUERY Q 32a - must sum to unquoted equity capital and reserves in Q32 - please check") -> OK Q 32a
A50: =IF(LEFT(A51,2)="OK",0,IF(LEFT(A51,2)="WA",2,1)) -> 2 | B50: =IF(LEFT(B51,2)="OK",0,IF(LEFT(B51,2)="WA",2,1)) -> 0 | C50: =IF(LEFT(C51,2)="OK",0,IF(LEFT(C51,2)="WA",2,1)) -> 0 | D50: =IF(LEFT(D51,2)="OK",0,IF(LEFT(D51,2)="WA",2,1)) -> 0 | E50: =IF(LEFT(E51,2)="OK",0,IF(LEFT(E51,2)="WA",2,1)) -> 0 | F50: =IF(LEFT(F51,2)="OK",0,IF(LEFT(F51,2)="WA",2,1)) -> 0 | G50: =IF(LEFT(G51,2)="OK",0,IF(LEFT(G51,2)="WA",2,1)) -> 0 | H50: =IF(LEFT(H51,2)="OK",0,IF(LEFT(H51,2)="WA",2,1)) -> 0 | ... IP50: =IF(LEFT(IP51,2)="OK",0,IF(LEFT(IP51,2)="WA",2,1)) -> 0
A51: =IF(ABS((Questionnaire!D130+Questionnaire!D82))>100,"WARNING Variable 2311/Q 29a & 33a - Net acquisitions in equity capital are greater than £100m - please check","OK - Net acquisitions in equity capital") -> WARNING Variable 2311/Q 29a & 33a - Net acquisitions in equity capital are greater than £100m - please check | B51: =IF(ABS((Questionnaire!E130+Questionnaire!E82))>100,"WARNING Variable 2311/Q 29a & 33a - Net acquisitions in equity capital are greater than £100m - please check","OK - Net acquisitions in equity capital") -> OK - Net acquisitions in equity capital | C51: =IF(ABS((Questionnaire!F130+Questionnaire!F82))>100,"WARNING Variable 2311/Q 29a & 33a - Net acquisitions in equity capital are greater than £100m - please check","OK - Net acquisitions in equity capital") -> OK - Net acquisitions in equity capital | D51: =IF(ABS((Questionnaire!G130+Questionnaire!G82))>100,"WARNING Variable 2311/Q 29a & 33a - Net acquisitions in equity capital are greater than £100m - please check","OK - Net acquisitions in equity capital") -> OK - Net acquisitions in equity capital | E51: =IF(ABS((Questionnaire!H130+Questionnaire!H82))>100,"WARNING Variable 2311/Q 29a & 33a - Net acquisitions in equity capital are greater than £100m - please check","OK - Net acquisitions in equity capital") -> OK - Net acquisitions in equity capital | F51: =IF(ABS((Questionnaire!I130+Questionnaire!I82))>100,"WARNING Variable 2311/Q 29a & 33a - Net acquisitions in equity capital are greater than £100m - please check","OK - Net acquisitions in equity capital") -> OK - Net acquisitions in equity capital | G51: =IF(ABS((Questionnaire!J130+Questionnaire!J82))>100,"WARNING Variable 2311/Q 29a & 33a - Net acquisitions in equity capital are greater than £100m - please check","OK - Net acquisitions in equity capital") -> OK - Net acquisitions in equity capital | H51: =IF(ABS((Questionnaire!K130+Questionnaire!K82))>100,"WARNING Variable 2311/Q 29a & 33a - Net acquisitions in equity capital are greater than £100m - please check","OK - Net acquisitions in equity capital") -> OK - Net acquisitions in equity capital | ... IP51: =IF(ABS((Questionnaire!IS130+Questionnaire!IS82))>100,"WARNING Variable 2311/Q 29a & 33a - Net acquisitions in equity capital are greater than £100m - please check","OK - Net acquisitions in equity capital") -> OK - Net acquisitions in equity capital
A52: =IF(LEFT(A53,2)="OK",0,IF(LEFT(A53,2)="QU",2,1)) -> 0 | B52: =IF(LEFT(B53,2)="OK",0,IF(LEFT(B53,2)="QU",2,1)) -> 0 | C52: =IF(LEFT(C53,2)="OK",0,IF(LEFT(C53,2)="QU",2,1)) -> 0 | D52: =IF(LEFT(D53,2)="OK",0,IF(LEFT(D53,2)="QU",2,1)) -> 0 | E52: =IF(LEFT(E53,2)="OK",0,IF(LEFT(E53,2)="QU",2,1)) -> 0 | F52: =IF(LEFT(F53,2)="OK",0,IF(LEFT(F53,2)="QU",2,1)) -> 0 | G52: =IF(LEFT(G53,2)="OK",0,IF(LEFT(G53,2)="QU",2,1)) -> 0 | H52: =IF(LEFT(H53,2)="OK",0,IF(LEFT(H53,2)="QU",2,1)) -> 0 | ... IP52: =IF(LEFT(IP53,2)="OK",0,IF(LEFT(IP53,2)="QU",2,1)) -> 0
A53: =IF(Questionnaire!D130=(Questionnaire!D132+Questionnaire!D133+Questionnaire!D134+Questionnaire!D135)=TRUE,"OK Q33.a.i","QUERY Q33.a - Components in 33a.i must sum to acquisitions of unquoted equity capital total value in 33.a - please check") -> OK Q33.a.i | B53: =IF(Questionnaire!E130=(Questionnaire!E132+Questionnaire!E133+Questionnaire!E134+Questionnaire!E135)=TRUE,"OK Q33.a.i","QUERY Q33.a - Components in 33a.i must sum to acquisitions of unquoted equity capital total value in 33.a - please check") -> OK Q33.a.i | C53: =IF(Questionnaire!F130=(Questionnaire!F132+Questionnaire!F133+Questionnaire!F134+Questionnaire!F135)=TRUE,"OK Q33.a.i","QUERY Q33.a - Components in 33a.i must sum to acquisitions of unquoted equity capital total value in 33.a - please check") -> OK Q33.a.i | D53: =IF(Questionnaire!G130=(Questionnaire!G132+Questionnaire!G133+Questionnaire!G134+Questionnaire!G135)=TRUE,"OK Q33.a.i","QUERY Q33.a - Components in 33a.i must sum to acquisitions of unquoted equity capital total value in 33.a - please check") -> OK Q33.a.i | E53: =IF(Questionnaire!H130=(Questionnaire!H132+Questionnaire!H133+Questionnaire!H134+Questionnaire!H135)=TRUE,"OK Q33.a.i","QUERY Q33.a - Components in 33a.i must sum to acquisitions of unquoted equity capital total value in 33.a - please check") -> OK Q33.a.i | F53: =IF(Questionnaire!I130=(Questionnaire!I132+Questionnaire!I133+Questionnaire!I134+Questionnaire!I135)=TRUE,"OK Q33.a.i","QUERY Q33.a - Components in 33a.i must sum to acquisitions of unquoted equity capital total value in 33.a - please check") -> OK Q33.a.i | G53: =IF(Questionnaire!J130=(Questionnaire!J132+Questionnaire!J133+Questionnaire!J134+Questionnaire!J135)=TRUE,"OK Q33.a.i","QUERY Q33.a - Components in 33a.i must sum to acquisitions of unquoted equity capital total value in 33.a - please check") -> OK Q33.a.i | H53: =IF(Questionnaire!K130=(Questionnaire!K132+Questionnaire!K133+Questionnaire!K134+Questionnaire!K135)=TRUE,"OK Q33.a.i","QUERY Q33.a - Components in 33a.i must sum to acquisitions of unquoted equity capital total value in 33.a - please check") -> OK Q33.a.i | ... IP53: =IF(Questionnaire!IS130=(Questionnaire!IS132+Questionnaire!IS133+Questionnaire!IS134+Questionnaire!IS135)=TRUE,"OK Q33.a.i","QUERY Q33.a - Components in 33a.i must sum to acquisitions of unquoted equity capital total value in 33.a - please check") -> OK Q33.a.i
A54: =IF(LEFT(A55,2)="OK",0,IF(LEFT(A55,2)="QU",2,1)) -> 0 | B54: =IF(LEFT(B55,2)="OK",0,IF(LEFT(B55,2)="WA",2,1)) -> 0 | C54: =IF(LEFT(C55,2)="OK",0,IF(LEFT(C55,2)="QU",2,1)) -> 0 | D54: =IF(LEFT(D55,2)="OK",0,IF(LEFT(D55,2)="QU",2,1)) -> 0 | E54: =IF(LEFT(E55,2)="OK",0,IF(LEFT(E55,2)="QU",2,1)) -> 0 | F54: =IF(LEFT(F55,2)="OK",0,IF(LEFT(F55,2)="QU",2,1)) -> 0 | G54: =IF(LEFT(G55,2)="OK",0,IF(LEFT(G55,2)="QU",2,1)) -> 0 | H54: =IF(LEFT(H55,2)="OK",0,IF(LEFT(H55,2)="QU",2,1)) -> 0 | I54: =IF(LEFT(I55,2)="OK",0,IF(LEFT(I55,2)="QU",2,1)) -> 0 | J54: =IF(LEFT(J55,2)="OK",0,IF(LEFT(J55,2)="QU",2,1)) -> 0 | ... IP54: =IF(LEFT(IP55,2)="OK",0,IF(LEFT(IP55,2)="QU",2,1)) -> 0
A55: =IF(Questionnaire!D130=(Questionnaire!D138+Questionnaire!D139+Questionnaire!D140+Questionnaire!D141)=TRUE,"OK Q33.a.ii","QUERY Q33b - Components in 33.a.ii must sum to acquisitions of unquoted equity capital total value in 33.a - please check") -> OK Q33.a.ii | B55: =IF(Questionnaire!E130=(Questionnaire!E138+Questionnaire!E139+Questionnaire!E140+Questionnaire!E141)=TRUE,"OK Q33.a.ii","QUERY Q33b - Components in 33.a.ii must sum to acquisitions of unquoted equity capital total value in 33.a - please check") -> OK Q33.a.ii | C55: =IF(Questionnaire!F130=(Questionnaire!F138+Questionnaire!F139+Questionnaire!F140+Questionnaire!F141)=TRUE,"OK Q33.a.ii","QUERY Q33b - Components in 33.a.ii must sum to acquisitions of unquoted equity capital total value in 33.a - please check") -> OK Q33.a.ii | D55: =IF(Questionnaire!G130=(Questionnaire!G138+Questionnaire!G139+Questionnaire!G140+Questionnaire!G141)=TRUE,"OK Q33.a.ii","QUERY Q33b - Components in 33.a.ii must sum to acquisitions of unquoted equity capital total value in 33.a - please check") -> OK Q33.a.ii | E55: =IF(Questionnaire!H130=(Questionnaire!H138+Questionnaire!H139+Questionnaire!H140+Questionnaire!H141)=TRUE,"OK Q33.a.ii","QUERY Q33b - Components in 33.a.ii must sum to acquisitions of unquoted equity capital total value in 33.a - please check") -> OK Q33.a.ii | F55: =IF(Questionnaire!I130=(Questionnaire!I138+Questionnaire!I139+Questionnaire!I140+Questionnaire!I141)=TRUE,"OK Q33.a.ii","QUERY Q33b - Components in 33.a.ii must sum to acquisitions of unquoted equity capital total value in 33.a - please check") -> OK Q33.a.ii | G55: =IF(Questionnaire!J130=(Questionnaire!J138+Questionnaire!J139+Questionnaire!J140+Questionnaire!J141)=TRUE,"OK Q33.a.ii","QUERY Q33b - Components in 33.a.ii must sum to acquisitions of unquoted equity capital total value in 33.a - please check") -> OK Q33.a.ii | H55: =IF(Questionnaire!K130=(Questionnaire!K138+Questionnaire!K139+Questionnaire!K140+Questionnaire!K141)=TRUE,"OK Q33.a.ii","QUERY Q33b - Components in 33.a.ii must sum to acquisitions of unquoted equity capital total value in 33.a - please check") -> OK Q33.a.ii | ... IP55: =IF(Questionnaire!IS130=(Questionnaire!IS138+Questionnaire!IS139+Questionnaire!IS140+Questionnaire!IS141)=TRUE,"OK Q33.a.ii","QUERY Q33b - Components in 33.a.ii must sum to acquisitions of unquoted equity capital total value in 33.a - please check") -> OK Q33.a.ii
A56: =IF(LEFT(A57,2)="OK",0,IF(LEFT(A57,2)="WA",2,1)) -> 0 | B56: =IF(LEFT(B57,2)="OK",0,IF(LEFT(B57,2)="WA",2,1)) -> 0 | C56: =IF(LEFT(C57,2)="OK",0,IF(LEFT(C57,2)="WA",2,1)) -> 0 | D56: =IF(LEFT(D57,2)="OK",0,IF(LEFT(D57,2)="WA",2,1)) -> 0 | E56: =IF(LEFT(E57,2)="OK",0,IF(LEFT(E57,2)="WA",2,1)) -> 0 | F56: =IF(LEFT(F57,2)="OK",0,IF(LEFT(F57,2)="WA",2,1)) -> 0 | G56: =IF(LEFT(G57,2)="OK",0,IF(LEFT(G57,2)="WA",2,1)) -> 0 | H56: =IF(LEFT(H57,2)="OK",0,IF(LEFT(H57,2)="WA",2,1)) -> 0 | ... IP56: =IF(LEFT(IP57,2)="OK",0,IF(LEFT(IP57,2)="WA",2,1)) -> 0
A57: =IF(ABS(Questionnaire!D95+Questionnaire!D143)>100,"WARNING Variable 2312/Q 29b & 33b - Net disposals in equity capital are greater than £100m - please check","OK - Net disposals in equity capital") -> OK - Net disposals in equity capital | B57: =IF(ABS(Questionnaire!E95+Questionnaire!E143)>100,"WARNING Variable 2312/Q 29b & 33b - Net disposals in equity capital are greater than £100m - please check","OK - Net disposals in equity capital") -> OK - Net disposals in equity capital | C57: =IF(ABS(Questionnaire!F95+Questionnaire!F143)>100,"WARNING Variable 2312/Q 29b & 33b - Net disposals in equity capital are greater than £100m - please check","OK - Net disposals in equity capital") -> OK - Net disposals in equity capital | D57: =IF(ABS(Questionnaire!G95+Questionnaire!G143)>100,"WARNING Variable 2312/Q 29b & 33b - Net disposals in equity capital are greater than £100m - please check","OK - Net disposals in equity capital") -> OK - Net disposals in equity capital | E57: =IF(ABS(Questionnaire!H95+Questionnaire!H143)>100,"WARNING Variable 2312/Q 29b & 33b - Net disposals in equity capital are greater than £100m - please check","OK - Net disposals in equity capital") -> OK - Net disposals in equity capital | F57: =IF(ABS(Questionnaire!I95+Questionnaire!I143)>100,"WARNING Variable 2312/Q 29b & 33b - Net disposals in equity capital are greater than £100m - please check","OK - Net disposals in equity capital") -> OK - Net disposals in equity capital | G57: =IF(ABS(Questionnaire!J95+Questionnaire!J143)>100,"WARNING Variable 2312/Q 29b & 33b - Net disposals in equity capital are greater than £100m - please check","OK - Net disposals in equity capital") -> OK - Net disposals in equity capital | H57: =IF(ABS(Questionnaire!K95+Questionnaire!K143)>100,"WARNING Variable 2312/Q 29b & 33b - Net disposals in equity capital are greater than £100m - please check","OK - Net disposals in equity capital") -> OK - Net disposals in equity capital | ... IP57: =IF(ABS(Questionnaire!IS95+Questionnaire!IS143)>100,"WARNING Variable 2312/Q 29b & 33b - Net disposals in equity capital are greater than £100m - please check","OK - Net disposals in equity capital") -> OK - Net disposals in equity capital
A58: =IF(LEFT(A59,2)="OK",0,IF(LEFT(A59,2)="QU",2,1)) -> 0 | B58: =IF(LEFT(B59,2)="OK",0,IF(LEFT(B59,2)="QU",2,1)) -> 0 | C58: =IF(LEFT(C59,2)="OK",0,IF(LEFT(C59,2)="QU",2,1)) -> 0 | D58: =IF(LEFT(D59,2)="OK",0,IF(LEFT(D59,2)="QU",2,1)) -> 0 | E58: =IF(LEFT(E59,2)="OK",0,IF(LEFT(E59,2)="QU",2,1)) -> 0 | F58: =IF(LEFT(F59,2)="OK",0,IF(LEFT(F59,2)="QU",2,1)) -> 0 | G58: =IF(LEFT(G59,2)="OK",0,IF(LEFT(G59,2)="QU",2,1)) -> 0 | H58: =IF(LEFT(H59,2)="OK",0,IF(LEFT(H59,2)="QU",2,1)) -> 0 | ... IP58: =IF(LEFT(IP59,2)="OK",0,IF(LEFT(IP59,2)="QU",2,1)) -> 0
A59: =IF(Questionnaire!D143=(Questionnaire!D145+Questionnaire!D146+Questionnaire!D147)=TRUE,"OK Q33.b.i","QUERY Q33b - Components in 33.b.i must sum to acquisitions of unquoted equity capital total value in 33.b - please check") -> OK Q33.b.i | B59: =IF(Questionnaire!E143=(Questionnaire!E145+Questionnaire!E146+Questionnaire!E147)=TRUE,"OK Q33.b.i","QUERY Q33b - Components in 33.b.i must sum to acquisitions of unquoted equity capital total value in 33.b - please check") -> OK Q33.b.i | C59: =IF(Questionnaire!F143=(Questionnaire!F145+Questionnaire!F146+Questionnaire!F147)=TRUE,"OK Q33.b.i","QUERY Q33b - Components in 33.b.i must sum to acquisitions of unquoted equity capital total value in 33.b - please check") -> OK Q33.b.i | D59: =IF(Questionnaire!G143=(Questionnaire!G145+Questionnaire!G146+Questionnaire!G147)=TRUE,"OK Q33.b.i","QUERY Q33b - Components in 33.b.i must sum to acquisitions of unquoted equity capital total value in 33.b - please check") -> OK Q33.b.i | E59: =IF(Questionnaire!H143=(Questionnaire!H145+Questionnaire!H146+Questionnaire!H147)=TRUE,"OK Q33.b.i","QUERY Q33b - Components in 33.b.i must sum to acquisitions of unquoted equity capital total value in 33.b - please check") -> OK Q33.b.i | F59: =IF(Questionnaire!I143=(Questionnaire!I145+Questionnaire!I146+Questionnaire!I147)=TRUE,"OK Q33.b.i","QUERY Q33b - Components in 33.b.i must sum to acquisitions of unquoted equity capital total value in 33.b - please check") -> OK Q33.b.i | G59: =IF(Questionnaire!J143=(Questionnaire!J145+Questionnaire!J146+Questionnaire!J147)=TRUE,"OK Q33.b.i","QUERY Q33b - Components in 33.b.i must sum to acquisitions of unquoted equity capital total value in 33.b - please check") -> OK Q33.b.i | H59: =IF(Questionnaire!K143=(Questionnaire!K145+Questionnaire!K146+Questionnaire!K147)=TRUE,"OK Q33.b.i","QUERY Q33b - Components in 33.b.i must sum to acquisitions of unquoted equity capital total value in 33.b - please check") -> OK Q33.b.i | ... IP59: =IF(Questionnaire!IS143=(Questionnaire!IS145+Questionnaire!IS146+Questionnaire!IS147)=TRUE,"OK Q33.b.i","QUERY Q33b - Components in 33.b.i must sum to acquisitions of unquoted equity capital total value in 33.b - please check") -> OK Q33.b.i
A60: =IF(LEFT(A61,2)="OK",0,IF(LEFT(A61,2)="QU",2,1)) -> 0 | B60: =IF(LEFT(B61,2)="OK",0,IF(LEFT(B61,2)="QU",2,1)) -> 0 | C60: =IF(LEFT(C61,2)="OK",0,IF(LEFT(C61,2)="QU",2,1)) -> 0 | D60: =IF(LEFT(D61,2)="OK",0,IF(LEFT(D61,2)="QU",2,1)) -> 0 | E60: =IF(LEFT(E61,2)="OK",0,IF(LEFT(E61,2)="QU",2,1)) -> 0 | F60: =IF(LEFT(F61,2)="OK",0,IF(LEFT(F61,2)="QU",2,1)) -> 0 | G60: =IF(LEFT(G61,2)="OK",0,IF(LEFT(G61,2)="QU",2,1)) -> 0 | H60: =IF(LEFT(H61,2)="OK",0,IF(LEFT(H61,2)="QU",2,1)) -> 0 | ... IP60: =IF(LEFT(IP61,2)="OK",0,IF(LEFT(IP61,2)="QU",2,1)) -> 0
A61: =IF(Questionnaire!D143=(Questionnaire!D150+Questionnaire!D151+Questionnaire!D152+Questionnaire!D153)=TRUE,"OK Q33.b.ii","QUERY Q33b - Components in 33.b.ii must sum to acquisitions of unquoted equity capital total value in 33.b - please check") -> OK Q33.b.ii | B61: =IF(Questionnaire!E143=(Questionnaire!E150+Questionnaire!E151+Questionnaire!E152+Questionnaire!E153)=TRUE,"OK Q33.b.ii","QUERY Q33b - Components in 33.b.ii must sum to acquisitions of unquoted equity capital total value in 33.b - please check") -> OK Q33.b.ii | C61: =IF(Questionnaire!F143=(Questionnaire!F150+Questionnaire!F151+Questionnaire!F152+Questionnaire!F153)=TRUE,"OK Q33.b.ii","QUERY Q33b - Components in 33.b.ii must sum to acquisitions of unquoted equity capital total value in 33.b - please check") -> OK Q33.b.ii | D61: =IF(Questionnaire!G143=(Questionnaire!G150+Questionnaire!G151+Questionnaire!G152+Questionnaire!G153)=TRUE,"OK Q33.b.ii","QUERY Q33b - Components in 33.b.ii must sum to acquisitions of unquoted equity capital total value in 33.b - please check") -> OK Q33.b.ii | E61: =IF(Questionnaire!H143=(Questionnaire!H150+Questionnaire!H151+Questionnaire!H152+Questionnaire!H153)=TRUE,"OK Q33.b.ii","QUERY Q33b - Components in 33.b.ii must sum to acquisitions of unquoted equity capital total value in 33.b - please check") -> OK Q33.b.ii | F61: =IF(Questionnaire!I143=(Questionnaire!I150+Questionnaire!I151+Questionnaire!I152+Questionnaire!I153)=TRUE,"OK Q33.b.ii","QUERY Q33b - Components in 33.b.ii must sum to acquisitions of unquoted equity capital total value in 33.b - please check") -> OK Q33.b.ii | G61: =IF(Questionnaire!J143=(Questionnaire!J150+Questionnaire!J151+Questionnaire!J152+Questionnaire!J153)=TRUE,"OK Q33.b.ii","QUERY Q33b - Components in 33.b.ii must sum to acquisitions of unquoted equity capital total value in 33.b - please check") -> OK Q33.b.ii | H61: =IF(Questionnaire!K143=(Questionnaire!K150+Questionnaire!K151+Questionnaire!K152+Questionnaire!K153)=TRUE,"OK Q33.b.ii","QUERY Q33b - Components in 33.b.ii must sum to acquisitions of unquoted equity capital total value in 33.b - please check") -> OK Q33.b.ii | ... IP61: =IF(Questionnaire!IS143=(Questionnaire!IS150+Questionnaire!IS151+Questionnaire!IS152+Questionnaire!IS153)=TRUE,"OK Q33.b.ii","QUERY Q33b - Components in 33.b.ii must sum to acquisitions of unquoted equity capital total value in 33.b - please check") -> OK Q33.b.ii
A62: =IF(LEFT(A63,2)="OK",0,IF(LEFT(A63,2)="WA",2,1)) -> 2 | B62: =IF(LEFT(B63,2)="OK",0,IF(LEFT(B63,2)="WA",2,1)) -> 0 | C62: =IF(LEFT(C63,2)="OK",0,IF(LEFT(C63,2)="WA",2,1)) -> 0 | D62: =IF(LEFT(D63,2)="OK",0,IF(LEFT(D63,2)="WA",2,1)) -> 0 | E62: =IF(LEFT(E63,2)="OK",0,IF(LEFT(E63,2)="WA",2,1)) -> 0 | F62: =IF(LEFT(F63,2)="OK",0,IF(LEFT(F63,2)="WA",2,1)) -> 0 | G62: =IF(LEFT(G63,2)="OK",0,IF(LEFT(G63,2)="WA",2,1)) -> 0 | H62: =IF(LEFT(H63,2)="OK",0,IF(LEFT(H63,2)="WA",2,1)) -> 0 | ... IP62: =IF(LEFT(IP63,2)="OK",0,IF(LEFT(IP63,2)="WA",2,1)) -> 0
A63: =IF(ABS(((Questionnaire!D82)+(Questionnaire!D130))-((Questionnaire!D143)+(Questionnaire!D95)))>100,"WARNING Q 29 & 33 - Net transactions in equity capital are greater than £100m - please check","OK - Net transactions in equity capital") -> WARNING Q 29 & 33 - Net transactions in equity capital are greater than £100m - please check | B63: =IF(ABS(((Questionnaire!E82)+(Questionnaire!E130))-((Questionnaire!E143)+(Questionnaire!E95)))>100,"WARNING Q 29 & 33 - Net transactions in equity capital are greater than £100m - please check","OK - Net transactions in equity capital") -> OK - Net transactions in equity capital | C63: =IF(ABS(((Questionnaire!F82)+(Questionnaire!F130))-((Questionnaire!F143)+(Questionnaire!F95)))>100,"WARNING Q 29 & 33 - Net transactions in equity capital are greater than £100m - please check","OK - Net transactions in equity capital") -> OK - Net transactions in equity capital | D63: =IF(ABS(((Questionnaire!G82)+(Questionnaire!G130))-((Questionnaire!G143)+(Questionnaire!G95)))>100,"WARNING Q 29 & 33 - Net transactions in equity capital are greater than £100m - please check","OK - Net transactions in equity capital") -> OK - Net transactions in equity capital | E63: =IF(ABS(((Questionnaire!H82)+(Questionnaire!H130))-((Questionnaire!H143)+(Questionnaire!H95)))>100,"WARNING Q 29 & 33 - Net transactions in equity capital are greater than £100m - please check","OK - Net transactions in equity capital") -> OK - Net transactions in equity capital | F63: =IF(ABS(((Questionnaire!I82)+(Questionnaire!I130))-((Questionnaire!I143)+(Questionnaire!I95)))>100,"WARNING Q 29 & 33 - Net transactions in equity capital are greater than £100m - please check","OK - Net transactions in equity capital") -> OK - Net transactions in equity capital | G63: =IF(ABS(((Questionnaire!J82)+(Questionnaire!J130))-((Questionnaire!J143)+(Questionnaire!J95)))>100,"WARNING Q 29 & 33 - Net transactions in equity capital are greater than £100m - please check","OK - Net transactions in equity capital") -> OK - Net transactions in equity capital | H63: =IF(ABS(((Questionnaire!K82)+(Questionnaire!K130))-((Questionnaire!K143)+(Questionnaire!K95)))>100,"WARNING Q 29 & 33 - Net transactions in equity capital are greater than £100m - please check","OK - Net transactions in equity capital") -> OK - Net transactions in equity capital | ... IP63: =IF(ABS(((Questionnaire!IS82)+(Questionnaire!IS130))-((Questionnaire!IS143)+(Questionnaire!IS95)))>100,"WARNING Q 29 & 33 - Net transactions in equity capital are greater than £100m - please check","OK - Net transactions in equity capital") -> OK - Net transactions in equity capital
A64: =IF(LEFT(A65,2)="OK",0,IF(LEFT(A65,2)="WA",2,1)) -> 2 | B64: =IF(LEFT(B65,2)="OK",0,IF(LEFT(B65,2)="WA",2,1)) -> 0 | C64: =IF(LEFT(C65,2)="OK",0,IF(LEFT(C65,2)="WA",2,1)) -> 0 | D64: =IF(LEFT(D65,2)="OK",0,IF(LEFT(D65,2)="WA",2,1)) -> 0 | E64: =IF(LEFT(E65,2)="OK",0,IF(LEFT(E65,2)="WA",2,1)) -> 0 | F64: =IF(LEFT(F65,2)="OK",0,IF(LEFT(F65,2)="WA",2,1)) -> 0 | G64: =IF(LEFT(G65,2)="OK",0,IF(LEFT(G65,2)="WA",2,1)) -> 0 | H64: =IF(LEFT(H65,2)="OK",0,IF(LEFT(H65,2)="WA",2,1)) -> 0 | ... IP64: =IF(LEFT(IP65,2)="OK",0,IF(LEFT(IP65,2)="WA",2,1)) -> 0
A65: =IF(ABS(Questionnaire!D78+Questionnaire!D113+Questionnaire!D52-Questionnaire!D68-Questionnaire!D72+Questionnaire!D82-Questionnaire!D95+Questionnaire!D108-Questionnaire!D109+Questionnaire!D156-Questionnaire!D157+Questionnaire!D130-Questionnaire!D143)>200,"WARNING - Net change in equity capital & reserves is greater than £200m - please check","OK - Net change in equity capital and reserves") -> WARNING - Net change in equity capital & reserves is greater than £200m - please check | B65: =IF(ABS(Questionnaire!E78+Questionnaire!E113+Questionnaire!E52-Questionnaire!E68-Questionnaire!E72+Questionnaire!E82-Questionnaire!E95+Questionnaire!E108-Questionnaire!E109+Questionnaire!E156-Questionnaire!E157+Questionnaire!E130-Questionnaire!E143)>200,"WARNING - Net change in equity capital & reserves is greater than £200m - please check","OK - Net change in equity capital and reserves") -> OK - Net change in equity capital and reserves | C65: =IF(ABS(Questionnaire!F78+Questionnaire!F113+Questionnaire!F52-Questionnaire!F68-Questionnaire!F72+Questionnaire!F82-Questionnaire!F95+Questionnaire!F108-Questionnaire!F109+Questionnaire!F156-Questionnaire!F157+Questionnaire!F130-Questionnaire!F143)>200,"WARNING - Net change in equity capital & reserves is greater than £200m - please check","OK - Net change in equity capital and reserves") -> OK - Net change in equity capital and reserves | D65: =IF(ABS(Questionnaire!G78+Questionnaire!G113+Questionnaire!G52-Questionnaire!G68-Questionnaire!G72+Questionnaire!G82-Questionnaire!G95+Questionnaire!G108-Questionnaire!G109+Questionnaire!G156-Questionnaire!G157+Questionnaire!G130-Questionnaire!G143)>200,"WARNING - Net change in equity capital & reserves is greater than £200m - please check","OK - Net change in equity capital and reserves") -> OK - Net change in equity capital and reserves | E65: =IF(ABS(Questionnaire!H78+Questionnaire!H113+Questionnaire!H52-Questionnaire!H68-Questionnaire!H72+Questionnaire!H82-Questionnaire!H95+Questionnaire!H108-Questionnaire!H109+Questionnaire!H156-Questionnaire!H157+Questionnaire!H130-Questionnaire!H143)>200,"WARNING - Net change in equity capital & reserves is greater than £200m - please check","OK - Net change in equity capital and reserves") -> OK - Net change in equity capital and reserves | F65: =IF(ABS(Questionnaire!I78+Questionnaire!I113+Questionnaire!I52-Questionnaire!I68-Questionnaire!I72+Questionnaire!I82-Questionnaire!I95+Questionnaire!I108-Questionnaire!I109+Questionnaire!I156-Questionnaire!I157+Questionnaire!I130-Questionnaire!I143)>200,"WARNING - Net change in equity capital & reserves is greater than £200m - please check","OK - Net change in equity capital and reserves") -> OK - Net change in equity capital and reserves | G65: =IF(ABS(Questionnaire!J78+Questionnaire!J113+Questionnaire!J52-Questionnaire!J68-Questionnaire!J72+Questionnaire!J82-Questionnaire!J95+Questionnaire!J108-Questionnaire!J109+Questionnaire!J156-Questionnaire!J157+Questionnaire!J130-Questionnaire!J143)>200,"WARNING - Net change in equity capital & reserves is greater than £200m - please check","OK - Net change in equity capital and reserves") -> OK - Net change in equity capital and reserves | H65: =IF(ABS(Questionnaire!K78+Questionnaire!K113+Questionnaire!K52-Questionnaire!K68-Questionnaire!K72+Questionnaire!K82-Questionnaire!K95+Questionnaire!K108-Questionnaire!K109+Questionnaire!K156-Questionnaire!K157+Questionnaire!K130-Questionnaire!K143)>200,"WARNING - Net change in equity capital & reserves is greater than £200m - please check","OK - Net change in equity capital and reserves") -> OK - Net change in equity capital and reserves | ... IP65: =IF(ABS(Questionnaire!IS78+Questionnaire!IS113+Questionnaire!IS52-Questionnaire!IS68-Questionnaire!IS72+Questionnaire!IS82-Questionnaire!IS95+Questionnaire!IS108-Questionnaire!IS109+Questionnaire!IS156-Questionnaire!IS157+Questionnaire!IS130-Questionnaire!IS143)>200,"WARNING - Net change in equity capital & reserves is greater than £200m - please check","OK - Net change in equity capital and reserves") -> OK - Net change in equity capital and reserves
A66: =IF(LEFT(A67,2)="OK",0,IF(LEFT(A67,2)="WA",2,1)) -> 0 | B66: =IF(LEFT(B67,2)="OK",0,IF(LEFT(B67,2)="WA",2,1)) -> 0 | C66: =IF(LEFT(C67,2)="OK",0,IF(LEFT(C67,2)="WA",2,1)) -> 0 | D66: =IF(LEFT(D67,2)="OK",0,IF(LEFT(D67,2)="WA",2,1)) -> 0 | E66: =IF(LEFT(E67,2)="OK",0,IF(LEFT(E67,2)="WA",2,1)) -> 0 | F66: =IF(LEFT(F67,2)="OK",0,IF(LEFT(F67,2)="WA",2,1)) -> 0 | G66: =IF(LEFT(G67,2)="OK",0,IF(LEFT(G67,2)="WA",2,1)) -> 0 | H66: =IF(LEFT(H67,2)="OK",0,IF(LEFT(H67,2)="WA",2,1)) -> 0 | ... IP66: =IF(LEFT(IP67,2)="OK",0,IF(LEFT(IP67,2)="WA",2,1)) -> 0
A67: =IF(ABS(Questionnaire!D162-Questionnaire!D161)>200,"WARNING Q 35 & 36 - Net change in preference shares etc. is greater than £200m - please check","OK - Net change in preference shares etc.") -> OK - Net change in preference shares etc. | B67: =IF(ABS(Questionnaire!E162-Questionnaire!E161)>200,"WARNING Q 35 & 36 - Net change in preference shares etc. is greater than £200m - please check","OK - Net change in preference shares etc.") -> OK - Net change in preference shares etc. | C67: =IF(ABS(Questionnaire!F162-Questionnaire!F161)>200,"WARNING Q 35 & 36 - Net change in preference shares etc. is greater than £200m - please check","OK - Net change in preference shares etc.") -> OK - Net change in preference shares etc. | D67: =IF(ABS(Questionnaire!G162-Questionnaire!G161)>200,"WARNING Q 35 & 36 - Net change in preference shares etc. is greater than £200m - please check","OK - Net change in preference shares etc.") -> OK - Net change in preference shares etc. | E67: =IF(ABS(Questionnaire!H162-Questionnaire!H161)>200,"WARNING Q 35 & 36 - Net change in preference shares etc. is greater than £200m - please check","OK - Net change in preference shares etc.") -> OK - Net change in preference shares etc. | F67: =IF(ABS(Questionnaire!I162-Questionnaire!I161)>200,"WARNING Q 35 & 36 - Net change in preference shares etc. is greater than £200m - please check","OK - Net change in preference shares etc.") -> OK - Net change in preference shares etc. | G67: =IF(ABS(Questionnaire!J162-Questionnaire!J161)>200,"WARNING Q 35 & 36 - Net change in preference shares etc. is greater than £200m - please check","OK - Net change in preference shares etc.") -> OK - Net change in preference shares etc. | H67: =IF(ABS(Questionnaire!K162-Questionnaire!K161)>200,"WARNING Q 35 & 36 - Net change in preference shares etc. is greater than £200m - please check","OK - Net change in preference shares etc.") -> OK - Net change in preference shares etc. | ... IP67: =IF(ABS(Questionnaire!IS162-Questionnaire!IS161)>200,"WARNING Q 35 & 36 - Net change in preference shares etc. is greater than £200m - please check","OK - Net change in preference shares etc.") -> OK - Net change in preference shares etc.
A68: =IF(LEFT(A69,2)="OK",0,IF(LEFT(A69,2)="QU",2,1)) -> 0 | B68: =IF(LEFT(B69,2)="OK",0,IF(LEFT(B69,2)="QU",2,1)) -> 0 | C68: =IF(LEFT(C69,2)="OK",0,IF(LEFT(C69,2)="QU",2,1)) -> 0 | D68: =IF(LEFT(D69,2)="OK",0,IF(LEFT(D69,2)="QU",2,1)) -> 0 | E68: =IF(LEFT(E69,2)="OK",0,IF(LEFT(E69,2)="QU",2,1)) -> 0 | F68: =IF(LEFT(F69,2)="OK",0,IF(LEFT(F69,2)="QU",2,1)) -> 0 | G68: =IF(LEFT(G69,2)="OK",0,IF(LEFT(G69,2)="QU",2,1)) -> 0 | H68: =IF(LEFT(H69,2)="OK",0,IF(LEFT(H69,2)="QU",2,1)) -> 0 | ... IP68: =IF(LEFT(IP69,2)="OK",0,IF(LEFT(IP69,2)="QU",2,1)) -> 0
A69: =IF(Questionnaire!D161+Questionnaire!D163-Questionnaire!D164+Questionnaire!D166-Questionnaire!D167=Questionnaire!D162,"OK Q 36","QUERY Q 36 - Closing Preference Shares - Sum of transactions does not equal closing balance - please check") -> OK Q 36 | B69: =IF(Questionnaire!E161+Questionnaire!E163-Questionnaire!E164+Questionnaire!E166-Questionnaire!E167=Questionnaire!E162,"OK Q 36","QUERY Q 36 - Closing Preference Shares - Sum of transactions does not equal closing balance - please check") -> OK Q 36 | C69: =IF(Questionnaire!F161+Questionnaire!F163-Questionnaire!F164+Questionnaire!F166-Questionnaire!F167=Questionnaire!F162,"OK Q 36","QUERY Q 36 - Closing Preference Shares - Sum of transactions does not equal closing balance - please check") -> OK Q 36 | D69: =IF(Questionnaire!G161+Questionnaire!G163-Questionnaire!G164+Questionnaire!G166-Questionnaire!G167=Questionnaire!G162,"OK Q 36","QUERY Q 36 - Closing Preference Shares - Sum of transactions does not equal closing balance - please check") -> OK Q 36 | E69: =IF(Questionnaire!H161+Questionnaire!H163-Questionnaire!H164+Questionnaire!H166-Questionnaire!H167=Questionnaire!H162,"OK Q 36","QUERY Q 36 - Closing Preference Shares - Sum of transactions does not equal closing balance - please check") -> OK Q 36 | F69: =IF(Questionnaire!I161+Questionnaire!I163-Questionnaire!I164+Questionnaire!I166-Questionnaire!I167=Questionnaire!I162,"OK Q 36","QUERY Q 36 - Closing Preference Shares - Sum of transactions does not equal closing balance - please check") -> OK Q 36 | G69: =IF(Questionnaire!J161+Questionnaire!J163-Questionnaire!J164+Questionnaire!J166-Questionnaire!J167=Questionnaire!J162,"OK Q 36","QUERY Q 36 - Closing Preference Shares - Sum of transactions does not equal closing balance - please check") -> OK Q 36 | H69: =IF(Questionnaire!K161+Questionnaire!K163-Questionnaire!K164+Questionnaire!K166-Questionnaire!K167=Questionnaire!K162,"OK Q 36","QUERY Q 36 - Closing Preference Shares - Sum of transactions does not equal closing balance - please check") -> OK Q 36 | ... IP69: =IF(Questionnaire!IS161+Questionnaire!IS163-Questionnaire!IS164+Questionnaire!IS166-Questionnaire!IS167=Questionnaire!IS162,"OK Q 36","QUERY Q 36 - Closing Preference Shares - Sum of transactions does not equal closing balance - please check") -> OK Q 36
A70: =IF(LEFT(A71,2)="OK",0,IF(LEFT(A71,2)="WA",2,1)) -> 0 | B70: =IF(LEFT(B71,2)="OK",0,IF(LEFT(B71,2)="WA",2,1)) -> 0 | C70: =IF(LEFT(C71,2)="OK",0,IF(LEFT(C71,2)="WA",2,1)) -> 0 | D70: =IF(LEFT(D71,2)="OK",0,IF(LEFT(D71,2)="WA",2,1)) -> 0 | E70: =IF(LEFT(E71,2)="OK",0,IF(LEFT(E71,2)="WA",2,1)) -> 0 | F70: =IF(LEFT(F71,2)="OK",0,IF(LEFT(F71,2)="WA",2,1)) -> 0 | G70: =IF(LEFT(G71,2)="OK",0,IF(LEFT(G71,2)="WA",2,1)) -> 0 | H70: =IF(LEFT(H71,2)="OK",0,IF(LEFT(H71,2)="WA",2,1)) -> 0 | ... IP70: =IF(LEFT(IP71,2)="OK",0,IF(LEFT(IP71,2)="WA",2,1)) -> 0
A71: =IF((ABS(Questionnaire!D172-Questionnaire!D171))>ABS(Questionnaire!D171*0.25),"WARNING Q 39 - ICCA owed by UK company - Diff between opening (Q 39.a) & closing balance (Q 39.b) >25% - please check","OK Q 39") -> OK Q 39 | B71: =IF((ABS(Questionnaire!E172-Questionnaire!E171))>ABS(Questionnaire!E171*0.25),"WARNING Q 39 - ICCA owed by UK company - Diff between opening (Q 39.a) & closing balance (Q 39.b) >25% - please check","OK Q 39") -> OK Q 39 | C71: =IF((ABS(Questionnaire!F172-Questionnaire!F171))>ABS(Questionnaire!F171*0.25),"WARNING Q 39 - ICCA owed by UK company - Diff between opening (Q 39.a) & closing balance (Q 39.b) >25% - please check","OK Q 39") -> OK Q 39 | D71: =IF((ABS(Questionnaire!G172-Questionnaire!G171))>ABS(Questionnaire!G171*0.25),"WARNING Q 39 - ICCA owed by UK company - Diff between opening (Q 39.a) & closing balance (Q 39.b) >25% - please check","OK Q 39") -> OK Q 39 | E71: =IF((ABS(Questionnaire!H172-Questionnaire!H171))>ABS(Questionnaire!H171*0.25),"WARNING Q 39 - ICCA owed by UK company - Diff between opening (Q 39.a) & closing balance (Q 39.b) >25% - please check","OK Q 39") -> OK Q 39 | F71: =IF((ABS(Questionnaire!I172-Questionnaire!I171))>ABS(Questionnaire!I171*0.25),"WARNING Q 39 - ICCA owed by UK company - Diff between opening (Q 39.a) & closing balance (Q 39.b) >25% - please check","OK Q 39") -> OK Q 39 | G71: =IF((ABS(Questionnaire!J172-Questionnaire!J171))>ABS(Questionnaire!J171*0.25),"WARNING Q 39 - ICCA owed by UK company - Diff between opening (Q 39.a) & closing balance (Q 39.b) >25% - please check","OK Q 39") -> OK Q 39 | H71: =IF((ABS(Questionnaire!K172-Questionnaire!K171))>ABS(Questionnaire!K171*0.25),"WARNING Q 39 - ICCA owed by UK company - Diff between opening (Q 39.a) & closing balance (Q 39.b) >25% - please check","OK Q 39") -> OK Q 39 | ... IP71: =IF((ABS(Questionnaire!IS172-Questionnaire!IS171))>ABS(Questionnaire!IS171*0.25),"WARNING Q 39 - ICCA owed by UK company - Diff between opening (Q 39.a) & closing balance (Q 39.b) >25% - please check","OK Q 39") -> OK Q 39
A72: =IF(LEFT(A73,2)="OK",0,IF(LEFT(A73,2)="WA",2,1)) -> 0 | B72: =IF(LEFT(B73,2)="OK",0,IF(LEFT(B73,2)="WA",2,1)) -> 0 | C72: =IF(LEFT(C73,2)="OK",0,IF(LEFT(C73,2)="WA",2,1)) -> 0 | D72: =IF(LEFT(D73,2)="OK",0,IF(LEFT(D73,2)="WA",2,1)) -> 0 | E72: =IF(LEFT(E73,2)="OK",0,IF(LEFT(E73,2)="WA",2,1)) -> 0 | F72: =IF(LEFT(F73,2)="OK",0,IF(LEFT(F73,2)="WA",2,1)) -> 0 | G72: =IF(LEFT(G73,2)="OK",0,IF(LEFT(G73,2)="WA",2,1)) -> 0 | H72: =IF(LEFT(H73,2)="OK",0,IF(LEFT(H73,2)="WA",2,1)) -> 0 | ... IP72: =IF(LEFT(IP73,2)="OK",0,IF(LEFT(IP73,2)="WA",2,1)) -> 0
A73: =IF(ABS(Questionnaire!D172-Questionnaire!D171)>500,"WARNING Q 39 - Change in ICCA balance owed by UK co. is greater than £500m - please check","OK - ICCA balance owed by UK company") -> OK - ICCA balance owed by UK company | B73: =IF(ABS(Questionnaire!E172-Questionnaire!E171)>500,"WARNING Q 39 - Change in ICCA balance owed by UK co. is greater than £500m - please check","OK - ICCA balance owed by UK company") -> OK - ICCA balance owed by UK company | C73: =IF(ABS(Questionnaire!F172-Questionnaire!F171)>500,"WARNING Q 39 - Change in ICCA balance owed by UK co. is greater than £500m - please check","OK - ICCA balance owed by UK company") -> OK - ICCA balance owed by UK company | D73: =IF(ABS(Questionnaire!G172-Questionnaire!G171)>500,"WARNING Q 39 - Change in ICCA balance owed by UK co. is greater than £500m - please check","OK - ICCA balance owed by UK company") -> OK - ICCA balance owed by UK company | E73: =IF(ABS(Questionnaire!H172-Questionnaire!H171)>500,"WARNING Q 39 - Change in ICCA balance owed by UK co. is greater than £500m - please check","OK - ICCA balance owed by UK company") -> OK - ICCA balance owed by UK company | F73: =IF(ABS(Questionnaire!I172-Questionnaire!I171)>500,"WARNING Q 39 - Change in ICCA balance owed by UK co. is greater than £500m - please check","OK - ICCA balance owed by UK company") -> OK - ICCA balance owed by UK company | G73: =IF(ABS(Questionnaire!J172-Questionnaire!J171)>500,"WARNING Q 39 - Change in ICCA balance owed by UK co. is greater than £500m - please check","OK - ICCA balance owed by UK company") -> OK - ICCA balance owed by UK company | H73: =IF(ABS(Questionnaire!K172-Questionnaire!K171)>500,"WARNING Q 39 - Change in ICCA balance owed by UK co. is greater than £500m - please check","OK - ICCA balance owed by UK company") -> OK - ICCA balance owed by UK company | ... IP73: =IF(ABS(Questionnaire!IS172-Questionnaire!IS171)>500,"WARNING Q 39 - Change in ICCA balance owed by UK co. is greater than £500m - please check","OK - ICCA balance owed by UK company") -> OK - ICCA balance owed by UK company
A74: =IF(LEFT(A75,2)="OK",0,IF(LEFT(A75,2)="WA",2,1)) -> 0 | B74: =IF(LEFT(B75,2)="OK",0,IF(LEFT(B75,2)="WA",2,1)) -> 0 | C74: =IF(LEFT(C75,2)="OK",0,IF(LEFT(C75,2)="WA",2,1)) -> 0 | D74: =IF(LEFT(D75,2)="OK",0,IF(LEFT(D75,2)="WA",2,1)) -> 0 | E74: =IF(LEFT(E75,2)="OK",0,IF(LEFT(E75,2)="WA",2,1)) -> 0 | F74: =IF(LEFT(F75,2)="OK",0,IF(LEFT(F75,2)="WA",2,1)) -> 0 | G74: =IF(LEFT(G75,2)="OK",0,IF(LEFT(G75,2)="WA",2,1)) -> 0 | H74: =IF(LEFT(H75,2)="OK",0,IF(LEFT(H75,2)="WA",2,1)) -> 0 | ... IP74: =IF(LEFT(IP75,2)="OK",0,IF(LEFT(IP75,2)="WA",2,1)) -> 0
A75: =IF(ABS((Questionnaire!D174-Questionnaire!D173)-(Questionnaire!D172-Questionnaire!D171))>500,"WARNING Variable Q 39 & 40 - Net change in ICCA balance is greater than £500m - please check","OK - Net change in ICCA balance") -> OK - Net change in ICCA balance | B75: =IF(ABS((Questionnaire!E174-Questionnaire!E173)-(Questionnaire!E172-Questionnaire!E171))>500,"WARNING Variable Q 39 & 40 - Net change in ICCA balance is greater than £500m - please check","OK - Net change in ICCA balance") -> OK - Net change in ICCA balance | C75: =IF(ABS((Questionnaire!F174-Questionnaire!F173)-(Questionnaire!F172-Questionnaire!F171))>500,"WARNING Variable Q 39 & 40 - Net change in ICCA balance is greater than £500m - please check","OK - Net change in ICCA balance") -> OK - Net change in ICCA balance | D75: =IF(ABS((Questionnaire!G174-Questionnaire!G173)-(Questionnaire!G172-Questionnaire!G171))>500,"WARNING Variable Q 39 & 40 - Net change in ICCA balance is greater than £500m - please check","OK - Net change in ICCA balance") -> OK - Net change in ICCA balance | E75: =IF(ABS((Questionnaire!H174-Questionnaire!H173)-(Questionnaire!H172-Questionnaire!H171))>500,"WARNING Variable Q 39 & 40 - Net change in ICCA balance is greater than £500m - please check","OK - Net change in ICCA balance") -> OK - Net change in ICCA balance | F75: =IF(ABS((Questionnaire!I174-Questionnaire!I173)-(Questionnaire!I172-Questionnaire!I171))>500,"WARNING Variable Q 39 & 40 - Net change in ICCA balance is greater than £500m - please check","OK - Net change in ICCA balance") -> OK - Net change in ICCA balance | G75: =IF(ABS((Questionnaire!J174-Questionnaire!J173)-(Questionnaire!J172-Questionnaire!J171))>500,"WARNING Variable Q 39 & 40 - Net change in ICCA balance is greater than £500m - please check","OK - Net change in ICCA balance") -> OK - Net change in ICCA balance | H75: =IF(ABS((Questionnaire!K174-Questionnaire!K173)-(Questionnaire!K172-Questionnaire!K171))>500,"WARNING Variable Q 39 & 40 - Net change in ICCA balance is greater than £500m - please check","OK - Net change in ICCA balance") -> OK - Net change in ICCA balance | ... IP75: =IF(ABS((Questionnaire!IS174-Questionnaire!IS173)-(Questionnaire!IS172-Questionnaire!IS171))>500,"WARNING Variable Q 39 & 40 - Net change in ICCA balance is greater than £500m - please check","OK - Net change in ICCA balance") -> OK - Net change in ICCA balance
A76: =IF(LEFT(A77,2)="OK",0,IF(LEFT(A77,2)="WA",2,1)) -> 0 | B76: =IF(LEFT(B77,2)="OK",0,IF(LEFT(B77,2)="WA",2,1)) -> 0 | C76: =IF(LEFT(C77,2)="OK",0,IF(LEFT(C77,2)="WA",2,1)) -> 0 | D76: =IF(LEFT(D77,2)="OK",0,IF(LEFT(D77,2)="WA",2,1)) -> 0 | E76: =IF(LEFT(E77,2)="OK",0,IF(LEFT(E77,2)="WA",2,1)) -> 0 | F76: =IF(LEFT(F77,2)="OK",0,IF(LEFT(F77,2)="WA",2,1)) -> 0 | G76: =IF(LEFT(G77,2)="OK",0,IF(LEFT(G77,2)="WA",2,1)) -> 0 | H76: =IF(LEFT(H77,2)="OK",0,IF(LEFT(H77,2)="WA",2,1)) -> 0 | ... IP76: =IF(LEFT(IP77,2)="OK",0,IF(LEFT(IP77,2)="WA",2,1)) -> 0
A77: =IF((ABS(Questionnaire!D174-Questionnaire!D172))>ABS((Questionnaire!D171-Questionnaire!D173)*0.25),"WARNING Q 39 & 40 - Net ICCA balance - Diff between opening & closing balance > 25% - please check","OK - Net ICCA balance") -> OK - Net ICCA balance | B77: =IF((ABS(Questionnaire!E174-Questionnaire!E172))>ABS((Questionnaire!E171-Questionnaire!E173)*0.25),"WARNING Q 39 & 40 - Net ICCA balance - Diff between opening & closing balance > 25% - please check","OK - Net ICCA balance") -> OK - Net ICCA balance | C77: =IF((ABS(Questionnaire!F174-Questionnaire!F172))>ABS((Questionnaire!F171-Questionnaire!F173)*0.25),"WARNING Q 39 & 40 - Net ICCA balance - Diff between opening & closing balance > 25% - please check","OK - Net ICCA balance") -> OK - Net ICCA balance | D77: =IF((ABS(Questionnaire!G174-Questionnaire!G172))>ABS((Questionnaire!G171-Questionnaire!G173)*0.25),"WARNING Q 39 & 40 - Net ICCA balance - Diff between opening & closing balance > 25% - please check","OK - Net ICCA balance") -> OK - Net ICCA balance | E77: =IF((ABS(Questionnaire!H174-Questionnaire!H172))>ABS((Questionnaire!H171-Questionnaire!H173)*0.25),"WARNING Q 39 & 40 - Net ICCA balance - Diff between opening & closing balance > 25% - please check","OK - Net ICCA balance") -> OK - Net ICCA balance | F77: =IF((ABS(Questionnaire!I174-Questionnaire!I172))>ABS((Questionnaire!I171-Questionnaire!I173)*0.25),"WARNING Q 39 & 40 - Net ICCA balance - Diff between opening & closing balance > 25% - please check","OK - Net ICCA balance") -> OK - Net ICCA balance | G77: =IF((ABS(Questionnaire!J174-Questionnaire!J172))>ABS((Questionnaire!J171-Questionnaire!J173)*0.25),"WARNING Q 39 & 40 - Net ICCA balance - Diff between opening & closing balance > 25% - please check","OK - Net ICCA balance") -> OK - Net ICCA balance | H77: =IF((ABS(Questionnaire!K174-Questionnaire!K172))>ABS((Questionnaire!K171-Questionnaire!K173)*0.25),"WARNING Q 39 & 40 - Net ICCA balance - Diff between opening & closing balance > 25% - please check","OK - Net ICCA balance") -> OK - Net ICCA balance | ... IP77: =IF((ABS(Questionnaire!IS174-Questionnaire!IS172))>ABS((Questionnaire!IS171-Questionnaire!IS173)*0.25),"WARNING Q 39 & 40 - Net ICCA balance - Diff between opening & closing balance > 25% - please check","OK - Net ICCA balance") -> OK - Net ICCA balance
A78: =IF(LEFT(A79,2)="OK",0,IF(LEFT(A79,2)="WA",2,1)) -> 0 | B78: =IF(LEFT(B79,2)="OK",0,IF(LEFT(B79,2)="WA",2,1)) -> 0 | C78: =IF(LEFT(C79,2)="OK",0,IF(LEFT(C79,2)="WA",2,1)) -> 0 | D78: =IF(LEFT(D79,2)="OK",0,IF(LEFT(D79,2)="WA",2,1)) -> 0 | E78: =IF(LEFT(E79,2)="OK",0,IF(LEFT(E79,2)="WA",2,1)) -> 0 | F78: =IF(LEFT(F79,2)="OK",0,IF(LEFT(F79,2)="WA",2,1)) -> 0 | G78: =IF(LEFT(G79,2)="OK",0,IF(LEFT(G79,2)="WA",2,1)) -> 0 | H78: =IF(LEFT(H79,2)="OK",0,IF(LEFT(H79,2)="WA",2,1)) -> 0 | ... IP78: =IF(LEFT(IP79,2)="OK",0,IF(LEFT(IP79,2)="WA",2,1)) -> 0
A79: =IF((ABS(Questionnaire!D174-Questionnaire!D172))>1000,"WARNING Q 39 & 40 - Closing level of net ICCA balance is greater than £1,000m - please check","OK - Closing level of net ICCA balance") -> OK - Closing level of net ICCA balance | B79: =IF((ABS(Questionnaire!E174-Questionnaire!E172))>1000,"WARNING Q 39 & 40 - Closing level of net ICCA balance is greater than £1,000m - please check","OK - Closing level of net ICCA balance") -> OK - Closing level of net ICCA balance | C79: =IF((ABS(Questionnaire!F174-Questionnaire!F172))>1000,"WARNING Q 39 & 40 - Closing level of net ICCA balance is greater than £1,000m - please check","OK - Closing level of net ICCA balance") -> OK - Closing level of net ICCA balance | D79: =IF((ABS(Questionnaire!G174-Questionnaire!G172))>1000,"WARNING Q 39 & 40 - Closing level of net ICCA balance is greater than £1,000m - please check","OK - Closing level of net ICCA balance") -> OK - Closing level of net ICCA balance | E79: =IF((ABS(Questionnaire!H174-Questionnaire!H172))>1000,"WARNING Q 39 & 40 - Closing level of net ICCA balance is greater than £1,000m - please check","OK - Closing level of net ICCA balance") -> OK - Closing level of net ICCA balance | F79: =IF((ABS(Questionnaire!I174-Questionnaire!I172))>1000,"WARNING Q 39 & 40 - Closing level of net ICCA balance is greater than £1,000m - please check","OK - Closing level of net ICCA balance") -> OK - Closing level of net ICCA balance | G79: =IF((ABS(Questionnaire!J174-Questionnaire!J172))>1000,"WARNING Q 39 & 40 - Closing level of net ICCA balance is greater than £1,000m - please check","OK - Closing level of net ICCA balance") -> OK - Closing level of net ICCA balance | H79: =IF((ABS(Questionnaire!K174-Questionnaire!K172))>1000,"WARNING Q 39 & 40 - Closing level of net ICCA balance is greater than £1,000m - please check","OK - Closing level of net ICCA balance") -> OK - Closing level of net ICCA balance | ... IP79: =IF((ABS(Questionnaire!IS174-Questionnaire!IS172))>1000,"WARNING Q 39 & 40 - Closing level of net ICCA balance is greater than £1,000m - please check","OK - Closing level of net ICCA balance") -> OK - Closing level of net ICCA balance
A80: =IF(LEFT(A81,2)="OK",0,IF(LEFT(A81,2)="WA",2,1)) -> 0 | B80: =IF(LEFT(B81,2)="OK",0,IF(LEFT(B81,2)="WA",2,1)) -> 0 | C80: =IF(LEFT(C81,2)="OK",0,IF(LEFT(C81,2)="WA",2,1)) -> 0 | D80: =IF(LEFT(D81,2)="OK",0,IF(LEFT(D81,2)="WA",2,1)) -> 0 | E80: =IF(LEFT(E81,2)="OK",0,IF(LEFT(E81,2)="WA",2,1)) -> 0 | F80: =IF(LEFT(F81,2)="OK",0,IF(LEFT(F81,2)="WA",2,1)) -> 0 | G80: =IF(LEFT(G81,2)="OK",0,IF(LEFT(G81,2)="WA",2,1)) -> 0 | H80: =IF(LEFT(H81,2)="OK",0,IF(LEFT(H81,2)="WA",2,1)) -> 0 | ... IP80: =IF(LEFT(IP81,2)="OK",0,IF(LEFT(IP81,2)="WA",2,1)) -> 0
A81: =IF((ABS(Questionnaire!D174-Questionnaire!D173))>ABS(Questionnaire!D173*0.25),"WARNING Q 40 - I/C owed to UK company - Diff between opening (Q 40.a) & closing (Q 40.b) balance >25% - please check","OK Q 40") -> OK Q 40 | B81: =IF((ABS(Questionnaire!E174-Questionnaire!E173))>ABS(Questionnaire!E173*0.25),"WARNING Q 40 - I/C owed to UK company - Diff between opening (Q 40.a) & closing (Q 40.b) balance >25% - please check","OK Q 40") -> OK Q 40 | C81: =IF((ABS(Questionnaire!F174-Questionnaire!F173))>ABS(Questionnaire!F173*0.25),"WARNING Q 40 - I/C owed to UK company - Diff between opening (Q 40.a) & closing (Q 40.b) balance >25% - please check","OK Q 40") -> OK Q 40 | D81: =IF((ABS(Questionnaire!G174-Questionnaire!G173))>ABS(Questionnaire!G173*0.25),"WARNING Q 40 - I/C owed to UK company - Diff between opening (Q 40.a) & closing (Q 40.b) balance >25% - please check","OK Q 40") -> OK Q 40 | E81: =IF((ABS(Questionnaire!H174-Questionnaire!H173))>ABS(Questionnaire!H173*0.25),"WARNING Q 40 - I/C owed to UK company - Diff between opening (Q 40.a) & closing (Q 40.b) balance >25% - please check","OK Q 40") -> OK Q 40 | F81: =IF((ABS(Questionnaire!I174-Questionnaire!I173))>ABS(Questionnaire!I173*0.25),"WARNING Q 40 - I/C owed to UK company - Diff between opening (Q 40.a) & closing (Q 40.b) balance >25% - please check","OK Q 40") -> OK Q 40 | G81: =IF((ABS(Questionnaire!J174-Questionnaire!J173))>ABS(Questionnaire!J173*0.25),"WARNING Q 40 - I/C owed to UK company - Diff between opening (Q 40.a) & closing (Q 40.b) balance >25% - please check","OK Q 40") -> OK Q 40 | H81: =IF((ABS(Questionnaire!K174-Questionnaire!K173))>ABS(Questionnaire!K173*0.25),"WARNING Q 40 - I/C owed to UK company - Diff between opening (Q 40.a) & closing (Q 40.b) balance >25% - please check","OK Q 40") -> OK Q 40 | ... IP81: =IF((ABS(Questionnaire!IS174-Questionnaire!IS173))>ABS(Questionnaire!IS173*0.25),"WARNING Q 40 - I/C owed to UK company - Diff between opening (Q 40.a) & closing (Q 40.b) balance >25% - please check","OK Q 40") -> OK Q 40
A82: =IF(LEFT(A83,2)="OK",0,IF(LEFT(A83,2)="WA",2,1)) -> 0 | B82: =IF(LEFT(B83,2)="OK",0,IF(LEFT(B83,2)="WA",2,1)) -> 0 | C82: =IF(LEFT(C83,2)="OK",0,IF(LEFT(C83,2)="WA",2,1)) -> 0 | D82: =IF(LEFT(D83,2)="OK",0,IF(LEFT(D83,2)="WA",2,1)) -> 0 | E82: =IF(LEFT(E83,2)="OK",0,IF(LEFT(E83,2)="WA",2,1)) -> 0 | F82: =IF(LEFT(F83,2)="OK",0,IF(LEFT(F83,2)="WA",2,1)) -> 0 | G82: =IF(LEFT(G83,2)="OK",0,IF(LEFT(G83,2)="WA",2,1)) -> 0 | H82: =IF(LEFT(H83,2)="OK",0,IF(LEFT(H83,2)="WA",2,1)) -> 0 | ... IP82: =IF(LEFT(IP83,2)="OK",0,IF(LEFT(IP83,2)="WA",2,1)) -> 0
A83: =IF(ABS(Questionnaire!D174-Questionnaire!D173)>500,"WARNING Q 40 - Change in ICCA balance owed to UK co. is greater than £500m - please check","OK - ICCA balance owed to UK company") -> OK - ICCA balance owed to UK company | B83: =IF(ABS(Questionnaire!E174-Questionnaire!E173)>500,"WARNING Q 40 - Change in ICCA balance owed to UK co. is greater than £500m - please check","OK - ICCA balance owed to UK company") -> OK - ICCA balance owed to UK company | C83: =IF(ABS(Questionnaire!F174-Questionnaire!F173)>500,"WARNING Q 40 - Change in ICCA balance owed to UK co. is greater than £500m - please check","OK - ICCA balance owed to UK company") -> OK - ICCA balance owed to UK company | D83: =IF(ABS(Questionnaire!G174-Questionnaire!G173)>500,"WARNING Q 40 - Change in ICCA balance owed to UK co. is greater than £500m - please check","OK - ICCA balance owed to UK company") -> OK - ICCA balance owed to UK company | E83: =IF(ABS(Questionnaire!H174-Questionnaire!H173)>500,"WARNING Q 40 - Change in ICCA balance owed to UK co. is greater than £500m - please check","OK - ICCA balance owed to UK company") -> OK - ICCA balance owed to UK company | F83: =IF(ABS(Questionnaire!I174-Questionnaire!I173)>500,"WARNING Q 40 - Change in ICCA balance owed to UK co. is greater than £500m - please check","OK - ICCA balance owed to UK company") -> OK - ICCA balance owed to UK company | G83: =IF(ABS(Questionnaire!J174-Questionnaire!J173)>500,"WARNING Q 40 - Change in ICCA balance owed to UK co. is greater than £500m - please check","OK - ICCA balance owed to UK company") -> OK - ICCA balance owed to UK company | H83: =IF(ABS(Questionnaire!K174-Questionnaire!K173)>500,"WARNING Q 40 - Change in ICCA balance owed to UK co. is greater than £500m - please check","OK - ICCA balance owed to UK company") -> OK - ICCA balance owed to UK company | ... IP83: =IF(ABS(Questionnaire!IS174-Questionnaire!IS173)>500,"WARNING Q 40 - Change in ICCA balance owed to UK co. is greater than £500m - please check","OK - ICCA balance owed to UK company") -> OK - ICCA balance owed to UK company
A84: =IF(LEFT(A85,2)="OK",0,IF(LEFT(A85,2)="WA",2,1)) -> 0 | B84: =IF(LEFT(B85,2)="OK",0,IF(LEFT(B85,2)="WA",2,1)) -> 0 | C84: =IF(LEFT(C85,2)="OK",0,IF(LEFT(C85,2)="WA",2,1)) -> 0 | D84: =IF(LEFT(D85,2)="OK",0,IF(LEFT(D85,2)="WA",2,1)) -> 0 | E84: =IF(LEFT(E85,2)="OK",0,IF(LEFT(E85,2)="WA",2,1)) -> 0 | F84: =IF(LEFT(F85,2)="OK",0,IF(LEFT(F85,2)="WA",2,1)) -> 0 | G84: =IF(LEFT(G85,2)="OK",0,IF(LEFT(G85,2)="WA",2,1)) -> 0 | H84: =IF(LEFT(H85,2)="OK",0,IF(LEFT(H85,2)="WA",2,1)) -> 0 | ... IP84: =IF(LEFT(IP85,2)="OK",0,IF(LEFT(IP85,2)="WA",2,1)) -> 0
A85: =IF(ABS(Questionnaire!D175-Questionnaire!D176)>50,"WARNING Q 41.a-41b - Net interest is greater than £50m - please check","OK Q 41.a-41b") -> OK Q 41.a-41b | B85: =IF(ABS(Questionnaire!E175-Questionnaire!E176)>50,"WARNING Q 41.a-41b - Net interest is greater than £50m - please check","OK Q 41.a-41b") -> OK Q 41.a-41b | C85: =IF(ABS(Questionnaire!F175-Questionnaire!F176)>50,"WARNING Q 41.a-41b - Net interest is greater than £50m - please check","OK Q 41.a-41b") -> OK Q 41.a-41b | D85: =IF(ABS(Questionnaire!G175-Questionnaire!G176)>50,"WARNING Q 41.a-41b - Net interest is greater than £50m - please check","OK Q 41.a-41b") -> OK Q 41.a-41b | E85: =IF(ABS(Questionnaire!H175-Questionnaire!H176)>50,"WARNING Q 41.a-41b - Net interest is greater than £50m - please check","OK Q 41.a-41b") -> OK Q 41.a-41b | F85: =IF(ABS(Questionnaire!I175-Questionnaire!I176)>50,"WARNING Q 41.a-41b - Net interest is greater than £50m - please check","OK Q 41.a-41b") -> OK Q 41.a-41b | G85: =IF(ABS(Questionnaire!J175-Questionnaire!J176)>50,"WARNING Q 41.a-41b - Net interest is greater than £50m - please check","OK Q 41.a-41b") -> OK Q 41.a-41b | H85: =IF(ABS(Questionnaire!K175-Questionnaire!K176)>50,"WARNING Q 41.a-41b - Net interest is greater than £50m - please check","OK Q 41.a-41b") -> OK Q 41.a-41b | ... IP85: =IF(ABS(Questionnaire!IS175-Questionnaire!IS176)>50,"WARNING Q 41.a-41b - Net interest is greater than £50m - please check","OK Q 41.a-41b") -> OK Q 41.a-41b
A86: =IF(LEFT(A87,2)="OK",0,IF(LEFT(A87,2)="WA",2,1)) -> 0 | B86: =IF(LEFT(B87,2)="OK",0,IF(LEFT(B87,2)="WA",2,1)) -> 0 | C86: =IF(LEFT(C87,2)="OK",0,IF(LEFT(C87,2)="WA",2,1)) -> 0 | D86: =IF(LEFT(D87,2)="OK",0,IF(LEFT(D87,2)="WA",2,1)) -> 0 | E86: =IF(LEFT(E87,2)="OK",0,IF(LEFT(E87,2)="WA",2,1)) -> 0 | F86: =IF(LEFT(F87,2)="OK",0,IF(LEFT(F87,2)="WA",2,1)) -> 0 | G86: =IF(LEFT(G87,2)="OK",0,IF(LEFT(G87,2)="WA",2,1)) -> 0 | H86: =IF(LEFT(H87,2)="OK",0,IF(LEFT(H87,2)="WA",2,1)) -> 0 | ... IP86: =IF(LEFT(IP87,2)="OK",0,IF(LEFT(IP87,2)="WA",2,1)) -> 0
A87: =IF(ABS(Questionnaire!D180-Questionnaire!D181)>50,"WARNING Q 42.a-42.b- Net Branch profit/loss is greater than £50m - please check","OK Q 42.a-42.b") -> OK Q 42.a-42.b | B87: =IF(ABS(Questionnaire!E180-Questionnaire!E181)>50,"WARNING Q 42.a-42.b- Net Branch profit/loss is greater than £50m - please check","OK Q 42.a-42.b") -> OK Q 42.a-42.b | C87: =IF(ABS(Questionnaire!F180-Questionnaire!F181)>50,"WARNING Q 42.a-42.b- Net Branch profit/loss is greater than £50m - please check","OK Q 42.a-42.b") -> OK Q 42.a-42.b | D87: =IF(ABS(Questionnaire!G180-Questionnaire!G181)>50,"WARNING Q 42.a-42.b- Net Branch profit/loss is greater than £50m - please check","OK Q 42.a-42.b") -> OK Q 42.a-42.b | E87: =IF(ABS(Questionnaire!H180-Questionnaire!H181)>50,"WARNING Q 42.a-42.b- Net Branch profit/loss is greater than £50m - please check","OK Q 42.a-42.b") -> OK Q 42.a-42.b | F87: =IF(ABS(Questionnaire!I180-Questionnaire!I181)>50,"WARNING Q 42.a-42.b- Net Branch profit/loss is greater than £50m - please check","OK Q 42.a-42.b") -> OK Q 42.a-42.b | G87: =IF(ABS(Questionnaire!J180-Questionnaire!J181)>50,"WARNING Q 42.a-42.b- Net Branch profit/loss is greater than £50m - please check","OK Q 42.a-42.b") -> OK Q 42.a-42.b | H87: =IF(ABS(Questionnaire!K180-Questionnaire!K181)>50,"WARNING Q 42.a-42.b- Net Branch profit/loss is greater than £50m - please check","OK Q 42.a-42.b") -> OK Q 42.a-42.b | ... IP87: =IF(ABS(Questionnaire!IS180-Questionnaire!IS181)>50,"WARNING Q 42.a-42.b- Net Branch profit/loss is greater than £50m - please check","OK Q 42.a-42.b") -> OK Q 42.a-42.b
A88: =IF(LEFT(A89,2)="OK",0,IF(LEFT(A89,2)="WA",2,1)) -> 0 | B88: =IF(LEFT(B89,2)="OK",0,IF(LEFT(B89,2)="WA",2,1)) -> 0 | C88: =IF(LEFT(C89,2)="OK",0,IF(LEFT(C89,2)="WA",2,1)) -> 0 | D88: =IF(LEFT(D89,2)="OK",0,IF(LEFT(D89,2)="WA",2,1)) -> 0 | E88: =IF(LEFT(E89,2)="OK",0,IF(LEFT(E89,2)="WA",2,1)) -> 0 | F88: =IF(LEFT(F89,2)="OK",0,IF(LEFT(F89,2)="WA",2,1)) -> 0 | G88: =IF(LEFT(G89,2)="OK",0,IF(LEFT(G89,2)="WA",2,1)) -> 0 | H88: =IF(LEFT(H89,2)="OK",0,IF(LEFT(H89,2)="WA",2,1)) -> 0 | ... IP88: =IF(LEFT(IP89,2)="OK",0,IF(LEFT(IP89,2)="WA",2,1)) -> 0
A89: =IF(ABS(Questionnaire!D187-Questionnaire!D186)-(Questionnaire!D185-Questionnaire!D184)>100,"WARNING Q 44 & 45 - Closing level of branch equity capital is greater than £100m - please check","OK - Closing level of branch equity capital") -> OK - Closing level of branch equity capital | B89: =IF(ABS(Questionnaire!E187-Questionnaire!E186)-(Questionnaire!E185-Questionnaire!E184)>100,"WARNING Q 44 & 45 - Closing level of branch equity capital is greater than £100m - please check","OK - Closing level of branch equity capital") -> OK - Closing level of branch equity capital | C89: =IF(ABS(Questionnaire!F187-Questionnaire!F186)-(Questionnaire!F185-Questionnaire!F184)>100,"WARNING Q 44 & 45 - Closing level of branch equity capital is greater than £100m - please check","OK - Closing level of branch equity capital") -> OK - Closing level of branch equity capital | D89: =IF(ABS(Questionnaire!G187-Questionnaire!G186)-(Questionnaire!G185-Questionnaire!G184)>100,"WARNING Q 44 & 45 - Closing level of branch equity capital is greater than £100m - please check","OK - Closing level of branch equity capital") -> OK - Closing level of branch equity capital | E89: =IF(ABS(Questionnaire!H187-Questionnaire!H186)-(Questionnaire!H185-Questionnaire!H184)>100,"WARNING Q 44 & 45 - Closing level of branch equity capital is greater than £100m - please check","OK - Closing level of branch equity capital") -> OK - Closing level of branch equity capital | F89: =IF(ABS(Questionnaire!I187-Questionnaire!I186)-(Questionnaire!I185-Questionnaire!I184)>100,"WARNING Q 44 & 45 - Closing level of branch equity capital is greater than £100m - please check","OK - Closing level of branch equity capital") -> OK - Closing level of branch equity capital | G89: =IF(ABS(Questionnaire!J187-Questionnaire!J186)-(Questionnaire!J185-Questionnaire!J184)>100,"WARNING Q 44 & 45 - Closing level of branch equity capital is greater than £100m - please check","OK - Closing level of branch equity capital") -> OK - Closing level of branch equity capital | H89: =IF(ABS(Questionnaire!K187-Questionnaire!K186)-(Questionnaire!K185-Questionnaire!K184)>100,"WARNING Q 44 & 45 - Closing level of branch equity capital is greater than £100m - please check","OK - Closing level of branch equity capital") -> OK - Closing level of branch equity capital | ... IP89: =IF(ABS(Questionnaire!IS187-Questionnaire!IS186)-(Questionnaire!IS185-Questionnaire!IS184)>100,"WARNING Q 44 & 45 - Closing level of branch equity capital is greater than £100m - please check","OK - Closing level of branch equity capital") -> OK - Closing level of branch equity capital
A90: =IF(LEFT(A91,2)="OK",0,IF(LEFT(A91,2)="WA",2,1)) -> 0 | B90: =IF(LEFT(B91,2)="OK",0,IF(LEFT(B91,2)="WA",2,1)) -> 0 | C90: =IF(LEFT(C91,2)="OK",0,IF(LEFT(C91,2)="WA",2,1)) -> 0 | D90: =IF(LEFT(D91,2)="OK",0,IF(LEFT(D91,2)="WA",2,1)) -> 0 | E90: =IF(LEFT(E91,2)="OK",0,IF(LEFT(E91,2)="WA",2,1)) -> 0 | F90: =IF(LEFT(F91,2)="OK",0,IF(LEFT(F91,2)="WA",2,1)) -> 0 | G90: =IF(LEFT(G91,2)="OK",0,IF(LEFT(G91,2)="WA",2,1)) -> 0 | H90: =IF(LEFT(H91,2)="OK",0,IF(LEFT(H91,2)="WA",2,1)) -> 0 | ... IP90: =IF(LEFT(IP91,2)="OK",0,IF(LEFT(IP91,2)="WA",2,1)) -> 0
A91: =IF(ABS(Questionnaire!D190-Questionnaire!D189)>50,"WARNING Q 46 - Change in branch equity owed to UK co. is greater than £50m - please check","OK - Branch equity owed to UK company") -> OK - Branch equity owed to UK company | B91: =IF(ABS(Questionnaire!E190-Questionnaire!E189)>50,"WARNING Q 46 - Change in branch equity owed to UK co. is greater than £50m - please check","OK - Branch equity owed to UK company") -> OK - Branch equity owed to UK company | C91: =IF(ABS(Questionnaire!F190-Questionnaire!F189)>50,"WARNING Q 46 - Change in branch equity owed to UK co. is greater than £50m - please check","OK - Branch equity owed to UK company") -> OK - Branch equity owed to UK company | D91: =IF(ABS(Questionnaire!G190-Questionnaire!G189)>50,"WARNING Q 46 - Change in branch equity owed to UK co. is greater than £50m - please check","OK - Branch equity owed to UK company") -> OK - Branch equity owed to UK company | E91: =IF(ABS(Questionnaire!H190-Questionnaire!H189)>50,"WARNING Q 46 - Change in branch equity owed to UK co. is greater than £50m - please check","OK - Branch equity owed to UK company") -> OK - Branch equity owed to UK company | F91: =IF(ABS(Questionnaire!I190-Questionnaire!I189)>50,"WARNING Q 46 - Change in branch equity owed to UK co. is greater than £50m - please check","OK - Branch equity owed to UK company") -> OK - Branch equity owed to UK company | G91: =IF(ABS(Questionnaire!J190-Questionnaire!J189)>50,"WARNING Q 46 - Change in branch equity owed to UK co. is greater than £50m - please check","OK - Branch equity owed to UK company") -> OK - Branch equity owed to UK company | H91: =IF(ABS(Questionnaire!K190-Questionnaire!K189)>50,"WARNING Q 46 - Change in branch equity owed to UK co. is greater than £50m - please check","OK - Branch equity owed to UK company") -> OK - Branch equity owed to UK company | ... IP91: =IF(ABS(Questionnaire!IS190-Questionnaire!IS189)>50,"WARNING Q 46 - Change in branch equity owed to UK co. is greater than £50m - please check","OK - Branch equity owed to UK company") -> OK - Branch equity owed to UK company
A92: =IF(LEFT(A93,2)="OK",0,IF(LEFT(A93,2)="WA",2,1)) -> 0 | B92: =IF(LEFT(B93,2)="OK",0,IF(LEFT(B93,2)="WA",2,1)) -> 0 | C92: =IF(LEFT(C93,2)="OK",0,IF(LEFT(C93,2)="WA",2,1)) -> 0 | D92: =IF(LEFT(D93,2)="OK",0,IF(LEFT(D93,2)="WA",2,1)) -> 0 | E92: =IF(LEFT(E93,2)="OK",0,IF(LEFT(E93,2)="WA",2,1)) -> 0 | F92: =IF(LEFT(F93,2)="OK",0,IF(LEFT(F93,2)="WA",2,1)) -> 0 | G92: =IF(LEFT(G93,2)="OK",0,IF(LEFT(G93,2)="WA",2,1)) -> 0 | H92: =IF(LEFT(H93,2)="OK",0,IF(LEFT(H93,2)="WA",2,1)) -> 0 | ... IP92: =IF(LEFT(IP93,2)="OK",0,IF(LEFT(IP93,2)="WA",2,1)) -> 0
A93: =IF(ABS(Questionnaire!D190-Questionnaire!D189-Questionnaire!D192-Questionnaire!D191)>50,"WARNING Q 46 & 47 - Net change in branch equity capital is greater than £50m - please check","OK - Net change in branch equity capital") -> OK - Net change in branch equity capital | B93: =IF(ABS(Questionnaire!E190-Questionnaire!E189-Questionnaire!E192-Questionnaire!E191)>50,"WARNING Q 46 & 47 - Net change in branch equity capital is greater than £50m - please check","OK - Net change in branch equity capital") -> OK - Net change in branch equity capital | C93: =IF(ABS(Questionnaire!F190-Questionnaire!F189-Questionnaire!F192-Questionnaire!F191)>50,"WARNING Q 46 & 47 - Net change in branch equity capital is greater than £50m - please check","OK - Net change in branch equity capital") -> OK - Net change in branch equity capital | D93: =IF(ABS(Questionnaire!G190-Questionnaire!G189-Questionnaire!G192-Questionnaire!G191)>50,"WARNING Q 46 & 47 - Net change in branch equity capital is greater than £50m - please check","OK - Net change in branch equity capital") -> OK - Net change in branch equity capital | E93: =IF(ABS(Questionnaire!H190-Questionnaire!H189-Questionnaire!H192-Questionnaire!H191)>50,"WARNING Q 46 & 47 - Net change in branch equity capital is greater than £50m - please check","OK - Net change in branch equity capital") -> OK - Net change in branch equity capital | F93: =IF(ABS(Questionnaire!I190-Questionnaire!I189-Questionnaire!I192-Questionnaire!I191)>50,"WARNING Q 46 & 47 - Net change in branch equity capital is greater than £50m - please check","OK - Net change in branch equity capital") -> OK - Net change in branch equity capital | G93: =IF(ABS(Questionnaire!J190-Questionnaire!J189-Questionnaire!J192-Questionnaire!J191)>50,"WARNING Q 46 & 47 - Net change in branch equity capital is greater than £50m - please check","OK - Net change in branch equity capital") -> OK - Net change in branch equity capital | H93: =IF(ABS(Questionnaire!K190-Questionnaire!K189-Questionnaire!K192-Questionnaire!K191)>50,"WARNING Q 46 & 47 - Net change in branch equity capital is greater than £50m - please check","OK - Net change in branch equity capital") -> OK - Net change in branch equity capital | ... IP93: =IF(ABS(Questionnaire!IS190-Questionnaire!IS189-Questionnaire!IS192-Questionnaire!IS191)>50,"WARNING Q 46 & 47 - Net change in branch equity capital is greater than £50m - please check","OK - Net change in branch equity capital") -> OK - Net change in branch equity capital
A94: =IF(LEFT(A95,2)="OK",0,IF(LEFT(A95,2)="WA",2,1)) -> 0 | B94: =IF(LEFT(B95,2)="OK",0,IF(LEFT(B95,2)="WA",2,1)) -> 0 | C94: =IF(LEFT(C95,2)="OK",0,IF(LEFT(C95,2)="WA",2,1)) -> 0 | D94: =IF(LEFT(D95,2)="OK",0,IF(LEFT(D95,2)="WA",2,1)) -> 0 | E94: =IF(LEFT(E95,2)="OK",0,IF(LEFT(E95,2)="WA",2,1)) -> 0 | F94: =IF(LEFT(F95,2)="OK",0,IF(LEFT(F95,2)="WA",2,1)) -> 0 | G94: =IF(LEFT(G95,2)="OK",0,IF(LEFT(G95,2)="WA",2,1)) -> 0 | H94: =IF(LEFT(H95,2)="OK",0,IF(LEFT(H95,2)="WA",2,1)) -> 0 | ... IP94: =IF(LEFT(IP95,2)="OK",0,IF(LEFT(IP95,2)="WA",2,1)) -> 0
A95: =IF(ABS(Questionnaire!D192-Questionnaire!D191)>50,"WARNING Q 47 - Change in branch equity owed by UK co. is greater than £50m - please check","OK - Branch equity owed by UK company") -> OK - Branch equity owed by UK company | B95: =IF(ABS(Questionnaire!E192-Questionnaire!E191)>50,"WARNING Q 47 - Change in branch equity owed by UK co. is greater than £50m - please check","OK - Branch equity owed by UK company") -> OK - Branch equity owed by UK company | C95: =IF(ABS(Questionnaire!F192-Questionnaire!F191)>50,"WARNING Q 47 - Change in branch equity owed by UK co. is greater than £50m - please check","OK - Branch equity owed by UK company") -> OK - Branch equity owed by UK company | D95: =IF(ABS(Questionnaire!G192-Questionnaire!G191)>50,"WARNING Q 47 - Change in branch equity owed by UK co. is greater than £50m - please check","OK - Branch equity owed by UK company") -> OK - Branch equity owed by UK company | E95: =IF(ABS(Questionnaire!H192-Questionnaire!H191)>50,"WARNING Q 47 - Change in branch equity owed by UK co. is greater than £50m - please check","OK - Branch equity owed by UK company") -> OK - Branch equity owed by UK company | F95: =IF(ABS(Questionnaire!I192-Questionnaire!I191)>50,"WARNING Q 47 - Change in branch equity owed by UK co. is greater than £50m - please check","OK - Branch equity owed by UK company") -> OK - Branch equity owed by UK company | G95: =IF(ABS(Questionnaire!J192-Questionnaire!J191)>50,"WARNING Q 47 - Change in branch equity owed by UK co. is greater than £50m - please check","OK - Branch equity owed by UK company") -> OK - Branch equity owed by UK company | H95: =IF(ABS(Questionnaire!K192-Questionnaire!K191)>50,"WARNING Q 47 - Change in branch equity owed by UK co. is greater than £50m - please check","OK - Branch equity owed by UK company") -> OK - Branch equity owed by UK company | ... IP95: =IF(ABS(Questionnaire!IS192-Questionnaire!IS191)>50,"WARNING Q 47 - Change in branch equity owed by UK co. is greater than £50m - please check","OK - Branch equity owed by UK company") -> OK - Branch equity owed by UK company
F97: Click to go back to top of this page

Sheet Country List
A1: Options for the country sector drop-down boxes
A2: Country code | B2: Country description | D2: Country code | E2: Immediate country description
E3: Non-UK
B4: AFGHANISTAN | C4: 609 | E4: AFGHANISTAN | F4: 609
B5: ALBANIA | C5: 514 | E5: ALBANIA | F5: 514
B6: ALGERIA | C6: 118 | E6: ALGERIA | F6: 118
B7: AMERICAN SAMOA | C7: 641 | E7: AMERICAN SAMOA | F7: 641
B8: ANDORRA | C8: 522 | E8: ANDORRA | F8: 522
B9: ANGOLA | C9: 2 | E9: ANGOLA | F9: 2
B10: ANGUILLA | C10: 821 | E10: ANGUILLA | F10: 821
B11: ANTARCTICA | C11: 644 | E11: ANTARCTICA | F11: 644
B12: ANTIGUA AND BARBUDA | C12: 104 | E12: ANTIGUA AND BARBUDA | F12: 104
B13: ARGENTINA | C13: 3 | E13: ARGENTINA | F13: 3
B14: ARMENIA | C14: 503 | E14: ARMENIA | F14: 503
B15: ARUBA | C15: 817 | E15: ARUBA | F15: 817
B16: AUSTRALIA | C16: 4 | E16: AUSTRALIA | F16: 4
B17: AUSTRIA | C17: 5 | E17: AUSTRIA | F17: 5
B18: AZERBAIJAN | C18: 504 | E18: AZERBAIJAN | F18: 504
... B28: BHUTAN | C28: 607 | E28: BHUTAN | F28: 607
B29: BOLIVIA | C29: 122 | E29: BOLIVIA | F29: 122
B30: BONAIRE, SINT EUSTATINS AND SABA | C30: 822 | E30: BONAIRE, SINT EUSTATINS AND SABA | F30: 822
B31: BOSNIA AND HERZEGOVINA | C31: 517 | E31: BOSNIA AND HERZEGOVINA | F31: 517
B32: BOTSWANA | C32: 101 | E32: BOTSWANA | F32: 101
B33: BOUVET ISLAND | C33: 645 | E33: BOUVET ISLAND | F33: 645
B34: BRAZIL | C34: 7 | E34: BRAZIL | F34: 7
B35: BRITISH INDIAN OCEAN TERRITORY | C35: 604 | E35: BRITISH INDIAN OCEAN TERRITORY | F35: 604
B36: BRUNEI DARUSSALAM | C36: 108 | E36: BRUNEI DARUSSALAM | F36: 108
B37: BULGARIA | C37: 127 | E37: BULGARIA | F37: 127
B38: BURKINA FASO | C38: 702 | E38: BURKINA FASO | F38: 702
B39: BURMA/MYANMAR | C39: 8 | E39: BURMA/MYANMAR | F39: 8
B40: BURUNDI | C40: 711 | E40: BURUNDI | F40: 711
B41: CAMBODIA | C41: 606 | E41: CAMBODIA | F41: 606
B42: CAMEROON | C42: 112 | E42: CAMEROON | F42: 112
B43: CANADA | C43: 9 | E43: CANADA | F43: 9
B44: CAPE VERDE | C44: 705 | E44: CAPE VERDE | F44: 705
B45: CAYMAN ISLANDS | C45: 106 | E45: CAYMAN ISLANDS | F45: 106
B46: CENTRAL AFRICAN REPUBLIC | C46: 717 | E46: CENTRAL AFRICAN REPUBLIC | F46: 717
B47: CHAD | C47: 704 | E47: CHAD | F47: 704
B48: CHILE | C48: 11 | E48: CHILE | F48: 11
B49: CHINA | C49: 98 | E49: CHINA | F49: 98
B50: CHRISTMAS ISLAND | C50: 638 | E50: CHRISTMAS ISLAND | F50: 638
B51: COCOS (KEELING) ISLANDS | C51: 637 | E51: COCOS (KEELING) ISLANDS | F51: 637
B52: COLOMBIA | C52: 114 | E52: COLOMBIA | F52: 114
B53: COMOROS | C53: 720 | E53: COMOROS | F53: 720
B54: CONGO | C54: 709 | E54: CONGO | F54: 709
B55: CONGO, THE DEMOCRATIC REPUBLIC OF THE | C55: 96 | E55: CONGO, THE DEMOCRATIC REPUBLIC OF THE | F55: 96
B56: COOK ISLANDS | C56: 627 | E56: COOK ISLANDS | F56: 627
B57: COSTA RICA | C57: 804 | E57: COSTA RICA | F57: 804
B58: CÔTE D’IVOIRE | C58: 708 | E58: CÔTE D’IVOIRE | F58: 708
B59: CROATIA | C59: 515 | E59: CROATIA | F59: 515
B60: CUBA | C60: 807 | E60: CUBA | F60: 807
B61: CURACAO | C61: 823 | E61: CURACAO | F61: 823
B62: CYPRUS | C62: 12 | E62: CYPRUS | F62: 12
B63: CZECHIA | C63: 128 | E63: CZECHIA | F63: 128
B64: DENMARK | C64: 13 | E64: DENMARK | F64: 13
B65: DJIBOUTI | C65: 712 | E65: DJIBOUTI | F65: 712
B66: DOMINICA | C66: 107 | E66: DOMINICA | F66: 107
B67: DOMINICAN REPUBLIC | C67: 806 | E67: DOMINICAN REPUBLIC | F67: 806
B68: ECUADOR | C68: 123 | E68: ECUADOR | F68: 123
B69: EGYPT | C69: 110 | E69: EGYPT | F69: 110
B70: EL SALVADOR | C70: 802 | E70: EL SALVADOR | F70: 802
B71: EQUATORIAL GUINEA | C71: 718 | E71: EQUATORIAL GUINEA | F71: 718
B72: ERITREA | C72: 721 | E72: ERITREA | F72: 721
B73: ESTONIA | C73: 510 | E73: ESTONIA | F73: 510
B74: ESWATINI | C74: 102 | E74: ESWATINI | F74: 102
B75: ETHIOPIA | C75: 113 | E75: ETHIOPIA | F75: 113
B76: FALKLAND ISLANDS | C76: 81 | E76: FALKLAND ISLANDS | F76: 81
B77: FAROE ISLANDS | C77: 526 | E77: FAROE ISLANDS | F77: 526
B78: FIJI | C78: 619 | E78: FIJI | F78: 619
B79: FINLAND | C79: 14 | E79: FINLAND | F79: 14
B80: FRANCE | C80: 15 | E80: FRANCE | F80: 15
B81: FRENCH POLYNESIA | C81: 635 | E81: FRENCH POLYNESIA | F81: 635
B82: FRENCH SOUTHERN TERRITORIES | C82: 647 | E82: FRENCH SOUTHERN TERRITORIES | F82: 647
B83: GABON | C83: 124 | E83: GABON | F83: 124
B84: GAMBIA | C84: 16 | E84: GAMBIA | F84: 16
B85: GEORGIA | C85: 513 | E85: GEORGIA | F85: 513
B86: GERMANY | C86: 17 | E86: GERMANY | F86: 17
B87: GHANA | C87: 18 | E87: GHANA | F87: 18
B88: GIBRALTAR | C88: 19 | E88: GIBRALTAR | F88: 19
B89: GREECE | C89: 20 | E89: GREECE | F89: 20
B90: GREENLAND | C90: 819 | E90: GREENLAND | F90: 819
B91: GRENADA | C91: 816 | E91: GRENADA | F91: 816
B92: GUAM | C92: 642 | E92: GUAM | F92: 642
B93: GUATEMALA | C93: 800 | E93: GUATEMALA | F93: 800
B94: GUERNSEY | C94: 527 | E94: GUERNSEY | F94: 527
B95: GUINEA | C95: 707 | E95: GUINEA | F95: 707
... B102: HONG KONG | C102: 22 | E102: HONG KONG | F102: 22
B103: HUNGARY | C103: 130 | E103: HUNGARY | F103: 130
B104: ICELAND | C104: 94 | E104: ICELAND | F104: 94
B105: INDIA | C105: 23 | E105: INDIA | F105: 23
B106: INDONESIA | C106: 24 | E106: INDONESIA | F106: 24
B107: IRAN | C107: 25 | E107: IRAN | F107: 25
B108: IRAQ | C108: 26 | E108: IRAQ | F108: 26
B109: IRELAND | C109: 27 | E109: IRELAND | F109: 27
B110: ISLE OF MAN | C110: 524 | E110: ISLE OF MAN | F110: 524
B111: ISRAEL | C111: 28 | E111: ISRAEL | F111: 28
B112: ITALY | C112: 29 | E112: ITALY | F112: 29
B113: JAMAICA | C113: 30 | E113: JAMAICA | F113: 30
B114: JAPAN | C114: 31 | E114: JAPAN | F114: 31
B115: JERSEY | C115: 523 | E115: JERSEY | F115: 523
...

Sheet Industry List
A1: Options for the industry sector drop-down boxes
B2: Industry description | C2: Industry code
A3: 692 | B3: Accounting activities | C3: 692
A4: 731 | B4: Advertising | C4: 731
A5: 710 | B5: Architectural & engineering | C5: 710
A6: 641 | B6: Banks only (excl insurance & pension funding) | C6: 641
A7: 301 | B7: Building of ships and boats | C7: 301
A8: 642 | B8: Building Societies | C8: 642
A9: 420 | B9: Civil engineering | C9: 420
A10: 620 | B10: Computer programming, consultancy & related activities | C10: 620
A11: 410 | B11: Construction of buildings | C11: 410
A12: 900 | B12: Creative arts & entertainment | C12: 900
A13: 010 | B13: Crop & animal production, hunting & related service activities | C13: 010
A14: 970 | B14: Domestic personnel, households as employers | C14: 970
A15: 850 | B15: Education | C15: 850
A16: 780 | B16: Employment activities | C16: 780
A17: 060 | B17: Extraction of crude petroleum & natural gas | C17: 060
A18: 990 | B18: Extraterritorial organisations & bodies | C18: 990
A19: 644 | B19: Financial holding companies only | C19: 644
A20: 651 | B20: Financial services (life insurance only) | C20: 651
A21: 652 | B21: Financial services (non-life insurance, pension funding) | C21: 652
A22: 661 | B22: Financial services (security dealing only) | C22: 661
A23: 030 | B23: Fishing & aquaculture | C23: 030
A24: 560 | B24: Food & beverage service | C24: 560
A25: 020 | B25: Forestry & logging | C25: 020
A26: 920 | B26: Gambling & betting activities | C26: 920
A27: 701 | B27: Head office activities | C27: 701
A28: 860 | B28: Health activities (human only) | C28: 860
A29: 550 | B29: Hotels, hostels, camping and other accommodation | C29: 550
A30: 630 | B30: Information service activities | C30: 630
A31: 691 | B31: Legal activities | C31: 691
A32: 910 | B32: Libraries, archives, museums & other cultural activities | C32: 910
A33: 330 | B33: Machinery & Equipment repair, maintenance & installation | C33: 330
A34: 702 | B34: Management consultancy | C34: 702
A35: 303 | B35: Manufacture of air and spacecraft and related machinery | C35: 303
A36: 240 | B36: Manufacture of basic metals | C36: 240
A37: 210 | B37: Manufacture of basic pharmaceutical products & pharmaceutical preparations | C37: 210
... A68: 940 | B68: Membership organisations | C68: 940
A69: 090 | B69: Mining & oil gas extraction - support services only | C69: 090
A70: 080 | B70: Mining & quarrying - other | C70: 080
A71: 050 | B71: Mining of coal & lignite | C71: 050
A72: 070 | B72: Mining of metal ores | C72: 070
A73: 590 | B73: Motion picture, video & TV production, sound recording & publishing activities | C73: 590
A74: 450 | B74: Motor vehicles & motorcycles, wholesale & retail trade of, and accessories | C74: 450
A75: 643 | B75: Non financial holding companies only | C75: 643
A76: 820 | B76: Office administration, support & other business support activities | C76: 820
A77: 645 | B77: Other financial services (trust funds) | C77: 645
A78: 740 | B78: Other professional, scientific and technical activities | C78: 740
A79: 960 | B79: Personal service activities | C79: 960
A80: 530 | B80: Postal & courier activities | C80: 530
A81: 180 | B81: Printing & reproduction of recorded media | C81: 180
A82: 600 | B82: Programming & broadcasting (TV and radio) | C82: 600
A83: 840 | B83: Public administration, defence, compulsory social security | C83: 840
A84: 580 | B84: Publishing activities | C84: 580
... A110: 460 | B110: Wholesale trade (excl motor vehicles & motor cycles) | C110: 460

Sheet Output
A1: =Questionnaire!A1 -> 062:0105 | B1: resp
A2: 9020 | B2: =IF(ISBLANK(VLOOKUP(A2,Questionnaire!A:D,3,FALSE)),"",VLOOKUP(A2,Questionnaire!A:D,3,FALSE)) -> Colin McColin
A3: 9030 | B3: =IF(ISBLANK(VLOOKUP(A3,Questionnaire!A:D,3,FALSE)),"",VLOOKUP(A3,Questionnaire!A:D,3,FALSE)) -> 0111 1111111
A4: 9040 | B4: =IF(ISBLANK(VLOOKUP(A4,Questionnaire!A:D,3,FALSE)),"",VLOOKUP(A4,Questionnaire!A:D,3,FALSE))
A5: 9050 | B5: =IF(ISBLANK(VLOOKUP(A5,Questionnaire!A:D,3,FALSE)),"",VLOOKUP(A5,Questionnaire!A:D,3,FALSE)) -> colin.mccolin@doogle.com
A6: 0411 | B6: =IF(ISBLANK(VLOOKUP(A6,Questionnaire!A:D,4,FALSE)),"",VLOOKUP(A6,Questionnaire!A:D,4,FALSE))
A7: 0412 | B7: =IF(ISBLANK(VLOOKUP(A7,Questionnaire!A:D,4,FALSE)),"",VLOOKUP(A7,Questionnaire!A:D,4,FALSE))
A8: 0421 | B8: =IF(ISBLANK(VLOOKUP(A8,Questionnaire!A:D,4,FALSE)),"",VLOOKUP(A8,Questionnaire!A:D,4,FALSE)) -> 2021
A9: 0315 | B9: =IF(ISNA(VLOOKUP(VLOOKUP(A9,Questionnaire!A:D,4,FALSE),'CORA Encoding'!A2:B4,2,FALSE)),"",VLOOKUP(VLOOKUP(A9,Questionnaire!A:D,4,FALSE),'CORA Encoding'!A2:B4,2,FALSE)) -> 01
A10: 0218 | B10: =IF(ISBLANK(VLOOKUP(A10,Questionnaire!A:D,4,FALSE)),"",VLOOKUP(A10,Questionnaire!A:D,4,FALSE)) -> Acme Ltd
A11: 0219 | B11: =IF(ISNA(VLOOKUP(VLOOKUP(A11,Questionnaire!A:D,4,FALSE),'Country List'!B:C,2,FALSE)),"",VLOOKUP(VLOOKUP(A11,Questionnaire!A:D,4,FALSE),'Country List'!B:C,2,FALSE)) -> 638
A12: 0228 | B12: =IF(ISNA(VLOOKUP(VLOOKUP(A12,Questionnaire!A:D,4,FALSE),'Industry List'!B:C,2,FALSE)),"",VLOOKUP(VLOOKUP(A12,Questionnaire!A:D,4,FALSE),'Industry List'!B:C,2,FALSE)) -> 020
A13: 3733 | B13: =IF(ISBLANK(VLOOKUP(A13,Questionnaire!A:D,4,FALSE)),"",VLOOKUP(A13,Questionnaire!A:D,4,FALSE)) -> 100
A14: 0231 | B14: =IF(ISBLANK(VLOOKUP(A14,Questionnaire!A:D,4,FALSE)),"",VLOOKUP(A14,Questionnaire!A:D,4,FALSE)) -> 10
A15: 0232 | B15: =IF(ISBLANK(VLOOKUP(A15,Questionnaire!A:D,4,FALSE)),"",VLOOKUP(A15,Questionnaire!A:D,4,FALSE)) -> 1
A16: 4606 | B16: =IF(ISBLANK(VLOOKUP(A16,Questionnaire!A:D,4,FALSE)),"",VLOOKUP(A16,Questionnaire!A:D,4,FALSE)) -> 0
A17: 0003 | B17: =VLOOKUP(VLOOKUP(A17,Questionnaire!A:D,4,FALSE),'CORA Encoding'!O:P,2,FALSE) -> 00
A18: 9061 | B18: =IF(ISBLANK(VLOOKUP(A18,Questionnaire!A:D,4,FALSE)),"",VLOOKUP(A18,Questionnaire!A:D,4,FALSE))
A19: 9071 | B19: =IF(ISBLANK(VLOOKUP(A19,Questionnaire!A:D,4,FALSE)),"",VLOOKUP(A19,Questionnaire!A:D,4,FALSE))
A20: 0211 | B20: =IF(ISBLANK(VLOOKUP(A20,Questionnaire!A:KQ,4,FALSE)),"#",VLOOKUP(A20,Questionnaire!A:KQ,4,FALSE)) -> Parent Company A | C20: 1
A21: 0601 | B21: =IF(ISNA(VLOOKUP(VLOOKUP(A21,Questionnaire!A:KQ,4,FALSE),'CORA Encoding'!D:E,2,FALSE)),"#",VLOOKUP(VLOOKUP(A21,Questionnaire!A:KQ,4,FALSE),'CORA Encoding'!D:E,2,FALSE)) -> 00
A22: 0505 | B22: =IF(ISNA(VLOOKUP(VLOOKUP(A22,Questionnaire!A:KQ,4,FALSE),'CORA Encoding'!G:H,2,FALSE)),"#",VLOOKUP(VLOOKUP(A22,Questionnaire!A:KQ,4,FALSE),'CORA Encoding'!G:H,2,FALSE)) -> 01
A23: 0212 | B23: =IF(ISNA(VLOOKUP(VLOOKUP(A23,Questionnaire!A:KQ,4,FALSE),'Country List'!E:F,2,FALSE)),"#",VLOOKUP(VLOOKUP(A23,Questionnaire!A:KQ,4,FALSE),'Country List'!E:F,2,FALSE)) -> 9
A24: 0213 | B24: =IF(ISNA(VLOOKUP(VLOOKUP(A24,Questionnaire!A:KQ,4,FALSE),'Industry List'!B:C,2,FALSE)),"#",VLOOKUP(VLOOKUP(A24,Questionnaire!A:KQ,4,FALSE),'Industry List'!B:C,2,FALSE)) -> 644
A25: 3734 | B25: =IF(ISBLANK(VLOOKUP(A25,Questionnaire!A:KQ,4,FALSE)),"#",VLOOKUP(A25,Questionnaire!A:KQ,4,FALSE)) -> 100
A26: 0214 | B26: =IF(ISBLANK(VLOOKUP(A26,Questionnaire!A:KQ,4,FALSE)),"#",VLOOKUP(A26,Questionnaire!A:KQ,4,FALSE)) -> 100
A27: 0602 | B27: =IF(ISNA(VLOOKUP(VLOOKUP(A27,Questionnaire!A:KQ,4,FALSE),'CORA Encoding'!J:K,2,FALSE)),"#",VLOOKUP(VLOOKUP(A27,Questionnaire!A:KQ,4,FALSE),'CORA Encoding'!J:K,2,FALSE)) -> 1
A28: 1011 | B28: =IF(ISBLANK(VLOOKUP(A28,Questionnaire!A:KQ,4,FALSE)),"#",VLOOKUP(A28,Questionnaire!A:KQ,4,FALSE)) -> #
A29: 4111 | B29: =IF(ISBLANK(VLOOKUP(A29,Questionnaire!A:KQ,4,FALSE)),"#",VLOOKUP(A29,Questionnaire!A:KQ,4,FALSE)) -> #
A30: 4112 | B30: =IF(ISBLANK(VLOOKUP(A30,Questionnaire!A:KQ,4,FALSE)),"#",VLOOKUP(A30,Questionnaire!A:KQ,4,FALSE)) -> #
A31: 4113 | B31: =IF(ISBLANK(VLOOKUP(A31,Questionnaire!A:KQ,4,FALSE)),"#",VLOOKUP(A31,Questionnaire!A:KQ,4,FALSE)) -> #
A32: 4114 | B32: =IF(ISBLANK(VLOOKUP(A32,Questionnaire!A:KQ,4,FALSE)),"#",VLOOKUP(A32,Questionnaire!A:KQ,4,FALSE)) -> #
A33: 4115 | B33: =IF(ISBLANK(VLOOKUP(A33,Questionnaire!A:KQ,4,FALSE)),"#",VLOOKUP(A33,Questionnaire!A:KQ,4,FALSE)) -> #
A34: 4116 | B34: =IF(ISBLANK(VLOOKUP(A34,Questionnaire!A:KQ,4,FALSE)),"#",VLOOKUP(A34,Questionnaire!A:KQ,4,FALSE)) -> #
A35: 4117 | B35: =IF(ISBLANK(VLOOKUP(A35,Questionnaire!A:KQ,4,FALSE)),"#",VLOOKUP(A35,Questionnaire!A:KQ,4,FALSE)) -> #
A36: 4118 | B36: =IF(ISBLANK(VLOOKUP(A36,Questionnaire!A:KQ,4,FALSE)),"#",VLOOKUP(A36,Questionnaire!A:KQ,4,FALSE)) -> #
A37: 4119 | B37: =IF(ISBLANK(VLOOKUP(A37,Questionnaire!A:KQ,4,FALSE)),"#",VLOOKUP(A37,Questionnaire!A:KQ,4,FALSE)) -> #
A38: 4130 | B38: =IF(ISBLANK(VLOOKUP(A38,Questionnaire!A:KQ,4,FALSE)),"#",VLOOKUP(A38,Questionnaire!A:KQ,4,FALSE)) -> #
A39: 4140 | B39: =IF(ISBLANK(VLOOKUP(A39,Questionnaire!A:KQ,4,FALSE)),"#",VLOOKUP(A39,Questionnaire!A:KQ,4,FALSE)) -> #
... A49: 3725 | B49: =IF(ISBLANK(VLOOKUP(A49,Questionnaire!A:KQ,4,FALSE)),"#",VLOOKUP(A49,Questionnaire!A:KQ,4,FALSE)) -> #
A50: 0605 | B50: =IF(ISNA(VLOOKUP(VLOOKUP(A50,Questionnaire!A:KQ,4,FALSE),'CORA Encoding'!M:N,2,FALSE)),"#",VLOOKUP(VLOOKUP(A50,Questionnaire!A:KQ,4,FALSE),'CORA Encoding'!M:N,2,FALSE)) -> 01
A51: 3191 | B51: =IF(ISBLANK(VLOOKUP(A51,Questionnaire!A:KQ,4,FALSE)),"#",VLOOKUP(A51,Questionnaire!A:KQ,4,FALSE)) -> #
A52: 3726 | B52: =IF(ISBLANK(VLOOKUP(A52,Questionnaire!A:KQ,4,FALSE)),"#",VLOOKUP(A52,Questionnaire!A:KQ,4,FALSE)) -> #
A53: 3192 | B53: =IF(ISBLANK(VLOOKUP(A53,Questionnaire!A:KQ,4,FALSE)),"#",VLOOKUP(A53,Questionnaire!A:KQ,4,FALSE)) -> #
A54: 3727 | B54: =IF(ISBLANK(VLOOKUP(A54,Questionnaire!A:KQ,4,FALSE)),"#",VLOOKUP(A54,Questionnaire!A:KQ,4,FALSE)) -> #
A55: 2111 | B55: =IF(ISBLANK(VLOOKUP(A55,Questionnaire!A:KQ,4,FALSE)),"#",VLOOKUP(A55,Questionnaire!A:KQ,4,FALSE)) -> #
A56: 4201 | B56: =IF(ISBLANK(VLOOKUP(A56,Questionnaire!A:KQ,4,FALSE)),"#",VLOOKUP(A56,Questionnaire!A:KQ,4,FALSE)) -> #
A57: 4202 | B57: =IF(ISBLANK(VLOOKUP(A57,Questionnaire!A:KQ,4,FALSE)),"#",VLOOKUP(A57,Questionnaire!A:KQ,4,FALSE)) -> #
A58: 4203 | B58: =IF(ISBLANK(VLOOKUP(A58,Questionnaire!A:KQ,4,FALSE)),"#",VLOOKUP(A58,Questionnaire!A:KQ,4,FALSE)) -> #
A59: 4204 | B59: =IF(ISBLANK(VLOOKUP(A59,Questionnaire!A:KQ,4,FALSE)),"#",VLOOKUP(A59,Questionnaire!A:KQ,4,FALSE)) -> #
A60: 4205 | B60: =IF(ISBLANK(VLOOKUP(A60,Questionnaire!A:KQ,4,FALSE)),"#",VLOOKUP(A60,Questionnaire!A:KQ,4,FALSE)) -> #
A61: 4211 | B61: =IF(ISBLANK(VLOOKUP(A61,Questionnaire!A:KQ,4,FALSE)),"#",VLOOKUP(A61,Questionnaire!A:KQ,4,FALSE)) -> #
A62: 4212 | B62: =IF(ISBLANK(VLOOKUP(A62,Questionnaire!A:KQ,4,FALSE)),"#",VLOOKUP(A62,Questionnaire!A:KQ,4,FALSE)) -> #
... A146: 4506 | B146: =IF(ISBLANK(VLOOKUP(A146,Questionnaire!A:KQ,4,FALSE)),"#",VLOOKUP(A146,Questionnaire!A:KQ,4,FALSE)) -> 0
A147: 0211 | B147: =IF(ISBLANK(VLOOKUP(A147,Questionnaire!A:KQ,5,FALSE)),"#",VLOOKUP(A147,Questionnaire!A:KQ,5,FALSE)) -> # | C147: 2
A148: 0601 | B148: =IF(ISNA(VLOOKUP(VLOOKUP(A148,Questionnaire!A:KQ,5,FALSE),'CORA Encoding'!D:E,2,FALSE)),"#",VLOOKUP(VLOOKUP(A148,Questionnaire!A:KQ,5,FALSE),'CORA Encoding'!D:E,2,FALSE)) -> #
A149: 0505 | B149: =IF(ISNA(VLOOKUP(VLOOKUP(A149,Questionnaire!A:KQ,5,FALSE),'CORA Encoding'!G:H,2,FALSE)),"#",VLOOKUP(VLOOKUP(A149,Questionnaire!A:KQ,5,FALSE),'CORA Encoding'!G:H,2,FALSE)) -> #
A150: 0212 | B150: =IF(ISNA(VLOOKUP(VLOOKUP(A150,Questionnaire!A:KQ,5,FALSE),'Country List'!E:F,2,FALSE)),"#",VLOOKUP(VLOOKUP(A150,Questionnaire!A:KQ,5,FALSE),'Country List'!E:F,2,FALSE)) -> #
A151: 0213 | B151: =IF(ISNA(VLOOKUP(VLOOKUP(A151,Questionnaire!A:KQ,5,FALSE),'Industry List'!B:C,2,FALSE)),"#",VLOOKUP(VLOOKUP(A151,Questionnaire!A:KQ,5,FALSE),'Industry List'!B:C,2,FALSE)) -> #
A152: 3734 | B152: =IF(ISBLANK(VLOOKUP(A152,Questionnaire!A:KQ,5,FALSE)),"#",VLOOKUP(A152,Questionnaire!A:KQ,5,FALSE)) -> #
A153: 0214 | B153: =IF(ISBLANK(VLOOKUP(A153,Questionnaire!A:KQ,5,FALSE)),"#",VLOOKUP(A153,Questionnaire!A:KQ,5,FALSE)) -> #
A154: 0602 | B154: =IF(ISNA(VLOOKUP(VLOOKUP(A154,Questionnaire!A:KQ,5,FALSE),'CORA Encoding'!J:K,2,FALSE)),"#",VLOOKUP(VLOOKUP(A154,Questionnaire!A:KQ,5,FALSE),'CORA Encoding'!J:K,2,FALSE)) -> #
A155: 1011 | B155: =IF(ISBLANK(VLOOKUP(A155,Questionnaire!A:KQ,5,FALSE)),"#",VLOOKUP(A155,Questionnaire!A:KQ,5,FALSE)) -> #
A156: 4111 | B156: =IF(ISBLANK(VLOOKUP(A156,Questionnaire!A:KQ,5,FALSE)),"#",VLOOKUP(A156,Questionnaire!A:KQ,5,FALSE)) -> #
A157: 4112 | B157: =IF(ISBLANK(VLOOKUP(A157,Questionnaire!A:KQ,5,FALSE)),"#",VLOOKUP(A157,Questionnaire!A:KQ,5,FALSE)) -> #
A158: 4113 | B158: =IF(ISBLANK(VLOOKUP(A158,Questionnaire!A:KQ,5,FALSE)),"#",VLOOKUP(A158,Questionnaire!A:KQ,5,FALSE)) -> #
A159: 4114 | B159: =IF(ISBLANK(VLOOKUP(A159,Questionnaire!A:KQ,5,FALSE)),"#",VLOOKUP(A159,Questionnaire!A:KQ,5,FALSE)) -> #
A160: 4115 | B160: =IF(ISBLANK(VLOOKUP(A160,Questionnaire!A:KQ,5,FALSE)),"#",VLOOKUP(A160,Questionnaire!A:KQ,5,FALSE)) -> #
A161: 4116 | B161: =IF(ISBLANK(VLOOKUP(A161,Questionnaire!A:KQ,5,FALSE)),"#",VLOOKUP(A161,Questionnaire!A:KQ,5,FALSE)) -> #
A162: 4117 | B162: =IF(ISBLANK(VLOOKUP(A162,Questionnaire!A:KQ,5,FALSE)),"#",VLOOKUP(A162,Questionnaire!A:KQ,5,FALSE)) -> #
A163: 4118 | B163: =IF(ISBLANK(VLOOKUP(A163,Questionnaire!A:KQ,5,FALSE)),"#",VLOOKUP(A163,Questionnaire!A:KQ,5,FALSE)) -> #
A164: 4119 | B164: =IF(ISBLANK(VLOOKUP(A164,Questionnaire!A:KQ,5,FALSE)),"#",VLOOKUP(A164,Questionnaire!A:KQ,5,FALSE)) -> #
A165: 4130 | B165: =IF(ISBLANK(VLOOKUP(A165,Questionnaire!A:KQ,5,FALSE)),"#",VLOOKUP(A165,Questionnaire!A:KQ,5,FALSE)) -> #
A166: 4140 | B166: =IF(ISBLANK(VLOOKUP(A166,Questionnaire!A:KQ,5,FALSE)),"#",VLOOKUP(A166,Questionnaire!A:KQ,5,FALSE)) -> #
... A176: 3725 | B176: =IF(ISBLANK(VLOOKUP(A176,Questionnaire!A:KQ,5,FALSE)),"#",VLOOKUP(A176,Questionnaire!A:KQ,5,FALSE)) -> #
A177: 0605 | B177: =IF(ISNA(VLOOKUP(VLOOKUP(A177,Questionnaire!A:KQ,5,FALSE),'CORA Encoding'!M:N,2,FALSE)),"#",VLOOKUP(VLOOKUP(A177,Questionnaire!A:KQ,5,FALSE),'CORA Encoding'!M:N,2,FALSE)) -> #
A178: 3191 | B178: =IF(ISBLANK(VLOOKUP(A178,Questionnaire!A:KQ,5,FALSE)),"#",VLOOKUP(A178,Questionnaire!A:KQ,5,FALSE)) -> #
A179: 3726 | B179: =IF(ISBLANK(VLOOKUP(A179,Questionnaire!A:KQ,5,FALSE)),"#",VLOOKUP(A179,Questionnaire!A:KQ,5,FALSE)) -> #
A180: 3192 | B180: =IF(ISBLANK(VLOOKUP(A180,Questionnaire!A:KQ,5,FALSE)),"#",VLOOKUP(A180,Questionnaire!A:KQ,5,FALSE)) -> #
A181: 3727 | B181: =IF(ISBLANK(VLOOKUP(A181,Questionnaire!A:KQ,5,FALSE)),"#",VLOOKUP(A181,Questionnaire!A:KQ,5,FALSE)) -> #
A182: 2111 | B182: =IF(ISBLANK(VLOOKUP(A182,Questionnaire!A:KQ,5,FALSE)),"#",VLOOKUP(A182,Questionnaire!A:KQ,5,FALSE)) -> #
A183: 4201 | B183: =IF(ISBLANK(VLOOKUP(A183,Questionnaire!A:KQ,5,FALSE)),"#",VLOOKUP(A183,Questionnaire!A:KQ,5,FALSE)) -> #
A184: 4202 | B184: =IF(ISBLANK(VLOOKUP(A184,Questionnaire!A:KQ,5,FALSE)),"#",VLOOKUP(A184,Questionnaire!A:KQ,5,FALSE)) -> #
A185: 4203 | B185: =IF(ISBLANK(VLOOKUP(A185,Questionnaire!A:KQ,5,FALSE)),"#",VLOOKUP(A185,Questionnaire!A:KQ,5,FALSE)) -> #
A186: 4204 | B186: =IF(ISBLANK(VLOOKUP(A186,Questionnaire!A:KQ,5,FALSE)),"#",VLOOKUP(A186,Questionnaire!A:KQ,5,FALSE)) -> #
A187: 4205 | B187: =IF(ISBLANK(VLOOKUP(A187,Questionnaire!A:KQ,5,FALSE)),"#",VLOOKUP(A187,Questionnaire!A:KQ,5,FALSE)) -> #
A188: 4211 | B188: =IF(ISBLANK(VLOOKUP(A188,Questionnaire!A:KQ,5,FALSE)),"#",VLOOKUP(A188,Questionnaire!A:KQ,5,FALSE)) -> #
A189: 4212 | B189: =IF(ISBLANK(VLOOKUP(A189,Questionnaire!A:KQ,5,FALSE)),"#",VLOOKUP(A189,Questionnaire!A:KQ,5,FALSE)) -> #
... A273: 4506 | B273: =IF(ISBLANK(VLOOKUP(A273,Questionnaire!A:KQ,5,FALSE)),"#",VLOOKUP(A273,Questionnaire!A:KQ,5,FALSE)) -> #
A274: 0211 | B274: =IF(ISBLANK(VLOOKUP(A274,Questionnaire!A:KQ,6,FALSE)),"#",VLOOKUP(A274,Questionnaire!A:KQ,6,FALSE)) -> # | C274: 3
A275: 0601 | B275: =IF(ISNA(VLOOKUP(VLOOKUP(A275,Questionnaire!A:KQ,6,FALSE),'CORA Encoding'!D:E,2,FALSE)),"#",VLOOKUP(VLOOKUP(A275,Questionnaire!A:KQ,6,FALSE),'CORA Encoding'!D:E,2,FALSE)) -> #
A276: 0505 | B276: =IF(ISNA(VLOOKUP(VLOOKUP(A276,Questionnaire!A:KQ,6,FALSE),'CORA Encoding'!G:H,2,FALSE)),"#",VLOOKUP(VLOOKUP(A276,Questionnaire!A:KQ,6,FALSE),'CORA Encoding'!G:H,2,FALSE)) -> #
A277: 0212 | B277: =IF(ISNA(VLOOKUP(VLOOKUP(A277,Questionnaire!A:KQ,6,FALSE),'Country List'!E:F,2,FALSE)),"#",VLOOKUP(VLOOKUP(A277,Questionnaire!A:KQ,6,FALSE),'Country List'!E:F,2,FALSE)) -> #
A278: 0213 | B278: =IF(ISNA(VLOOKUP(VLOOKUP(A278,Questionnaire!A:KQ,6,FALSE),'Industry List'!B:C,2,FALSE)),"#",VLOOKUP(VLOOKUP(A278,Questionnaire!A:KQ,6,FALSE),'Industry List'!B:C,2,FALSE)) -> #
A279: 3734 | B279: =IF(ISBLANK(VLOOKUP(A279,Questionnaire!A:KQ,6,FALSE)),"#",VLOOKUP(A279,Questionnaire!A:KQ,6,FALSE)) -> #
A280: 0214 | B280: =IF(ISBLANK(VLOOKUP(A280,Questionnaire!A:KQ,6,FALSE)),"#",VLOOKUP(A280,Questionnaire!A:KQ,6,FALSE)) -> #
A281: 0602 | B281: =IF(ISNA(VLOOKUP(VLOOKUP(A281,Questionnaire!A:KQ,6,FALSE),'CORA Encoding'!J:K,2,FALSE)),"#",VLOOKUP(VLOOKUP(A281,Questionnaire!A:KQ,6,FALSE),'CORA Encoding'!J:K,2,FALSE)) -> #
A282: 1011 | B282: =IF(ISBLANK(VLOOKUP(A282,Questionnaire!A:KQ,6,FALSE)),"#",VLOOKUP(A282,Questionnaire!A:KQ,6,FALSE)) -> #
A283: 4111 | B283: =IF(ISBLANK(VLOOKUP(A283,Questionnaire!A:KQ,6,FALSE)),"#",VLOOKUP(A283,Questionnaire!A:KQ,6,FALSE)) -> #
A284: 4112 | B284: =IF(ISBLANK(VLOOKUP(A284,Questionnaire!A:KQ,6,FALSE)),"#",VLOOKUP(A284,Questionnaire!A:KQ,6,FALSE)) -> #
...

Sheet CORA Encoding
A1: 0312 | D1: 0601 | G1: 0505 | J1: 0602 | M1: 0605 | O1: 0003
A2: N/A (branch) | B2: -1 | D2: Foreign Parent | E2: 00 | G2: No | H2: 00 | J2: Affiliate | K2: 1 | M2: Unquoted | N2: 01 | O2: 0 | P2: 00
A3: No (unquoted affiliate) | B3: 01 | D3: Head Office | E3: 00 | G3: Yes | H3: 01 | J3: Branch | K3: 2 | M3: Quoted | N3: 10 | O3: 1 | P3: 10
A4: Yes (quoted affiliate) | B4: 10 | D4: Fellow Enterprise | E4: 10 | J4: Fellow Enterprise | K4: 3
